Workbook

Sheet autozliczanie (2025-12)
B1: Tytuł | E1: RAZEM | H1: Histmag (szacunkowy) | K1: sieci | N1: Virtualo | Q1: Empik | T1: Publio | W1: Legimi | Z1: Nexto | AC1: Woblink | AF1: Azymut | AI1: Ebookpoint | AL1: Nasbi | AO1: Storytel | AR1: Audioteka | AU1: Bookbeat
H2: kwoty są szacunkowe
A4: 9788365156365 | B4: Azja we krwi, Konflikty – zbrodnie – ludobójstwo | E4: =H4+K4 -> 1 | F4: =I4+L4 -> 1.95 | H4: =SUMIF(konwertery!A$2:A$300,A4,Histmag!C$2:C$300) -> 0 | I4: =SUMIF(konwertery!A$2:A$300,A4,konwertery!B$2:B$300) * 0.97 -> 0 | K4: =N4+Q4+T4+W4+Z4+AC4+AF4+AI4+AL4+AO4+AR4+AU4 -> 1 | L4: =O4+R4+U4+X4+AA4+AD4+AG4+AJ4+AM4+AP4+AS4+AV4 -> 1.95 | N4: =SUMIF(konwertery!C$2:C$300,A4,Virtualo!L$2:L$300) -> 0 | O4: =(SUMIF(konwertery!C$2:C$300,A4,Virtualo!P$2:P$300)) -> 0 | Q4: =SUMIF(konwertery!D$2:D$300,A4,Empik!M$2:M$300) -> 0 | R4: =SUMIF(konwertery!D$2:D$300,A4,Empik!N$2:N$300) -> 0 | T4: =SUMIF(konwertery!E$2:E$300,A4,Publio!P$2:P$300) -> 0 | U4: =SUMIF(konwertery!E$2:E$300,A4,konwertery!F$2:F$300) -> 0 | W4: =SUMIF(Legimi!D$2:D$300,A4,Legimi!G$2:G$300) -> 0 | X4: =SUMIF(Legimi!D$2:D$300,A4,Legimi!H$2:H$300) -> 0 | Z4: =SUMIF(konwertery!G$2:G$302,A4,Nexto!J$2:J$283) -> 0 | AA4: =SUMIF(konwertery!G$2:G$302,A4,Nexto!N$2:P$302) -> 0 | AC4: =SUMIF(Woblink!E$14:E$314,A4,Woblink!I$14:I$314) -> 0 | AD4: =SUMIF(Woblink!E$14:E$314,A4,konwertery!R$2:R$300) -> 0 | AF4: =SUM(SUMIF(konwertery!I$2:I$300,A4,Azymut!H$2:H$298),(SUMIF(konwertery!S$2:S$300,A4,AzymutB!H$2:H300)*2)) -> 0 | AG4: =SUM(SUMIF(konwertery!I$2:I$300,A4,konwertery!J$2:J$300),SUMIF(konwertery!S$2:S$300,A4,konwertery!T$2:T$300)) -> 0 | AI4: =SUMIF(konwertery!K$2:K$300,A4,Ebookpoint!F$14:F$312) -> 0 | AJ4: =SUMIF(konwertery!K$2:K$300,A4,Ebookpoint!M$14:M$312) -> 0 | AL4: =SUMIF(konwertery!L$2:L$300,A4,Nasbi!F$14:F$312) -> 0 | AM4: =SUMIF(konwertery!L$2:L$300,A4,Nasbi!K$14:K$312) -> 0 | AO4: =SUMIF(StorytelE!C$2:C$300,A4,konwertery!M$2:M$300)+SUMIF(StorytelA!C$2:C$300,A4,konwertery!N$2:N$300) -> 1 | AP4: =SUMIF(StorytelE!C$2:C$300,A4,konwertery!O$2:O$300)+SUMIF(StorytelA!C$2:C$300,A4,konwertery!P$2:P$300) -> 1.95 | AR4: =SUMIF(konwertery!U$2:U$300,A4,Audioteka!E$4:E$302) -> 0 | AS4: =SUMIF(konwertery!U$2:U$300,A4,Audioteka!O$4:O$302) -> 0 | AU4: =SUMIF(Bookbeat!A$9:A$309,A4,Bookbeat!H$9:H$309) -> 0 | AV4: =SUMIF(Bookbeat!A$9:A$309,A4,Bookbeat!L$9:L$309) -> 0
A5: 9788393463077 | B5: Batoh 1652 – Wiedeń 1683, Od kompromitacji do wiktorii | E5: =H5+K5 -> 3 | F5: =I5+L5 -> 21.4952 | H5: =SUMIF(konwertery!A$2:A$300,A5,Histmag!C$2:C$300) -> 3 | I5: =SUMIF(konwertery!A$2:A$300,A5,konwertery!B$2:B$300) * 0.97 -> 21.4952 | K5: =N5+Q5+T5+W5+Z5+AC5+AF5+AI5+AL5+AO5+AR5+AU5 -> 0 | L5: =O5+R5+U5+X5+AA5+AD5+AG5+AJ5+AM5+AP5+AS5+AV5 -> 0 | N5: =SUMIF(konwertery!C$2:C$300,A5,Virtualo!L$2:L$300) -> 0 | O5: =(SUMIF(konwertery!C$2:C$300,A5,Virtualo!P$2:P$300)) -> 0 | Q5: =SUMIF(konwertery!D$2:D$300,A5,Empik!M$2:M$300) -> 0 | R5: =SUMIF(konwertery!D$2:D$300,A5,Empik!N$2:N$300) -> 0 | T5: =SUMIF(konwertery!E$2:E$300,A5,Publio!P$2:P$300) -> 0 | U5: =SUMIF(konwertery!E$2:E$300,A5,konwertery!F$2:F$300) -> 0 | W5: =SUMIF(Legimi!D$2:D$300,A5,Legimi!G$2:G$300) -> 0 | X5: =SUMIF(Legimi!D$2:D$300,A5,Legimi!H$2:H$300) -> 0 | Z5: =SUMIF(konwertery!G$2:G$302,A5,Nexto!J$2:J$283) -> 0 | AA5: =SUMIF(konwertery!G$2:G$302,A5,Nexto!N$2:P$302) -> 0 | AC5: =SUMIF(Woblink!E$9:E$309,A5,Woblink!I$9:I$309) -> 0 | AD5: =SUMIF(Woblink!E$14:E$314,A5,konwertery!R$2:R$300) -> 0 | AF5: =SUM(SUMIF(konwertery!I$2:I$300,A5,Azymut!H$2:H$298),(SUMIF(konwertery!S$2:S$300,A5,AzymutB!H$2:H301)*2)) -> 0 | AG5: =SUM(SUMIF(konwertery!I$2:I$300,A5,konwertery!J$2:J$300),SUMIF(konwertery!S$2:S$300,A5,konwertery!T$2:T$300)) -> 0 | AI5: =SUMIF(konwertery!K$2:K$300,A5,Ebookpoint!F$14:F$312) -> 0 | AJ5: =SUMIF(konwertery!K$2:K$300,A5,Ebookpoint!M$14:M$312) -> 0 | AL5: =SUMIF(konwertery!L$2:L$300,A5,Nasbi!F$14:F$312) -> 0 | AM5: =SUMIF(konwertery!L$2:L$300,A5,Nasbi!K$14:K$312) -> 0 | AO5: =SUMIF(StorytelE!C$2:C$300,A5,konwertery!M$2:M$300)+SUMIF(StorytelA!C$2:C$300,A5,konwertery!N$2:N$300) -> 0 | AP5: =SUMIF(StorytelE!C$2:C$300,A5,konwertery!O$2:O$300)+SUMIF(StorytelA!C$2:C$300,A5,konwertery!P$2:P$300) -> 0 | AR5: =SUMIF(konwertery!U$2:U$300,A5,Audioteka!E$4:E$302) -> 0 | AS5: =SUMIF(konwertery!U$2:U$300,A5,Audioteka!O$4:O$302) -> 0 | AU5: =SUMIF(Bookbeat!A$9:A$309,A5,Bookbeat!H$9:H$309) -> 0 | AV5: =SUMIF(Bookbeat!A$9:A$309,A5,Bookbeat!L$9:L$309) -> 0
A6: 9788365156068 | B6: Bohaterowie popkultury: od Robin Hooda do Rambo | E6: =H6+K6 -> 0 | F6: =I6+L6 -> 0 | H6: =SUMIF(konwertery!A$2:A$300,A6,Histmag!C$2:C$300) -> 0 | I6: =SUMIF(konwertery!A$2:A$300,A6,konwertery!B$2:B$300) * 0.97 -> 0 | K6: =N6+Q6+T6+W6+Z6+AC6+AF6+AI6+AL6+AO6+AR6+AU6 -> 0 | L6: =O6+R6+U6+X6+AA6+AD6+AG6+AJ6+AM6+AP6+AS6+AV6 -> 0 | N6: =SUMIF(konwertery!C$2:C$300,A6,Virtualo!L$2:L$300) -> 0 | O6: =(SUMIF(konwertery!C$2:C$300,A6,Virtualo!P$2:P$300)) -> 0 | Q6: =SUMIF(konwertery!D$2:D$300,A6,Empik!M$2:M$300) -> 0 | R6: =SUMIF(konwertery!D$2:D$300,A6,Empik!N$2:N$300) -> 0 | T6: =SUMIF(konwertery!E$2:E$300,A6,Publio!P$2:P$300) -> 0 | U6: =SUMIF(konwertery!E$2:E$300,A6,konwertery!F$2:F$300) -> 0 | W6: =SUMIF(Legimi!D$2:D$300,A6,Legimi!G$2:G$300) -> 0 | X6: =SUMIF(Legimi!D$2:D$300,A6,Legimi!H$2:H$300) -> 0 | Z6: =SUMIF(konwertery!G$2:G$302,A6,Nexto!J$2:J$283) -> 0 | AA6: =SUMIF(konwertery!G$2:G$302,A6,Nexto!N$2:P$302) -> 0 | AC6: =SUMIF(Woblink!E$9:E$309,A6,Woblink!I$9:I$309) -> 0 | AD6: =SUMIF(Woblink!E$14:E$314,A6,konwertery!R$2:R$300) -> 0 | AF6: =SUM(SUMIF(konwertery!I$2:I$300,A6,Azymut!H$2:H$298),(SUMIF(konwertery!S$2:S$300,A6,AzymutB!H$2:H302)*2)) -> 0 | AG6: =SUM(SUMIF(konwertery!I$2:I$300,A6,konwertery!J$2:J$300),SUMIF(konwertery!S$2:S$300,A6,konwertery!T$2:T$300)) -> 0 | AI6: =SUMIF(konwertery!K$2:K$300,A6,Ebookpoint!F$14:F$312) -> 0 | AJ6: =SUMIF(konwertery!K$2:K$300,A6,Ebookpoint!M$14:M$312) -> 0 | AL6: =SUMIF(konwertery!L$2:L$300,A6,Nasbi!F$14:F$312) -> 0 | AM6: =SUMIF(konwertery!L$2:L$300,A6,Nasbi!K$14:K$312) -> 0 | AO6: =SUMIF(StorytelE!C$2:C$300,A6,konwertery!M$2:M$300)+SUMIF(StorytelA!C$2:C$300,A6,konwertery!N$2:N$300) -> 0 | AP6: =SUMIF(StorytelE!C$2:C$300,A6,konwertery!O$2:O$300)+SUMIF(StorytelA!C$2:C$300,A6,konwertery!P$2:P$300) -> 0 | AR6: =SUMIF(konwertery!U$2:U$300,A6,Audioteka!E$4:E$302) -> 0 | AS6: =SUMIF(konwertery!U$2:U$300,A6,Audioteka!O$4:O$302) -> 0 | AU6: =SUMIF(Bookbeat!A$9:A$309,A6,Bookbeat!H$9:H$309) -> 0 | AV6: =SUMIF(Bookbeat!A$9:A$309,A6,Bookbeat!L$9:L$309) -> 0
A7: 9788365156754 | B7: Cywilizacja śmierci. Rosyjski kolonializm na Wschodzie | E7: =H7+K7 -> 6 | F7: =I7+L7 -> 60.2103 | H7: =SUMIF(konwertery!A$2:A$300,A7,Histmag!C$2:C$300) -> 3 | I7: =SUMIF(konwertery!A$2:A$300,A7,konwertery!B$2:B$300) * 0.97 -> 32.9703 | K7: =N7+Q7+T7+W7+Z7+AC7+AF7+AI7+AL7+AO7+AR7+AU7 -> 3 | L7: =O7+R7+U7+X7+AA7+AD7+AG7+AJ7+AM7+AP7+AS7+AV7 -> 27.24 | N7: =SUMIF(konwertery!C$2:C$300,A7,Virtualo!L$2:L$300) -> 0 | O7: =(SUMIF(konwertery!C$2:C$300,A7,Virtualo!P$2:P$300)) -> 0 | Q7: =SUMIF(konwertery!D$2:D$300,A7,Empik!M$2:M$300) -> 0 | R7: =SUMIF(konwertery!D$2:D$300,A7,Empik!N$2:N$300) -> 0 | T7: =SUMIF(konwertery!E$2:E$300,A7,Publio!P$2:P$300) -> 0 | U7: =SUMIF(konwertery!E$2:E$300,A7,konwertery!F$2:F$300) -> 0 | W7: =SUMIF(Legimi!D$2:D$300,A7,Legimi!G$2:G$300) -> 0 | X7: =SUMIF(Legimi!D$2:D$300,A7,Legimi!H$2:H$300) -> 0 | Z7: =SUMIF(konwertery!G$2:G$302,A7,Nexto!J$2:J$283) -> 0 | AA7: =SUMIF(konwertery!G$2:G$302,A7,Nexto!N$2:P$302) -> 0 | AC7: =SUMIF(Woblink!E$14:E$314,A7,Woblink!I$14:I$314) -> 0 | AD7: =SUMIF(Woblink!E$14:E$314,A7,konwertery!R$2:R$300) -> 0 | AF7: =SUM(SUMIF(konwertery!I$2:I$300,A7,Azymut!H$2:H$298),(SUMIF(konwertery!S$2:S$300,A7,AzymutB!H$2:H303)*2)) -> 0 | AG7: =SUM(SUMIF(konwertery!I$2:I$300,A7,konwertery!J$2:J$300),SUMIF(konwertery!S$2:S$300,A7,konwertery!T$2:T$300)) -> 0 | AI7: =SUMIF(konwertery!K$2:K$300,A7,Ebookpoint!F$14:F$312) -> 3 | AJ7: =SUMIF(konwertery!K$2:K$300,A7,Ebookpoint!M$14:M$312) -> 27.24 | AL7: =SUMIF(konwertery!L$2:L$300,A7,Nasbi!F$14:F$312) -> 0 | AM7: =SUMIF(konwertery!L$2:L$300,A7,Nasbi!K$14:K$312) -> 0 | AO7: =SUMIF(StorytelE!C$2:C$300,A7,konwertery!M$2:M$300)+SUMIF(StorytelA!C$2:C$300,A7,konwertery!N$2:N$300) -> 0 | AP7: =SUMIF(StorytelE!C$2:C$300,A7,konwertery!O$2:O$300)+SUMIF(StorytelA!C$2:C$300,A7,konwertery!P$2:P$300) -> 0 | AR7: =SUMIF(konwertery!U$2:U$300,A7,Audioteka!E$4:E$302) -> 0 | AS7: =SUMIF(konwertery!U$2:U$300,A7,Audioteka!O$4:O$302) -> 0 | AU7: =SUMIF(Bookbeat!A$9:A$309,A7,Bookbeat!H$9:H$309) -> 0 | AV7: =SUMIF(Bookbeat!A$9:A$309,A7,Bookbeat!L$9:L$309) -> 0
A8: 9788365156808 | B8: Cywilizacja śmierci. Rosyjski kolonializm na Wschodzie (audio) | E8: =H8+K8 -> 75 | F8: =I8+L8 -> 113.45 | H8: =SUMIF(konwertery!A$2:A$300,A8,Histmag!C$2:C$300) -> 0 | I8: =SUMIF(konwertery!A$2:A$300,A8,konwertery!B$2:B$300) * 0.97 -> 0 | K8: =N8+Q8+T8+W8+Z8+AC8+AF8+AI8+AL8+AO8+AR8+AU8 -> 75 | L8: =O8+R8+U8+X8+AA8+AD8+AG8+AJ8+AM8+AP8+AS8+AV8 -> 113.45 | N8: =SUMIF(konwertery!C$2:C$300,A8,Virtualo!L$2:L$300) -> 0 | O8: =(SUMIF(konwertery!C$2:C$300,A8,Virtualo!P$2:P$300)) -> 0 | Q8: =SUMIF(konwertery!D$2:D$300,A8,Empik!M$2:M$300) -> 1 | R8: =SUMIF(konwertery!D$2:D$300,A8,Empik!N$2:N$300) -> 9 | T8: =SUMIF(konwertery!E$2:E$300,A8,Publio!P$2:P$300) -> 0 | U8: =SUMIF(konwertery!E$2:E$300,A8,konwertery!F$2:F$300) -> 0 | W8: =SUMIF(Legimi!D$2:D$300,A8,Legimi!G$2:G$300) -> 0 | X8: =SUMIF(Legimi!D$2:D$300,A8,Legimi!H$2:H$300) -> 0 | Z8: =SUMIF(konwertery!G$2:G$302,A8,Nexto!J$2:J$283) -> 0 | AA8: =SUMIF(konwertery!G$2:G$302,A8,Nexto!N$2:P$302) -> 0 | AC8: =SUMIF(Woblink!E$14:E$314,A8,Woblink!I$14:I$314) -> 0 | AD8: =SUMIF(Woblink!E$14:E$314,A8,konwertery!R$2:R$300) -> 0 | AF8: =SUM(SUMIF(konwertery!I$2:I$300,A8,Azymut!H$2:H$298),(SUMIF(konwertery!S$2:S$300,A8,AzymutB!H$2:H304)*2)) -> 0 | AG8: =SUM(SUMIF(konwertery!I$2:I$300,A8,konwertery!J$2:J$300),SUMIF(konwertery!S$2:S$300,A8,konwertery!T$2:T$300)) -> 0 | AI8: =SUMIF(konwertery!K$2:K$300,A8,Ebookpoint!F$14:F$312) -> 0 | AJ8: =SUMIF(konwertery!K$2:K$300,A8,Ebookpoint!M$14:M$312) -> 0 | AL8: =SUMIF(konwertery!L$2:L$300,A8,Nasbi!F$14:F$312) -> 0 | AM8: =SUMIF(konwertery!L$2:L$300,A8,Nasbi!K$14:K$312) -> 0 | AO8: =SUMIF(StorytelE!C$2:C$300,A8,konwertery!M$2:M$300)+SUMIF(StorytelA!C$2:C$300,A8,konwertery!N$2:N$300) -> 73 | AP8: =SUMIF(StorytelE!C$2:C$300,A8,konwertery!O$2:O$300)+SUMIF(StorytelA!C$2:C$300,A8,konwertery!P$2:P$300) -> 95.94 | AR8: =SUMIF(konwertery!U$2:U$300,A8,Audioteka!E$4:E$302) -> 1 | AS8: =SUMIF(konwertery!U$2:U$300,A8,Audioteka!O$4:O$302) -> 8.51 | AU8: =SUMIF(Bookbeat!A$9:A$309,A8,Bookbeat!H$9:H$309) -> 0 | AV8: =SUMIF(Bookbeat!A$9:A$309,A8,Bookbeat!L$9:L$309) -> 0
A9: 9788365156594 | B9: Czerwone mundury, Armia Brytyjska w czasach wojny o niepodległość USA | E9: =H9+K9 -> 1 | F9: =I9+L9 -> 5.9461 | H9: =SUMIF(konwertery!A$2:A$300,A9,Histmag!C$2:C$300) -> 1 | I9: =SUMIF(konwertery!A$2:A$300,A9,konwertery!B$2:B$300) * 0.97 -> 5.9461 | K9: =N9+Q9+T9+W9+Z9+AC9+AF9+AI9+AL9+AO9+AR9+AU9 -> 0 | L9: =O9+R9+U9+X9+AA9+AD9+AG9+AJ9+AM9+AP9+AS9+AV9 -> 0 | N9: =SUMIF(konwertery!C$2:C$300,A9,Virtualo!L$2:L$300) -> 0 | O9: =(SUMIF(konwertery!C$2:C$300,A9,Virtualo!P$2:P$300)) -> 0 | Q9: =SUMIF(konwertery!D$2:D$300,A9,Empik!M$2:M$300) -> 0 | R9: =SUMIF(konwertery!D$2:D$300,A9,Empik!N$2:N$300) -> 0 | T9: =SUMIF(konwertery!E$2:E$300,A9,Publio!P$2:P$300) -> 0 | U9: =SUMIF(konwertery!E$2:E$300,A9,konwertery!F$2:F$300) -> 0 | W9: =SUMIF(Legimi!D$2:D$300,A9,Legimi!G$2:G$300) -> 0 | X9: =SUMIF(Legimi!D$2:D$300,A9,Legimi!H$2:H$300) -> 0 | Z9: =SUMIF(konwertery!G$2:G$302,A9,Nexto!J$2:J$283) -> 0 | AA9: =SUMIF(konwertery!G$2:G$302,A9,Nexto!N$2:P$302) -> 0 | AC9: =SUMIF(Woblink!E$9:E$309,A9,Woblink!I$9:I$309) -> 0 | AD9: =SUMIF(Woblink!E$14:E$314,A9,konwertery!R$2:R$300) -> 0 | AF9: =SUM(SUMIF(konwertery!I$2:I$300,A9,Azymut!H$2:H$298),(SUMIF(konwertery!S$2:S$300,A9,AzymutB!H$2:H305)*2)) -> 0 | AG9: =SUM(SUMIF(konwertery!I$2:I$300,A9,konwertery!J$2:J$300),SUMIF(konwertery!S$2:S$300,A9,konwertery!T$2:T$300)) -> 0 | AI9: =SUMIF(konwertery!K$2:K$300,A9,Ebookpoint!F$14:F$312) -> 0 | AJ9: =SUMIF(konwertery!K$2:K$300,A9,Ebookpoint!M$14:M$312) -> 0 | AL9: =SUMIF(konwertery!L$2:L$300,A9,Nasbi!F$14:F$312) -> 0 | AM9: =SUMIF(konwertery!L$2:L$300,A9,Nasbi!K$14:K$312) -> 0 | AO9: =SUMIF(StorytelE!C$2:C$300,A9,konwertery!M$2:M$300)+SUMIF(StorytelA!C$2:C$300,A9,konwertery!N$2:N$300) -> 0 | AP9: =SUMIF(StorytelE!C$2:C$300,A9,konwertery!O$2:O$300)+SUMIF(StorytelA!C$2:C$300,A9,konwertery!P$2:P$300) -> 0 | AR9: =SUMIF(konwertery!U$2:U$300,A9,Audioteka!E$4:E$302) -> 0 | AS9: =SUMIF(konwertery!U$2:U$300,A9,Audioteka!O$4:O$302) -> 0 | AU9: =SUMIF(Bookbeat!A$9:A$309,A9,Bookbeat!H$9:H$309) -> 0 | AV9: =SUMIF(Bookbeat!A$9:A$309,A9,Bookbeat!L$9:L$309) -> 0
A10: 9788393463022 | B10: Czy Zygmunt III Waza zasłużył na niesławę? | E10: =H10+K10 -> 1 | F10: =I10+L10 -> 4.1516 | H10: =SUMIF(konwertery!A$2:A$300,A10,Histmag!C$2:C$300) -> 1 | I10: =SUMIF(konwertery!A$2:A$300,A10,konwertery!B$2:B$300) * 0.97 -> 4.1516 | K10: =N10+Q10+T10+W10+Z10+AC10+AF10+AI10+AL10+AO10+AR10+AU10 -> 0 | L10: =O10+R10+U10+X10+AA10+AD10+AG10+AJ10+AM10+AP10+AS10+AV10 -> 0 | N10: =SUMIF(konwertery!C$2:C$300,A10,Virtualo!L$2:L$300) -> 0 | O10: =(SUMIF(konwertery!C$2:C$300,A10,Virtualo!P$2:P$300)) -> 0 | Q10: =SUMIF(konwertery!D$2:D$300,A10,Empik!M$2:M$300) -> 0 | R10: =SUMIF(konwertery!D$2:D$300,A10,Empik!N$2:N$300) -> 0 | T10: =SUMIF(konwertery!E$2:E$300,A10,Publio!P$2:P$300) -> 0 | U10: =SUMIF(konwertery!E$2:E$300,A10,konwertery!F$2:F$300) -> 0 | W10: =SUMIF(Legimi!D$2:D$300,A10,Legimi!G$2:G$300) -> 0 | X10: =SUMIF(Legimi!D$2:D$300,A10,Legimi!H$2:H$300) -> 0 | Z10: =SUMIF(konwertery!G$2:G$302,A10,Nexto!J$2:J$283) -> 0 | AA10: =SUMIF(konwertery!G$2:G$302,A10,Nexto!N$2:P$302) -> 0 | AC10: =SUMIF(Woblink!E$9:E$309,A10,Woblink!I$9:I$309) -> 0 | AD10: =SUMIF(Woblink!E$14:E$314,A10,konwertery!R$2:R$300) -> 0 | AF10: =SUM(SUMIF(konwertery!I$2:I$300,A10,Azymut!H$2:H$298),(SUMIF(konwertery!S$2:S$300,A10,AzymutB!H$2:H306)*2)) -> 0 | AG10: =SUM(SUMIF(konwertery!I$2:I$300,A10,konwertery!J$2:J$300),SUMIF(konwertery!S$2:S$300,A10,konwertery!T$2:T$300)) -> 0 | AI10: =SUMIF(konwertery!K$2:K$300,A10,Ebookpoint!F$14:F$312) -> 0 | AJ10: =SUMIF(konwertery!K$2:K$300,A10,Ebookpoint!M$14:M$312) -> 0 | AL10: =SUMIF(konwertery!L$2:L$300,A10,Nasbi!F$14:F$312) -> 0 | AM10: =SUMIF(konwertery!L$2:L$300,A10,Nasbi!K$14:K$312) -> 0 | AO10: =SUMIF(StorytelE!C$2:C$300,A10,konwertery!M$2:M$300)+SUMIF(StorytelA!C$2:C$300,A10,konwertery!N$2:N$300) -> 0 | AP10: =SUMIF(StorytelE!C$2:C$300,A10,konwertery!O$2:O$300)+SUMIF(StorytelA!C$2:C$300,A10,konwertery!P$2:P$300) -> 0 | AR10: =SUMIF(konwertery!U$2:U$300,A10,Audioteka!E$4:E$302) -> 0 | AS10: =SUMIF(konwertery!U$2:U$300,A10,Audioteka!O$4:O$302) -> 0 | AU10: =SUMIF(Bookbeat!A$9:A$309,A10,Bookbeat!H$9:H$309) -> 0 | AV10: =SUMIF(Bookbeat!A$9:A$309,A10,Bookbeat!L$9:L$309) -> 0
A11: 9788365156044 | B11: Damy wielkiego ekranu: Gwiazdy Hollywood od Audrey Hepburn do Elizabeth Taylor | E11: =H11+K11 -> 0 | F11: =I11+L11 -> 0 | H11: =SUMIF(konwertery!A$2:A$300,A11,Histmag!C$2:C$300) -> 0 | I11: =SUMIF(konwertery!A$2:A$300,A11,konwertery!B$2:B$300) * 0.97 -> 0 | K11: =N11+Q11+T11+W11+Z11+AC11+AF11+AI11+AL11+AO11+AR11+AU11 -> 0 | L11: =O11+R11+U11+X11+AA11+AD11+AG11+AJ11+AM11+AP11+AS11+AV11 -> 0 | N11: =SUMIF(konwertery!C$2:C$300,A11,Virtualo!L$2:L$300) -> 0 | O11: =(SUMIF(konwertery!C$2:C$300,A11,Virtualo!P$2:P$300)) -> 0 | Q11: =SUMIF(konwertery!D$2:D$300,A11,Empik!M$2:M$300) -> 0 | R11: =SUMIF(konwertery!D$2:D$300,A11,Empik!N$2:N$300) -> 0 | T11: =SUMIF(konwertery!E$2:E$300,A11,Publio!P$2:P$300) -> 0 | U11: =SUMIF(konwertery!E$2:E$300,A11,konwertery!F$2:F$300) -> 0 | W11: =SUMIF(Legimi!D$2:D$300,A11,Legimi!G$2:G$300) -> 0 | X11: =SUMIF(Legimi!D$2:D$300,A11,Legimi!H$2:H$300) -> 0 | Z11: =SUMIF(konwertery!G$2:G$302,A11,Nexto!J$2:J$283) -> 0 | AA11: =SUMIF(konwertery!G$2:G$302,A11,Nexto!N$2:P$302) -> 0 | AC11: =SUMIF(Woblink!E$9:E$309,A11,Woblink!I$9:I$309) -> 0 | AD11: =SUMIF(Woblink!E$14:E$314,A11,konwertery!R$2:R$300) -> 0 | AF11: =SUM(SUMIF(konwertery!I$2:I$300,A11,Azymut!H$2:H$298),(SUMIF(konwertery!S$2:S$300,A11,AzymutB!H$2:H307)*2)) -> 0 | AG11: =SUM(SUMIF(konwertery!I$2:I$300,A11,konwertery!J$2:J$300),SUMIF(konwertery!S$2:S$300,A11,konwertery!T$2:T$300)) -> 0 | AI11: =SUMIF(konwertery!K$2:K$300,A11,Ebookpoint!F$14:F$312) -> 0 | AJ11: =SUMIF(konwertery!K$2:K$300,A11,Ebookpoint!M$14:M$312) -> 0 | AL11: =SUMIF(konwertery!L$2:L$300,A11,Nasbi!F$14:F$312) -> 0 | AM11: =SUMIF(konwertery!L$2:L$300,A11,Nasbi!K$14:K$312) -> 0 | AO11: =SUMIF(StorytelE!C$2:C$300,A11,konwertery!M$2:M$300)+SUMIF(StorytelA!C$2:C$300,A11,konwertery!N$2:N$300) -> 0 | AP11: =SUMIF(StorytelE!C$2:C$300,A11,konwertery!O$2:O$300)+SUMIF(StorytelA!C$2:C$300,A11,konwertery!P$2:P$300) -> 0 | AR11: =SUMIF(konwertery!U$2:U$300,A11,Audioteka!E$4:E$302) -> 0 | AS11: =SUMIF(konwertery!U$2:U$300,A11,Audioteka!O$4:O$302) -> 0 | AU11: =SUMIF(Bookbeat!A$9:A$309,A11,Bookbeat!H$9:H$309) -> 0 | AV11: =SUMIF(Bookbeat!A$9:A$309,A11,Bookbeat!L$9:L$309) -> 0
A12: 9788365156532 | B12: Dowody zbrodni, Początki kryminalistyki | E12: =H12+K12 -> 5 | F12: =I12+L12 -> 45.8262 | H12: =SUMIF(konwertery!A$2:A$300,A12,Histmag!C$2:C$300) -> 1 | I12: =SUMIF(konwertery!A$2:A$300,A12,konwertery!B$2:B$300) * 0.97 -> 10.1462 | K12: =N12+Q12+T12+W12+Z12+AC12+AF12+AI12+AL12+AO12+AR12+AU12 -> 4 | L12: =O12+R12+U12+X12+AA12+AD12+AG12+AJ12+AM12+AP12+AS12+AV12 -> 35.68 | N12: =SUMIF(konwertery!C$2:C$300,A12,Virtualo!L$2:L$300) -> 1 | O12: =(SUMIF(konwertery!C$2:C$300,A12,Virtualo!P$2:P$300)) -> 12.31 | Q12: =SUMIF(konwertery!D$2:D$300,A12,Empik!M$2:M$300) -> 2 | R12: =SUMIF(konwertery!D$2:D$300,A12,Empik!N$2:N$300) -> 12 | T12: =SUMIF(konwertery!E$2:E$300,A12,Publio!P$2:P$300) -> 0 | U12: =SUMIF(konwertery!E$2:E$300,A12,konwertery!F$2:F$300) -> 0 | W12: =SUMIF(Legimi!D$2:D$300,A12,Legimi!G$2:G$300) -> 0 | X12: =SUMIF(Legimi!D$2:D$300,A12,Legimi!H$2:H$300) -> 0 | Z12: =SUMIF(konwertery!G$2:G$302,A12,Nexto!J$2:J$283) -> 0 | AA12: =SUMIF(konwertery!G$2:G$302,A12,Nexto!N$2:P$302) -> 0 | AC12: =SUMIF(Woblink!E$9:E$309,A12,Woblink!I$9:I$309) -> 1 | AD12: =SUMIF(Woblink!E$14:E$314,A12,konwertery!R$2:R$300) -> 11.37 | AF12: =SUM(SUMIF(konwertery!I$2:I$300,A12,Azymut!H$2:H$298),(SUMIF(konwertery!S$2:S$300,A12,AzymutB!H$2:H308)*2)) -> 0 | AG12: =SUM(SUMIF(konwertery!I$2:I$300,A12,konwertery!J$2:J$300),SUMIF(konwertery!S$2:S$300,A12,konwertery!T$2:T$300)) -> 0 | AI12: =SUMIF(konwertery!K$2:K$300,A12,Ebookpoint!F$14:F$312) -> 0 | AJ12: =SUMIF(konwertery!K$2:K$300,A12,Ebookpoint!M$14:M$312) -> 0 | AL12: =SUMIF(konwertery!L$2:L$300,A12,Nasbi!F$14:F$312) -> 0 | AM12: =SUMIF(konwertery!L$2:L$300,A12,Nasbi!K$14:K$312) -> 0 | AO12: =SUMIF(StorytelE!C$2:C$300,A12,konwertery!M$2:M$300)+SUMIF(StorytelA!C$2:C$300,A12,konwertery!N$2:N$300) -> 0 | AP12: =SUMIF(StorytelE!C$2:C$300,A12,konwertery!O$2:O$300)+SUMIF(StorytelA!C$2:C$300,A12,konwertery!P$2:P$300) -> 0 | AR12: =SUMIF(konwertery!U$2:U$300,A12,Audioteka!E$4:E$302) -> 0 | AS12: =SUMIF(konwertery!U$2:U$300,A12,Audioteka!O$4:O$302) -> 0 | AU12: =SUMIF(Bookbeat!A$9:A$309,A12,Bookbeat!H$9:H$309) -> 0 | AV12: =SUMIF(Bookbeat!A$9:A$309,A12,Bookbeat!L$9:L$309) -> 0
A13: 9788365156624 | B13: Dowody zbrodni, Początki kryminalistyki (audio) | E13: =H13+K13 -> 6 | F13: =I13+L13 -> 42.79 | H13: =SUMIF(konwertery!A$2:A$300,A13,Histmag!C$2:C$300) -> 0 | I13: =SUMIF(konwertery!A$2:A$300,A13,konwertery!B$2:B$300) * 0.97 -> 0 | K13: =N13+Q13+T13+W13+Z13+AC13+AF13+AI13+AL13+AO13+AR13+AU13 -> 6 | L13: =O13+R13+U13+X13+AA13+AD13+AG13+AJ13+AM13+AP13+AS13+AV13 -> 42.79 | N13: =SUMIF(konwertery!C$2:C$300,A13,Virtualo!L$2:L$300) -> 0 | O13: =(SUMIF(konwertery!C$2:C$300,A13,Virtualo!P$2:P$300)) -> 0 | Q13: =SUMIF(konwertery!D$2:D$300,A13,Empik!M$2:M$300) -> 0 | R13: =SUMIF(konwertery!D$2:D$300,A13,Empik!N$2:N$300) -> 0 | T13: =SUMIF(konwertery!E$2:E$300,A13,Publio!P$2:P$300) -> 0 | U13: =SUMIF(konwertery!E$2:E$300,A13,konwertery!F$2:F$300) -> 0 | W13: =SUMIF(Legimi!D$2:D$300,A13,Legimi!G$2:G$300) -> 0 | X13: =SUMIF(Legimi!D$2:D$300,A13,Legimi!H$2:H$300) -> 0 | Z13: =SUMIF(konwertery!G$2:G$302,A13,Nexto!J$2:J$283) -> 0 | AA13: =SUMIF(konwertery!G$2:G$302,A13,Nexto!N$2:P$302) -> 0 | AC13: =SUMIF(Woblink!E$9:E$309,A13,Woblink!I$9:I$309) -> 0 | AD13: =SUMIF(Woblink!E$14:E$314,A13,konwertery!R$2:R$300) -> 0 | AF13: =SUM(SUMIF(konwertery!I$2:I$300,A13,Azymut!H$2:H$298),(SUMIF(konwertery!S$2:S$300,A13,AzymutB!H$2:H309)*2)) -> 1 | AG13: =SUM(SUMIF(konwertery!I$2:I$300,A13,konwertery!J$2:J$300),SUMIF(konwertery!S$2:S$300,A13,konwertery!T$2:T$300)) -> 11.37 | AI13: =SUMIF(konwertery!K$2:K$300,A13,Ebookpoint!F$14:F$312) -> 1 | AJ13: =SUMIF(konwertery!K$2:K$300,A13,Ebookpoint!M$14:M$312) -> 12.13 | AL13: =SUMIF(konwertery!L$2:L$300,A13,Nasbi!F$14:F$312) -> 1 | AM13: =SUMIF(konwertery!L$2:L$300,A13,Nasbi!K$14:K$312) -> 12.13 | AO13: =SUMIF(StorytelE!C$2:C$300,A13,konwertery!M$2:M$300)+SUMIF(StorytelA!C$2:C$300,A13,konwertery!N$2:N$300) -> 2 | AP13: =SUMIF(StorytelE!C$2:C$300,A13,konwertery!O$2:O$300)+SUMIF(StorytelA!C$2:C$300,A13,konwertery!P$2:P$300) -> 4.06 | AR13: =SUMIF(konwertery!U$2:U$300,A13,Audioteka!E$4:E$302) -> 0 | AS13: =SUMIF(konwertery!U$2:U$300,A13,Audioteka!O$4:O$302) -> 0 | AU13: =SUMIF(Bookbeat!A$9:A$309,A13,Bookbeat!H$9:H$309) -> 1 | AV13: =SUMIF(Bookbeat!A$9:A$309,A13,Bookbeat!L$9:L$309) -> 3.1
A14: 9788365156181 | B14: Dramat Afganistanu: XIX wiek | E14: =H14+K14 -> 0 | F14: =I14+L14 -> 0 | H14: =SUMIF(konwertery!A$2:A$300,A14,Histmag!C$2:C$300) -> 0 | I14: =SUMIF(konwertery!A$2:A$300,A14,konwertery!B$2:B$300) * 0.97 -> 0 | K14: =N14+Q14+T14+W14+Z14+AC14+AF14+AI14+AL14+AO14+AR14+AU14 -> 0 | L14: =O14+R14+U14+X14+AA14+AD14+AG14+AJ14+AM14+AP14+AS14+AV14 -> 0 | N14: =SUMIF(konwertery!C$2:C$300,A14,Virtualo!L$2:L$300) -> 0 | O14: =(SUMIF(konwertery!C$2:C$300,A14,Virtualo!P$2:P$300)) -> 0 | Q14: =SUMIF(konwertery!D$2:D$300,A14,Empik!M$2:M$300) -> 0 | R14: =SUMIF(konwertery!D$2:D$300,A14,Empik!N$2:N$300) -> 0 | T14: =SUMIF(konwertery!E$2:E$300,A14,Publio!P$2:P$300) -> 0 | U14: =SUMIF(konwertery!E$2:E$300,A14,konwertery!F$2:F$300) -> 0 | W14: =SUMIF(Legimi!D$2:D$300,A14,Legimi!G$2:G$300) -> 0 | X14: =SUMIF(Legimi!D$2:D$300,A14,Legimi!H$2:H$300) -> 0 | Z14: =SUMIF(konwertery!G$2:G$302,A14,Nexto!J$2:J$283) -> 0 | AA14: =SUMIF(konwertery!G$2:G$302,A14,Nexto!N$2:P$302) -> 0 | AC14: =SUMIF(Woblink!E$9:E$309,A14,Woblink!I$9:I$309) -> 0 | AD14: =SUMIF(Woblink!E$14:E$314,A14,konwertery!R$2:R$300) -> 0 | AF14: =SUM(SUMIF(konwertery!I$2:I$300,A14,Azymut!H$2:H$298),(SUMIF(konwertery!S$2:S$300,A14,AzymutB!H$2:H310)*2)) -> 0 | AG14: =SUM(SUMIF(konwertery!I$2:I$300,A14,konwertery!J$2:J$300),SUMIF(konwertery!S$2:S$300,A14,konwertery!T$2:T$300)) -> 0 | AI14: =SUMIF(konwertery!K$2:K$300,A14,Ebookpoint!F$14:F$312) -> 0 | AJ14: =SUMIF(konwertery!K$2:K$300,A14,Ebookpoint!M$14:M$312) -> 0 | AL14: =SUMIF(konwertery!L$2:L$300,A14,Nasbi!F$14:F$312) -> 0 | AM14: =SUMIF(konwertery!L$2:L$300,A14,Nasbi!K$14:K$312) -> 0 | AO14: =SUMIF(StorytelE!C$2:C$300,A14,konwertery!M$2:M$300)+SUMIF(StorytelA!C$2:C$300,A14,konwertery!N$2:N$300) -> 0 | AP14: =SUMIF(StorytelE!C$2:C$300,A14,konwertery!O$2:O$300)+SUMIF(StorytelA!C$2:C$300,A14,konwertery!P$2:P$300) -> 0 | AR14: =SUMIF(konwertery!U$2:U$300,A14,Audioteka!E$4:E$302) -> 0 | AS14: =SUMIF(konwertery!U$2:U$300,A14,Audioteka!O$4:O$302) -> 0 | AU14: =SUMIF(Bookbeat!A$9:A$309,A14,Bookbeat!H$9:H$309) -> 0 | AV14: =SUMIF(Bookbeat!A$9:A$309,A14,Bookbeat!L$9:L$309) -> 0
A15: 9788365156204 | B15: Dramat Afganistanu: XX wiek | E15: =H15+K15 -> 1 | F15: =I15+L15 -> 4.3 | H15: =SUMIF(konwertery!A$2:A$300,A15,Histmag!C$2:C$300) -> 0 | I15: =SUMIF(konwertery!A$2:A$300,A15,konwertery!B$2:B$300) * 0.97 -> 0 | K15: =N15+Q15+T15+W15+Z15+AC15+AF15+AI15+AL15+AO15+AR15+AU15 -> 1 | L15: =O15+R15+U15+X15+AA15+AD15+AG15+AJ15+AM15+AP15+AS15+AV15 -> 4.3 | N15: =SUMIF(konwertery!C$2:C$300,A15,Virtualo!L$2:L$300) -> 0 | O15: =(SUMIF(konwertery!C$2:C$300,A15,Virtualo!P$2:P$300)) -> 0 | Q15: =SUMIF(konwertery!D$2:D$300,A15,Empik!M$2:M$300) -> 0 | R15: =SUMIF(konwertery!D$2:D$300,A15,Empik!N$2:N$300) -> 0 | T15: =SUMIF(konwertery!E$2:E$300,A15,Publio!P$2:P$300) -> 0 | U15: =SUMIF(konwertery!E$2:E$300,A15,konwertery!F$2:F$300) -> 0 | W15: =SUMIF(Legimi!D$2:D$300,A15,Legimi!G$2:G$300) -> 0 | X15: =SUMIF(Legimi!D$2:D$300,A15,Legimi!H$2:H$300) -> 0 | Z15: =SUMIF(konwertery!G$2:G$302,A15,Nexto!J$2:J$283) -> 1 | AA15: =SUMIF(konwertery!G$2:G$302,A15,Nexto!N$2:P$302) -> 4.3 | AC15: =SUMIF(Woblink!E$9:E$309,A15,Woblink!I$9:I$309) -> 0 | AD15: =SUMIF(Woblink!E$14:E$314,A15,konwertery!R$2:R$300) -> 0 | AF15: =SUM(SUMIF(konwertery!I$2:I$300,A15,Azymut!H$2:H$298),(SUMIF(konwertery!S$2:S$300,A15,AzymutB!H$2:H311)*2)) -> 0 | AG15: =SUM(SUMIF(konwertery!I$2:I$300,A15,konwertery!J$2:J$300),SUMIF(konwertery!S$2:S$300,A15,konwertery!T$2:T$300)) -> 0 | AI15: =SUMIF(konwertery!K$2:K$300,A15,Ebookpoint!F$14:F$312) -> 0 | AJ15: =SUMIF(konwertery!K$2:K$300,A15,Ebookpoint!M$14:M$312) -> 0 | AL15: =SUMIF(konwertery!L$2:L$300,A15,Nasbi!F$14:F$312) -> 0 | AM15: =SUMIF(konwertery!L$2:L$300,A15,Nasbi!K$14:K$312) -> 0 | AO15: =SUMIF(StorytelE!C$2:C$300,A15,konwertery!M$2:M$300)+SUMIF(StorytelA!C$2:C$300,A15,konwertery!N$2:N$300) -> 0 | AP15: =SUMIF(StorytelE!C$2:C$300,A15,konwertery!O$2:O$300)+SUMIF(StorytelA!C$2:C$300,A15,konwertery!P$2:P$300) -> 0 | AR15: =SUMIF(konwertery!U$2:U$300,A15,Audioteka!E$4:E$302) -> 0 | AS15: =SUMIF(konwertery!U$2:U$300,A15,Audioteka!O$4:O$302) -> 0 | AU15: =SUMIF(Bookbeat!A$9:A$309,A15,Bookbeat!H$9:H$309) -> 0 | AV15: =SUMIF(Bookbeat!A$9:A$309,A15,Bookbeat!L$9:L$309) -> 0
A16: 9788365156631 | B16: Droga do imperium. Początki Wielkiej Brytanii 1603-1707 | E16: =H16+K16 -> 1 | F16: =I16+L16 -> 9.5448 | H16: =SUMIF(konwertery!A$2:A$300,A16,Histmag!C$2:C$300) -> 1 | I16: =SUMIF(konwertery!A$2:A$300,A16,konwertery!B$2:B$300) * 0.97 -> 9.5448 | K16: =N16+Q16+T16+W16+Z16+AC16+AF16+AI16+AL16+AO16+AR16+AU16 -> 0 | L16: =O16+R16+U16+X16+AA16+AD16+AG16+AJ16+AM16+AP16+AS16+AV16 -> 0 | N16: =SUMIF(konwertery!C$2:C$300,A16,Virtualo!L$2:L$300) -> 0 | O16: =(SUMIF(konwertery!C$2:C$300,A16,Virtualo!P$2:P$300)) -> 0 | Q16: =SUMIF(konwertery!D$2:D$300,A16,Empik!M$2:M$300) -> 0 | R16: =SUMIF(konwertery!D$2:D$300,A16,Empik!N$2:N$300) -> 0 | T16: =SUMIF(konwertery!E$2:E$300,A16,Publio!P$2:P$300) -> 0 | U16: =SUMIF(konwertery!E$2:E$300,A16,konwertery!F$2:F$300) -> 0 | W16: =SUMIF(Legimi!D$2:D$300,A16,Legimi!G$2:G$300) -> 0 | X16: =SUMIF(Legimi!D$2:D$300,A16,Legimi!H$2:H$300) -> 0 | Z16: =SUMIF(konwertery!G$2:G$302,A16,Nexto!J$2:J$283) -> 0 | AA16: =SUMIF(konwertery!G$2:G$302,A16,Nexto!N$2:P$302) -> 0 | AC16: =SUMIF(Woblink!E$9:E$309,A16,Woblink!I$9:I$309) -> 0 | AD16: =SUMIF(Woblink!E$14:E$314,A16,konwertery!R$2:R$300) -> 0 | AF16: =SUM(SUMIF(konwertery!I$2:I$300,A16,Azymut!H$2:H$298),(SUMIF(konwertery!S$2:S$300,A16,AzymutB!H$2:H312)*2)) -> 0 | AG16: =SUM(SUMIF(konwertery!I$2:I$300,A16,konwertery!J$2:J$300),SUMIF(konwertery!S$2:S$300,A16,konwertery!T$2:T$300)) -> 0 | AI16: =SUMIF(konwertery!K$2:K$300,A16,Ebookpoint!F$14:F$312) -> 0 | AJ16: =SUMIF(konwertery!K$2:K$300,A16,Ebookpoint!M$14:M$312) -> 0 | AL16: =SUMIF(konwertery!L$2:L$300,A16,Nasbi!F$14:F$312) -> 0 | AM16: =SUMIF(konwertery!L$2:L$300,A16,Nasbi!K$14:K$312) -> 0 | AO16: =SUMIF(StorytelE!C$2:C$300,A16,konwertery!M$2:M$300)+SUMIF(StorytelA!C$2:C$300,A16,konwertery!N$2:N$300) -> 0 | AP16: =SUMIF(StorytelE!C$2:C$300,A16,konwertery!O$2:O$300)+SUMIF(StorytelA!C$2:C$300,A16,konwertery!P$2:P$300) -> 0 | AR16: =SUMIF(konwertery!U$2:U$300,A16,Audioteka!E$4:E$302) -> 0 | AS16: =SUMIF(konwertery!U$2:U$300,A16,Audioteka!O$4:O$302) -> 0 | AU16: =SUMIF(Bookbeat!A$9:A$309,A16,Bookbeat!H$9:H$309) -> 0 | AV16: =SUMIF(Bookbeat!A$9:A$309,A16,Bookbeat!L$9:L$309) -> 0
A17: 9788393463084 | B17: Elita władzy w Królestwie Jerozolimskim | E17: =H17+K17 -> 0 | F17: =I17+L17 -> 0 | H17: =SUMIF(konwertery!A$2:A$300,A17,Histmag!C$2:C$300) -> 0 | I17: =SUMIF(konwertery!A$2:A$300,A17,konwertery!B$2:B$300) * 0.97 -> 0 | K17: =N17+Q17+T17+W17+Z17+AC17+AF17+AI17+AL17+AO17+AR17+AU17 -> 0 | L17: =O17+R17+U17+X17+AA17+AD17+AG17+AJ17+AM17+AP17+AS17+AV17 -> 0 | N17: =SUMIF(konwertery!C$2:C$300,A17,Virtualo!L$2:L$300) -> 0 | O17: =(SUMIF(konwertery!C$2:C$300,A17,Virtualo!P$2:P$300)) -> 0 | Q17: =SUMIF(konwertery!D$2:D$300,A17,Empik!M$2:M$300) -> 0 | R17: =SUMIF(konwertery!D$2:D$300,A17,Empik!N$2:N$300) -> 0 | T17: =SUMIF(konwertery!E$2:E$300,A17,Publio!P$2:P$300) -> 0 | U17: =SUMIF(konwertery!E$2:E$300,A17,konwertery!F$2:F$300) -> 0 | W17: =SUMIF(Legimi!D$2:D$300,A17,Legimi!G$2:G$300) -> 0 | X17: =SUMIF(Legimi!D$2:D$300,A17,Legimi!H$2:H$300) -> 0 | Z17: =SUMIF(konwertery!G$2:G$302,A17,Nexto!J$2:J$283) -> 0 | AA17: =SUMIF(konwertery!G$2:G$302,A17,Nexto!N$2:P$302) -> 0 | AC17: =SUMIF(Woblink!E$9:E$309,A17,Woblink!I$9:I$309) -> 0 | AD17: =SUMIF(Woblink!E$14:E$314,A17,konwertery!R$2:R$300) -> 0 | AF17: =SUM(SUMIF(konwertery!I$2:I$300,A17,Azymut!H$2:H$298),(SUMIF(konwertery!S$2:S$300,A17,AzymutB!H$2:H313)*2)) -> 0 | AG17: =SUM(SUMIF(konwertery!I$2:I$300,A17,konwertery!J$2:J$300),SUMIF(konwertery!S$2:S$300,A17,konwertery!T$2:T$300)) -> 0 | AI17: =SUMIF(konwertery!K$2:K$300,A17,Ebookpoint!F$14:F$312) -> 0 | AJ17: =SUMIF(konwertery!K$2:K$300,A17,Ebookpoint!M$14:M$312) -> 0 | AL17: =SUMIF(konwertery!L$2:L$300,A17,Nasbi!F$14:F$312) -> 0 | AM17: =SUMIF(konwertery!L$2:L$300,A17,Nasbi!K$14:K$312) -> 0 | AO17: =SUMIF(StorytelE!C$2:C$300,A17,konwertery!M$2:M$300)+SUMIF(StorytelA!C$2:C$300,A17,konwertery!N$2:N$300) -> 0 | AP17: =SUMIF(StorytelE!C$2:C$300,A17,konwertery!O$2:O$300)+SUMIF(StorytelA!C$2:C$300,A17,konwertery!P$2:P$300) -> 0 | AR17: =SUMIF(konwertery!U$2:U$300,A17,Audioteka!E$4:E$302) -> 0 | AS17: =SUMIF(konwertery!U$2:U$300,A17,Audioteka!O$4:O$302) -> 0 | AU17: =SUMIF(Bookbeat!A$9:A$309,A17,Bookbeat!H$9:H$309) -> 0 | AV17: =SUMIF(Bookbeat!A$9:A$309,A17,Bookbeat!L$9:L$309) -> 0
A18: 9788365156280 | B18: Gdy Polacy nosili dredy, Kołtun – historia prawdziwa | E18: =H18+K18 -> 4 | F18: =I18+L18 -> 15.7521 | H18: =SUMIF(konwertery!A$2:A$300,A18,Histmag!C$2:C$300) -> 1 | I18: =SUMIF(konwertery!A$2:A$300,A18,konwertery!B$2:B$300) * 0.97 -> 7.6921 | K18: =N18+Q18+T18+W18+Z18+AC18+AF18+AI18+AL18+AO18+AR18+AU18 -> 3 | L18: =O18+R18+U18+X18+AA18+AD18+AG18+AJ18+AM18+AP18+AS18+AV18 -> 8.06 | N18: =SUMIF(konwertery!C$2:C$300,A18,Virtualo!L$2:L$300) -> 0 | O18: =(SUMIF(konwertery!C$2:C$300,A18,Virtualo!P$2:P$300)) -> 0 | Q18: =SUMIF(konwertery!D$2:D$300,A18,Empik!M$2:M$300) -> 0 | R18: =SUMIF(konwertery!D$2:D$300,A18,Empik!N$2:N$300) -> 0 | T18: =SUMIF(konwertery!E$2:E$300,A18,Publio!P$2:P$300) -> 0 | U18: =SUMIF(konwertery!E$2:E$300,A18,konwertery!F$2:F$300) -> 0 | W18: =SUMIF(Legimi!D$2:D$300,A18,Legimi!G$2:G$300) -> 0 | X18: =SUMIF(Legimi!D$2:D$300,A18,Legimi!H$2:H$300) -> 0 | Z18: =SUMIF(konwertery!G$2:G$302,A18,Nexto!J$2:J$283) -> 1 | AA18: =SUMIF(konwertery!G$2:G$302,A18,Nexto!N$2:P$302) -> 4.97 | AC18: =SUMIF(Woblink!E$9:E$309,A18,Woblink!I$9:I$309) -> 0 | AD18: =SUMIF(Woblink!E$14:E$314,A18,konwertery!R$2:R$300) -> 0 | AF18: =SUM(SUMIF(konwertery!I$2:I$300,A18,Azymut!H$2:H$298),(SUMIF(konwertery!S$2:S$300,A18,AzymutB!H$2:H314)*2)) -> 0 | AG18: =SUM(SUMIF(konwertery!I$2:I$300,A18,konwertery!J$2:J$300),SUMIF(konwertery!S$2:S$300,A18,konwertery!T$2:T$300)) -> 0 | AI18: =SUMIF(konwertery!K$2:K$300,A18,Ebookpoint!F$14:F$312) -> 0 | AJ18: =SUMIF(konwertery!K$2:K$300,A18,Ebookpoint!M$14:M$312) -> 0 | AL18: =SUMIF(konwertery!L$2:L$300,A18,Nasbi!F$14:F$312) -> 0 | AM18: =SUMIF(konwertery!L$2:L$300,A18,Nasbi!K$14:K$312) -> 0 | AO18: =SUMIF(StorytelE!C$2:C$300,A18,konwertery!M$2:M$300)+SUMIF(StorytelA!C$2:C$300,A18,konwertery!N$2:N$300) -> 2 | AP18: =SUMIF(StorytelE!C$2:C$300,A18,konwertery!O$2:O$300)+SUMIF(StorytelA!C$2:C$300,A18,konwertery!P$2:P$300) -> 3.09 | AR18: =SUMIF(konwertery!U$2:U$300,A18,Audioteka!E$4:E$302) -> 0 | AS18: =SUMIF(konwertery!U$2:U$300,A18,Audioteka!O$4:O$302) -> 0 | AU18: =SUMIF(Bookbeat!A$9:A$309,A18,Bookbeat!H$9:H$309) -> 0 | AV18: =SUMIF(Bookbeat!A$9:A$309,A18,Bookbeat!L$9:L$309) -> 0
A19: 9788365156761 | B19: Gdy Polacy nosili dredy, Kołtun – historia prawdziwa (audio) | E19: =H19+K19 -> 50 | F19: =I19+L19 -> 120.91 | H19: =SUMIF(konwertery!A$2:A$300,A19,Histmag!C$2:C$300) -> 0 | I19: =SUMIF(konwertery!A$2:A$300,A19,konwertery!B$2:B$300) * 0.97 -> 0 | K19: =N19+Q19+T19+W19+Z19+AC19+AF19+AI19+AL19+AO19+AR19+AU19 -> 50 | L19: =O19+R19+U19+X19+AA19+AD19+AG19+AJ19+AM19+AP19+AS19+AV19 -> 120.91 | N19: =SUMIF(konwertery!C$2:C$300,A19,Virtualo!L$2:L$300) -> 0 | O19: =(SUMIF(konwertery!C$2:C$300,A19,Virtualo!P$2:P$300)) -> 0 | Q19: =SUMIF(konwertery!D$2:D$300,A19,Empik!M$2:M$300) -> 4 | R19: =SUMIF(konwertery!D$2:D$300,A19,Empik!N$2:N$300) -> 36 | T19: =SUMIF(konwertery!E$2:E$300,A19,Publio!P$2:P$300) -> 0 | U19: =SUMIF(konwertery!E$2:E$300,A19,konwertery!F$2:F$300) -> 0 | W19: =SUMIF(Legimi!D$2:D$300,A19,Legimi!G$2:G$300) -> 1 | X19: =SUMIF(Legimi!D$2:D$300,A19,Legimi!H$2:H$300) -> 9.93 | Z19: =SUMIF(konwertery!G$2:G$302,A19,Nexto!J$2:J$283) -> 0 | AA19: =SUMIF(konwertery!G$2:G$302,A19,Nexto!N$2:P$302) -> 0 | AC19: =SUMIF(Woblink!E$14:E$314,A19,Woblink!I$14:I$314) -> 0 | AD19: =SUMIF(Woblink!E$14:E$314,A19,konwertery!R$2:R$300) -> 0 | AF19: =SUM(SUMIF(konwertery!I$2:I$300,A19,Azymut!H$2:H$298),(SUMIF(konwertery!S$2:S$300,A19,AzymutB!H$2:H315)*2)) -> 0 | AG19: =SUM(SUMIF(konwertery!I$2:I$300,A19,konwertery!J$2:J$300),SUMIF(konwertery!S$2:S$300,A19,konwertery!T$2:T$300)) -> 0 | AI19: =SUMIF(konwertery!K$2:K$300,A19,Ebookpoint!F$14:F$312) -> 0 | AJ19: =SUMIF(konwertery!K$2:K$300,A19,Ebookpoint!M$14:M$312) -> 0 | AL19: =SUMIF(konwertery!L$2:L$300,A19,Nasbi!F$14:F$312) -> 0 | AM19: =SUMIF(konwertery!L$2:L$300,A19,Nasbi!K$14:K$312) -> 0 | AO19: =SUMIF(StorytelE!C$2:C$300,A19,konwertery!M$2:M$300)+SUMIF(StorytelA!C$2:C$300,A19,konwertery!N$2:N$300) -> 43 | AP19: =SUMIF(StorytelE!C$2:C$300,A19,konwertery!O$2:O$300)+SUMIF(StorytelA!C$2:C$300,A19,konwertery!P$2:P$300) -> 57.96 | AR19: =SUMIF(konwertery!U$2:U$300,A19,Audioteka!E$4:E$302) -> 2 | AS19: =SUMIF(konwertery!U$2:U$300,A19,Audioteka!O$4:O$302) -> 17.02 | AU19: =SUMIF(Bookbeat!A$9:A$309,A19,Bookbeat!H$9:H$309) -> 0 | AV19: =SUMIF(Bookbeat!A$9:A$309,A19,Bookbeat!L$9:L$309) -> 0
A20: 9788365156464 | B20: Gdzie diabeł nie może, Morderczynie i filutki | E20: =H20+K20 -> 1 | F20: =I20+L20 -> 7 | H20: =SUMIF(konwertery!A$2:A$300,A20,Histmag!C$2:C$300) -> 0 | I20: =SUMIF(konwertery!A$2:A$300,A20,konwertery!B$2:B$300) * 0.97 -> 0 | K20: =N20+Q20+T20+W20+Z20+AC20+AF20+AI20+AL20+AO20+AR20+AU20 -> 1 | L20: =O20+R20+U20+X20+AA20+AD20+AG20+AJ20+AM20+AP20+AS20+AV20 -> 7 | N20: =SUMIF(konwertery!C$2:C$300,A20,Virtualo!L$2:L$300) -> 0 | O20: =(SUMIF(konwertery!C$2:C$300,A20,Virtualo!P$2:P$300)) -> 0 | Q20: =SUMIF(konwertery!D$2:D$300,A20,Empik!M$2:M$300) -> 1 | R20: =SUMIF(konwertery!D$2:D$300,A20,Empik!N$2:N$300) -> 7 | T20: =SUMIF(konwertery!E$2:E$300,A20,Publio!P$2:P$300) -> 0 | U20: =SUMIF(konwertery!E$2:E$300,A20,konwertery!F$2:F$300) -> 0 | W20: =SUMIF(Legimi!D$2:D$300,A20,Legimi!G$2:G$300) -> 0 | X20: =SUMIF(Legimi!D$2:D$300,A20,Legimi!H$2:H$300) -> 0 | Z20: =SUMIF(konwertery!G$2:G$302,A20,Nexto!J$2:J$283) -> 0 | AA20: =SUMIF(konwertery!G$2:G$302,A20,Nexto!N$2:P$302) -> 0 | AC20: =SUMIF(Woblink!E$9:E$309,A20,Woblink!I$9:I$309) -> 0 | AD20: =SUMIF(Woblink!E$14:E$314,A20,konwertery!R$2:R$300) -> 0 | AF20: =SUM(SUMIF(konwertery!I$2:I$300,A20,Azymut!H$2:H$298),(SUMIF(konwertery!S$2:S$300,A20,AzymutB!H$2:H316)*2)) -> 0 | AG20: =SUM(SUMIF(konwertery!I$2:I$300,A20,konwertery!J$2:J$300),SUMIF(konwertery!S$2:S$300,A20,konwertery!T$2:T$300)) -> 0 | AI20: =SUMIF(konwertery!K$2:K$300,A20,Ebookpoint!F$14:F$312) -> 0 | AJ20: =SUMIF(konwertery!K$2:K$300,A20,Ebookpoint!M$14:M$312) -> 0 | AL20: =SUMIF(konwertery!L$2:L$300,A20,Nasbi!F$14:F$312) -> 0 | AM20: =SUMIF(konwertery!L$2:L$300,A20,Nasbi!K$14:K$312) -> 0 | AO20: =SUMIF(StorytelE!C$2:C$300,A20,konwertery!M$2:M$300)+SUMIF(StorytelA!C$2:C$300,A20,konwertery!N$2:N$300) -> 0 | AP20: =SUMIF(StorytelE!C$2:C$300,A20,konwertery!O$2:O$300)+SUMIF(StorytelA!C$2:C$300,A20,konwertery!P$2:P$300) -> 0 | AR20: =SUMIF(konwertery!U$2:U$300,A20,Audioteka!E$4:E$302) -> 0 | AS20: =SUMIF(konwertery!U$2:U$300,A20,Audioteka!O$4:O$302) -> 0 | AU20: =SUMIF(Bookbeat!A$9:A$309,A20,Bookbeat!H$9:H$309) -> 0 | AV20: =SUMIF(Bookbeat!A$9:A$309,A20,Bookbeat!L$9:L$309) -> 0
A21: 9788365156242 | B21: Geniusze, nowatorzy i skandaliści polskiej literatury, Od Przybyszewskiego do Gombrowicza | E21: =H21+K21 -> 2 | F21: =I21+L21 -> 12.3601 | H21: =SUMIF(konwertery!A$2:A$300,A21,Histmag!C$2:C$300) -> 1 | I21: =SUMIF(konwertery!A$2:A$300,A21,konwertery!B$2:B$300) * 0.97 -> 10.9901 | K21: =N21+Q21+T21+W21+Z21+AC21+AF21+AI21+AL21+AO21+AR21+AU21 -> 1 | L21: =O21+R21+U21+X21+AA21+AD21+AG21+AJ21+AM21+AP21+AS21+AV21 -> 1.37 | N21: =SUMIF(konwertery!C$2:C$300,A21,Virtualo!L$2:L$300) -> 0 | O21: =(SUMIF(konwertery!C$2:C$300,A21,Virtualo!P$2:P$300)) -> 0 | Q21: =SUMIF(konwertery!D$2:D$300,A21,Empik!M$2:M$300) -> 0 | R21: =SUMIF(konwertery!D$2:D$300,A21,Empik!N$2:N$300) -> 0 | T21: =SUMIF(konwertery!E$2:E$300,A21,Publio!P$2:P$300) -> 0 | U21: =SUMIF(konwertery!E$2:E$300,A21,konwertery!F$2:F$300) -> 0 | W21: =SUMIF(Legimi!D$2:D$300,A21,Legimi!G$2:G$300) -> 0 | X21: =SUMIF(Legimi!D$2:D$300,A21,Legimi!H$2:H$300) -> 0 | Z21: =SUMIF(konwertery!G$2:G$302,A21,Nexto!J$2:J$283) -> 0 | AA21: =SUMIF(konwertery!G$2:G$302,A21,Nexto!N$2:P$302) -> 0 | AC21: =SUMIF(Woblink!E$9:E$309,A21,Woblink!I$9:I$309) -> 0 | AD21: =SUMIF(Woblink!E$14:E$314,A21,konwertery!R$2:R$300) -> 0 | AF21: =SUM(SUMIF(konwertery!I$2:I$300,A21,Azymut!H$2:H$298),(SUMIF(konwertery!S$2:S$300,A21,AzymutB!H$2:H317)*2)) -> 0 | AG21: =SUM(SUMIF(konwertery!I$2:I$300,A21,konwertery!J$2:J$300),SUMIF(konwertery!S$2:S$300,A21,konwertery!T$2:T$300)) -> 0 | AI21: =SUMIF(konwertery!K$2:K$300,A21,Ebookpoint!F$14:F$312) -> 0 | AJ21: =SUMIF(konwertery!K$2:K$300,A21,Ebookpoint!M$14:M$312) -> 0 | AL21: =SUMIF(konwertery!L$2:L$300,A21,Nasbi!F$14:F$312) -> 0 | AM21: =SUMIF(konwertery!L$2:L$300,A21,Nasbi!K$14:K$312) -> 0 | AO21: =SUMIF(StorytelE!C$2:C$300,A21,konwertery!M$2:M$300)+SUMIF(StorytelA!C$2:C$300,A21,konwertery!N$2:N$300) -> 1 | AP21: =SUMIF(StorytelE!C$2:C$300,A21,konwertery!O$2:O$300)+SUMIF(StorytelA!C$2:C$300,A21,konwertery!P$2:P$300) -> 1.37 | AR21: =SUMIF(konwertery!U$2:U$300,A21,Audioteka!E$4:E$302) -> 0 | AS21: =SUMIF(konwertery!U$2:U$300,A21,Audioteka!O$4:O$302) -> 0 | AU21: =SUMIF(Bookbeat!A$9:A$309,A21,Bookbeat!H$9:H$309) -> 0 | AV21: =SUMIF(Bookbeat!A$9:A$309,A21,Bookbeat!L$9:L$309) -> 0
A22: 9788365156716 | B22: Geniusze, nowatorzy i skandaliści polskiej literatury, Od Przybyszewskiego do Gombrowicza (audio) | E22: =H22+K22 -> 68 | F22: =I22+L22 -> 229.32 | H22: =SUMIF(konwertery!A$2:A$300,A22,Histmag!C$2:C$300) -> 0 | I22: =SUMIF(konwertery!A$2:A$300,A22,konwertery!B$2:B$300) * 0.97 -> 0 | K22: =N22+Q22+T22+W22+Z22+AC22+AF22+AI22+AL22+AO22+AR22+AU22 -> 68 | L22: =O22+R22+U22+X22+AA22+AD22+AG22+AJ22+AM22+AP22+AS22+AV22 -> 229.32 | N22: =SUMIF(konwertery!C$2:C$300,A22,Virtualo!L$2:L$300) -> 3 | O22: =(SUMIF(konwertery!C$2:C$300,A22,Virtualo!P$2:P$300)) -> 27.66 | Q22: =SUMIF(konwertery!D$2:D$300,A22,Empik!M$2:M$300) -> 7 | R22: =SUMIF(konwertery!D$2:D$300,A22,Empik!N$2:N$300) -> 51 | T22: =SUMIF(konwertery!E$2:E$300,A22,Publio!P$2:P$300) -> 0 | U22: =SUMIF(konwertery!E$2:E$300,A22,konwertery!F$2:F$300) -> 0 | W22: =SUMIF(Legimi!D$2:D$300,A22,Legimi!G$2:G$300) -> 1 | X22: =SUMIF(Legimi!D$2:D$300,A22,Legimi!H$2:H$300) -> 9.93 | Z22: =SUMIF(konwertery!G$2:G$302,A22,Nexto!J$2:J$283) -> 0 | AA22: =SUMIF(konwertery!G$2:G$302,A22,Nexto!N$2:P$302) -> 0 | AC22: =SUMIF(Woblink!E$9:E$309,A22,Woblink!I$9:I$309) -> 1 | AD22: =SUMIF(Woblink!E$14:E$314,A22,konwertery!R$2:R$300) -> 8.51 | AF22: =SUM(SUMIF(konwertery!I$2:I$300,A22,Azymut!H$2:H$298),(SUMIF(konwertery!S$2:S$300,A22,AzymutB!H$2:H318)*2)) -> 0 | AG22: =SUM(SUMIF(konwertery!I$2:I$300,A22,konwertery!J$2:J$300),SUMIF(konwertery!S$2:S$300,A22,konwertery!T$2:T$300)) -> 0 | AI22: =SUMIF(konwertery!K$2:K$300,A22,Ebookpoint!F$14:F$312) -> 1 | AJ22: =SUMIF(konwertery!K$2:K$300,A22,Ebookpoint!M$14:M$312) -> 9.08 | AL22: =SUMIF(konwertery!L$2:L$300,A22,Nasbi!F$14:F$312) -> 0 | AM22: =SUMIF(konwertery!L$2:L$300,A22,Nasbi!K$14:K$312) -> 0 | AO22: =SUMIF(StorytelE!C$2:C$300,A22,konwertery!M$2:M$300)+SUMIF(StorytelA!C$2:C$300,A22,konwertery!N$2:N$300) -> 42 | AP22: =SUMIF(StorytelE!C$2:C$300,A22,konwertery!O$2:O$300)+SUMIF(StorytelA!C$2:C$300,A22,konwertery!P$2:P$300) -> 57.45 | AR22: =SUMIF(konwertery!U$2:U$300,A22,Audioteka!E$4:E$302) -> 6 | AS22: =SUMIF(konwertery!U$2:U$300,A22,Audioteka!O$4:O$302) -> 51.06 | AU22: =SUMIF(Bookbeat!A$9:A$309,A22,Bookbeat!H$9:H$309) -> 7 | AV22: =SUMIF(Bookbeat!A$9:A$309,A22,Bookbeat!L$9:L$309) -> 14.63
A23: 9788393463039 | B23: Gorące lata trzydzieste, Wydarzenia, które wstrząsnęły Rzeczpospolitą | E23: =H23+K23 -> 3 | F23: =I23+L23 -> 19.3418 | H23: =SUMIF(konwertery!A$2:A$300,A23,Histmag!C$2:C$300) -> 3 | I23: =SUMIF(konwertery!A$2:A$300,A23,konwertery!B$2:B$300) * 0.97 -> 19.3418 | K23: =N23+Q23+T23+W23+Z23+AC23+AF23+AI23+AL23+AO23+AR23+AU23 -> 0 | L23: =O23+R23+U23+X23+AA23+AD23+AG23+AJ23+AM23+AP23+AS23+AV23 -> 0 | N23: =SUMIF(konwertery!C$2:C$300,A23,Virtualo!L$2:L$300) -> 0 | O23: =(SUMIF(konwertery!C$2:C$300,A23,Virtualo!P$2:P$300)) -> 0 | Q23: =SUMIF(konwertery!D$2:D$300,A23,Empik!M$2:M$300) -> 0 | R23: =SUMIF(konwertery!D$2:D$300,A23,Empik!N$2:N$300) -> 0 | T23: =SUMIF(konwertery!E$2:E$300,A23,Publio!P$2:P$300) -> 0 | U23: =SUMIF(konwertery!E$2:E$300,A23,konwertery!F$2:F$300) -> 0 | W23: =SUMIF(Legimi!D$2:D$300,A23,Legimi!G$2:G$300) -> 0 | X23: =SUMIF(Legimi!D$2:D$300,A23,Legimi!H$2:H$300) -> 0 | Z23: =SUMIF(konwertery!G$2:G$302,A23,Nexto!J$2:J$283) -> 0 | AA23: =SUMIF(konwertery!G$2:G$302,A23,Nexto!N$2:P$302) -> 0 | AC23: =SUMIF(Woblink!E$9:E$309,A23,Woblink!I$9:I$309) -> 0 | AD23: =SUMIF(Woblink!E$14:E$314,A23,konwertery!R$2:R$300) -> 0 | AF23: =SUM(SUMIF(konwertery!I$2:I$300,A23,Azymut!H$2:H$298),(SUMIF(konwertery!S$2:S$300,A23,AzymutB!H$2:H319)*2)) -> 0 | AG23: =SUM(SUMIF(konwertery!I$2:I$300,A23,konwertery!J$2:J$300),SUMIF(konwertery!S$2:S$300,A23,konwertery!T$2:T$300)) -> 0 | AI23: =SUMIF(konwertery!K$2:K$300,A23,Ebookpoint!F$14:F$312) -> 0 | AJ23: =SUMIF(konwertery!K$2:K$300,A23,Ebookpoint!M$14:M$312) -> 0 | AL23: =SUMIF(konwertery!L$2:L$300,A23,Nasbi!F$14:F$312) -> 0 | AM23: =SUMIF(konwertery!L$2:L$300,A23,Nasbi!K$14:K$312) -> 0 | AO23: =SUMIF(StorytelE!C$2:C$300,A23,konwertery!M$2:M$300)+SUMIF(StorytelA!C$2:C$300,A23,konwertery!N$2:N$300) -> 0 | AP23: =SUMIF(StorytelE!C$2:C$300,A23,konwertery!O$2:O$300)+SUMIF(StorytelA!C$2:C$300,A23,konwertery!P$2:P$300) -> 0 | AR23: =SUMIF(konwertery!U$2:U$300,A23,Audioteka!E$4:E$302) -> 0 | AS23: =SUMIF(konwertery!U$2:U$300,A23,Audioteka!O$4:O$302) -> 0 | AU23: =SUMIF(Bookbeat!A$9:A$309,A23,Bookbeat!H$9:H$309) -> 0 | AV23: =SUMIF(Bookbeat!A$9:A$309,A23,Bookbeat!L$9:L$309) -> 0
A24: 9788365156457 | B24: Gorące lata trzydzieste, Wydarzenia, które wstrząsnęły Rzeczpospolitą (audio) | E24: =H24+K24 -> 41 | F24: =I24+L24 -> 75.3544 | H24: =SUMIF(konwertery!A$2:A$300,A24,Histmag!C$2:C$300) -> 1 | I24: =SUMIF(konwertery!A$2:A$300,A24,konwertery!B$2:B$300) * 0.97 -> 7.2944 | K24: =N24+Q24+T24+W24+Z24+AC24+AF24+AI24+AL24+AO24+AR24+AU24 -> 40 | L24: =O24+R24+U24+X24+AA24+AD24+AG24+AJ24+AM24+AP24+AS24+AV24 -> 68.06 | N24: =SUMIF(konwertery!C$2:C$300,A24,Virtualo!L$2:L$300) -> 0 | O24: =(SUMIF(konwertery!C$2:C$300,A24,Virtualo!P$2:P$300)) -> 0 | Q24: =SUMIF(konwertery!D$2:D$300,A24,Empik!M$2:M$300) -> 3 | R24: =SUMIF(konwertery!D$2:D$300,A24,Empik!N$2:N$300) -> 19 | T24: =SUMIF(konwertery!E$2:E$300,A24,Publio!P$2:P$300) -> 0 | U24: =SUMIF(konwertery!E$2:E$300,A24,konwertery!F$2:F$300) -> 0 | W24: =SUMIF(Legimi!D$2:D$300,A24,Legimi!G$2:G$300) -> 1 | X24: =SUMIF(Legimi!D$2:D$300,A24,Legimi!H$2:H$300) -> 7.27 | Z24: =SUMIF(konwertery!G$2:G$302,A24,Nexto!J$2:J$283) -> 0 | AA24: =SUMIF(konwertery!G$2:G$302,A24,Nexto!N$2:P$302) -> 0 | AC24: =SUMIF(Woblink!E$9:E$309,A24,Woblink!I$9:I$309) -> 0 | AD24: =SUMIF(Woblink!E$14:E$314,A24,konwertery!R$2:R$300) -> 0 | AF24: =SUM(SUMIF(konwertery!I$2:I$300,A24,Azymut!H$2:H$298),(SUMIF(konwertery!S$2:S$300,A24,AzymutB!H$2:H320)*2)) -> 0 | AG24: =SUM(SUMIF(konwertery!I$2:I$300,A24,konwertery!J$2:J$300),SUMIF(konwertery!S$2:S$300,A24,konwertery!T$2:T$300)) -> 0 | AI24: =SUMIF(konwertery!K$2:K$300,A24,Ebookpoint!F$14:F$312) -> 0 | AJ24: =SUMIF(konwertery!K$2:K$300,A24,Ebookpoint!M$14:M$312) -> 0 | AL24: =SUMIF(konwertery!L$2:L$300,A24,Nasbi!F$14:F$312) -> 0 | AM24: =SUMIF(konwertery!L$2:L$300,A24,Nasbi!K$14:K$312) -> 0 | AO24: =SUMIF(StorytelE!C$2:C$300,A24,konwertery!M$2:M$300)+SUMIF(StorytelA!C$2:C$300,A24,konwertery!N$2:N$300) -> 35 | AP24: =SUMIF(StorytelE!C$2:C$300,A24,konwertery!O$2:O$300)+SUMIF(StorytelA!C$2:C$300,A24,konwertery!P$2:P$300) -> 35.56 | AR24: =SUMIF(konwertery!U$2:U$300,A24,Audioteka!E$4:E$302) -> 1 | AS24: =SUMIF(konwertery!U$2:U$300,A24,Audioteka!O$4:O$302) -> 6.23 | AU24: =SUMIF(Bookbeat!A$9:A$309,A24,Bookbeat!H$9:H$309) -> 0 | AV24: =SUMIF(Bookbeat!A$9:A$309,A24,Bookbeat!L$9:L$309) -> 0
A25: 9788365156105 | B25: Henryk Sienkiewicz jakiego nie znamy | E25: =H25+K25 -> 0 | F25: =I25+L25 -> 0 | H25: =SUMIF(konwertery!A$2:A$300,A25,Histmag!C$2:C$300) -> 0 | I25: =SUMIF(konwertery!A$2:A$300,A25,konwertery!B$2:B$300) * 0.97 -> 0 | K25: =N25+Q25+T25+W25+Z25+AC25+AF25+AI25+AL25+AO25+AR25+AU25 -> 0 | L25: =O25+R25+U25+X25+AA25+AD25+AG25+AJ25+AM25+AP25+AS25+AV25 -> 0 | N25: =SUMIF(konwertery!C$2:C$300,A25,Virtualo!L$2:L$300) -> 0 | O25: =(SUMIF(konwertery!C$2:C$300,A25,Virtualo!P$2:P$300)) -> 0 | Q25: =SUMIF(konwertery!D$2:D$300,A25,Empik!M$2:M$300) -> 0 | R25: =SUMIF(konwertery!D$2:D$300,A25,Empik!N$2:N$300) -> 0 | T25: =SUMIF(konwertery!E$2:E$300,A25,Publio!P$2:P$300) -> 0 | U25: =SUMIF(konwertery!E$2:E$300,A25,konwertery!F$2:F$300) -> 0 | W25: =SUMIF(Legimi!D$2:D$300,A25,Legimi!G$2:G$300) -> 0 | X25: =SUMIF(Legimi!D$2:D$300,A25,Legimi!H$2:H$300) -> 0 | Z25: =SUMIF(konwertery!G$2:G$302,A25,Nexto!J$2:J$283) -> 0 | AA25: =SUMIF(konwertery!G$2:G$302,A25,Nexto!N$2:P$302) -> 0 | AC25: =SUMIF(Woblink!E$9:E$309,A25,Woblink!I$9:I$309) -> 0 | AD25: =SUMIF(Woblink!E$14:E$314,A25,konwertery!R$2:R$300) -> 0 | AF25: =SUM(SUMIF(konwertery!I$2:I$300,A25,Azymut!H$2:H$298),(SUMIF(konwertery!S$2:S$300,A25,AzymutB!H$2:H321)*2)) -> 0 | AG25: =SUM(SUMIF(konwertery!I$2:I$300,A25,konwertery!J$2:J$300),SUMIF(konwertery!S$2:S$300,A25,konwertery!T$2:T$300)) -> 0 | AI25: =SUMIF(konwertery!K$2:K$300,A25,Ebookpoint!F$14:F$312) -> 0 | AJ25: =SUMIF(konwertery!K$2:K$300,A25,Ebookpoint!M$14:M$312) -> 0 | AL25: =SUMIF(konwertery!L$2:L$300,A25,Nasbi!F$14:F$312) -> 0 | AM25: =SUMIF(konwertery!L$2:L$300,A25,Nasbi!K$14:K$312) -> 0 | AO25: =SUMIF(StorytelE!C$2:C$300,A25,konwertery!M$2:M$300)+SUMIF(StorytelA!C$2:C$300,A25,konwertery!N$2:N$300) -> 0 | AP25: =SUMIF(StorytelE!C$2:C$300,A25,konwertery!O$2:O$300)+SUMIF(StorytelA!C$2:C$300,A25,konwertery!P$2:P$300) -> 0 | AR25: =SUMIF(konwertery!U$2:U$300,A25,Audioteka!E$4:E$302) -> 0 | AS25: =SUMIF(konwertery!U$2:U$300,A25,Audioteka!O$4:O$302) -> 0 | AU25: =SUMIF(Bookbeat!A$9:A$309,A25,Bookbeat!H$9:H$309) -> 0 | AV25: =SUMIF(Bookbeat!A$9:A$309,A25,Bookbeat!L$9:L$309) -> 0
A26: 9788365156587 | B26: Hetmani i dowódcy I Rzeczpospolitej | E26: =H26+K26 -> 2 | F26: =I26+L26 -> 17.8868 | H26: =SUMIF(konwertery!A$2:A$300,A26,Histmag!C$2:C$300) -> 2 | I26: =SUMIF(konwertery!A$2:A$300,A26,konwertery!B$2:B$300) * 0.97 -> 17.8868 | K26: =N26+Q26+T26+W26+Z26+AC26+AF26+AI26+AL26+AO26+AR26+AU26 -> 0 | L26: =O26+R26+U26+X26+AA26+AD26+AG26+AJ26+AM26+AP26+AS26+AV26 -> 0 | N26: =SUMIF(konwertery!C$2:C$300,A26,Virtualo!L$2:L$300) -> 0 | O26: =(SUMIF(konwertery!C$2:C$300,A26,Virtualo!P$2:P$300)) -> 0 | Q26: =SUMIF(konwertery!D$2:D$300,A26,Empik!M$2:M$300) -> 0 | R26: =SUMIF(konwertery!D$2:D$300,A26,Empik!N$2:N$300) -> 0 | T26: =SUMIF(konwertery!E$2:E$300,A26,Publio!P$2:P$300) -> 0 | U26: =SUMIF(konwertery!E$2:E$300,A26,konwertery!F$2:F$300) -> 0 | W26: =SUMIF(Legimi!D$2:D$300,A26,Legimi!G$2:G$300) -> 0 | X26: =SUMIF(Legimi!D$2:D$300,A26,Legimi!H$2:H$300) -> 0 | Z26: =SUMIF(konwertery!G$2:G$302,A26,Nexto!J$2:J$283) -> 0 | AA26: =SUMIF(konwertery!G$2:G$302,A26,Nexto!N$2:P$302) -> 0 | AC26: =SUMIF(Woblink!E$9:E$309,A26,Woblink!I$9:I$309) -> 0 | AD26: =SUMIF(Woblink!E$14:E$314,A26,konwertery!R$2:R$300) -> 0 | AF26: =SUM(SUMIF(konwertery!I$2:I$300,A26,Azymut!H$2:H$298),(SUMIF(konwertery!S$2:S$300,A26,AzymutB!H$2:H322)*2)) -> 0 | AG26: =SUM(SUMIF(konwertery!I$2:I$300,A26,konwertery!J$2:J$300),SUMIF(konwertery!S$2:S$300,A26,konwertery!T$2:T$300)) -> 0 | AI26: =SUMIF(konwertery!K$2:K$300,A26,Ebookpoint!F$14:F$312) -> 0 | AJ26: =SUMIF(konwertery!K$2:K$300,A26,Ebookpoint!M$14:M$312) -> 0 | AL26: =SUMIF(konwertery!L$2:L$300,A26,Nasbi!F$14:F$312) -> 0 | AM26: =SUMIF(konwertery!L$2:L$300,A26,Nasbi!K$14:K$312) -> 0 | AO26: =SUMIF(StorytelE!C$2:C$300,A26,konwertery!M$2:M$300)+SUMIF(StorytelA!C$2:C$300,A26,konwertery!N$2:N$300) -> 0 | AP26: =SUMIF(StorytelE!C$2:C$300,A26,konwertery!O$2:O$300)+SUMIF(StorytelA!C$2:C$300,A26,konwertery!P$2:P$300) -> 0 | AR26: =SUMIF(konwertery!U$2:U$300,A26,Audioteka!E$4:E$302) -> 0 | AS26: =SUMIF(konwertery!U$2:U$300,A26,Audioteka!O$4:O$302) -> 0 | AU26: =SUMIF(Bookbeat!A$9:A$309,A26,Bookbeat!H$9:H$309) -> 0 | AV26: =SUMIF(Bookbeat!A$9:A$309,A26,Bookbeat!L$9:L$309) -> 0
A27: 9788365156549 | B27: Hetmani i dowódcy I Rzeczpospolitej, Część II | E27: =H27+K27 -> 3 | F27: =I27+L27 -> 27.5189 | H27: =SUMIF(konwertery!A$2:A$300,A27,Histmag!C$2:C$300) -> 3 | I27: =SUMIF(konwertery!A$2:A$300,A27,konwertery!B$2:B$300) * 0.97 -> 27.5189 | K27: =N27+Q27+T27+W27+Z27+AC27+AF27+AI27+AL27+AO27+AR27+AU27 -> 0 | L27: =O27+R27+U27+X27+AA27+AD27+AG27+AJ27+AM27+AP27+AS27+AV27 -> 0 | N27: =SUMIF(konwertery!C$2:C$300,A27,Virtualo!L$2:L$300) -> 0 | O27: =(SUMIF(konwertery!C$2:C$300,A27,Virtualo!P$2:P$300)) -> 0 | Q27: =SUMIF(konwertery!D$2:D$300,A27,Empik!M$2:M$300) -> 0 | R27: =SUMIF(konwertery!D$2:D$300,A27,Empik!N$2:N$300) -> 0 | T27: =SUMIF(konwertery!E$2:E$300,A27,Publio!P$2:P$300) -> 0 | U27: =SUMIF(konwertery!E$2:E$300,A27,konwertery!F$2:F$300) -> 0 | W27: =SUMIF(Legimi!D$2:D$300,A27,Legimi!G$2:G$300) -> 0 | X27: =SUMIF(Legimi!D$2:D$300,A27,Legimi!H$2:H$300) -> 0 | Z27: =SUMIF(konwertery!G$2:G$302,A27,Nexto!J$2:J$283) -> 0 | AA27: =SUMIF(konwertery!G$2:G$302,A27,Nexto!N$2:P$302) -> 0 | AC27: =SUMIF(Woblink!E$9:E$309,A27,Woblink!I$9:I$309) -> 0 | AD27: =SUMIF(Woblink!E$14:E$314,A27,konwertery!R$2:R$300) -> 0 | AF27: =SUM(SUMIF(konwertery!I$2:I$300,A27,Azymut!H$2:H$298),(SUMIF(konwertery!S$2:S$300,A27,AzymutB!H$2:H323)*2)) -> 0 | AG27: =SUM(SUMIF(konwertery!I$2:I$300,A27,konwertery!J$2:J$300),SUMIF(konwertery!S$2:S$300,A27,konwertery!T$2:T$300)) -> 0 | AI27: =SUMIF(konwertery!K$2:K$300,A27,Ebookpoint!F$14:F$312) -> 0 | AJ27: =SUMIF(konwertery!K$2:K$300,A27,Ebookpoint!M$14:M$312) -> 0 | AL27: =SUMIF(konwertery!L$2:L$300,A27,Nasbi!F$14:F$312) -> 0 | AM27: =SUMIF(konwertery!L$2:L$300,A27,Nasbi!K$14:K$312) -> 0 | AO27: =SUMIF(StorytelE!C$2:C$300,A27,konwertery!M$2:M$300)+SUMIF(StorytelA!C$2:C$300,A27,konwertery!N$2:N$300) -> 0 | AP27: =SUMIF(StorytelE!C$2:C$300,A27,konwertery!O$2:O$300)+SUMIF(StorytelA!C$2:C$300,A27,konwertery!P$2:P$300) -> 0 | AR27: =SUMIF(konwertery!U$2:U$300,A27,Audioteka!E$4:E$302) -> 0 | AS27: =SUMIF(konwertery!U$2:U$300,A27,Audioteka!O$4:O$302) -> 0 | AU27: =SUMIF(Bookbeat!A$9:A$309,A27,Bookbeat!H$9:H$309) -> 0 | AV27: =SUMIF(Bookbeat!A$9:A$309,A27,Bookbeat!L$9:L$309) -> 0
A28: 9788365156310 | B28: Hetmani i dowódcy I Rzeczpospolitej, Część III | E28: =H28+K28 -> 5 | F28: =I28+L28 -> 38.5889 | H28: =SUMIF(konwertery!A$2:A$300,A28,Histmag!C$2:C$300) -> 3 | I28: =SUMIF(konwertery!A$2:A$300,A28,konwertery!B$2:B$300) * 0.97 -> 27.5189 | K28: =N28+Q28+T28+W28+Z28+AC28+AF28+AI28+AL28+AO28+AR28+AU28 -> 2 | L28: =O28+R28+U28+X28+AA28+AD28+AG28+AJ28+AM28+AP28+AS28+AV28 -> 11.07 | N28: =SUMIF(konwertery!C$2:C$300,A28,Virtualo!L$2:L$300) -> 0 | O28: =(SUMIF(konwertery!C$2:C$300,A28,Virtualo!P$2:P$300)) -> 0 | Q28: =SUMIF(konwertery!D$2:D$300,A28,Empik!M$2:M$300) -> 1 | R28: =SUMIF(konwertery!D$2:D$300,A28,Empik!N$2:N$300) -> 9 | T28: =SUMIF(konwertery!E$2:E$300,A28,Publio!P$2:P$300) -> 0 | U28: =SUMIF(konwertery!E$2:E$300,A28,konwertery!F$2:F$300) -> 0 | W28: =SUMIF(Legimi!D$2:D$300,A28,Legimi!G$2:G$300) -> 0 | X28: =SUMIF(Legimi!D$2:D$300,A28,Legimi!H$2:H$300) -> 0 | Z28: =SUMIF(konwertery!G$2:G$302,A28,Nexto!J$2:J$283) -> 0 | AA28: =SUMIF(konwertery!G$2:G$302,A28,Nexto!N$2:P$302) -> 0 | AC28: =SUMIF(Woblink!E$9:E$309,A28,Woblink!I$9:I$309) -> 0 | AD28: =SUMIF(Woblink!E$14:E$314,A28,konwertery!R$2:R$300) -> 0 | AF28: =SUM(SUMIF(konwertery!I$2:I$300,A28,Azymut!H$2:H$298),(SUMIF(konwertery!S$2:S$300,A28,AzymutB!H$2:H324)*2)) -> 0 | AG28: =SUM(SUMIF(konwertery!I$2:I$300,A28,konwertery!J$2:J$300),SUMIF(konwertery!S$2:S$300,A28,konwertery!T$2:T$300)) -> 0 | AI28: =SUMIF(konwertery!K$2:K$300,A28,Ebookpoint!F$14:F$312) -> 0 | AJ28: =SUMIF(konwertery!K$2:K$300,A28,Ebookpoint!M$14:M$312) -> 0 | AL28: =SUMIF(konwertery!L$2:L$300,A28,Nasbi!F$14:F$312) -> 0 | AM28: =SUMIF(konwertery!L$2:L$300,A28,Nasbi!K$14:K$312) -> 0 | AO28: =SUMIF(StorytelE!C$2:C$300,A28,konwertery!M$2:M$300)+SUMIF(StorytelA!C$2:C$300,A28,konwertery!N$2:N$300) -> 1 | AP28: =SUMIF(StorytelE!C$2:C$300,A28,konwertery!O$2:O$300)+SUMIF(StorytelA!C$2:C$300,A28,konwertery!P$2:P$300) -> 2.07 | AR28: =SUMIF(konwertery!U$2:U$300,A28,Audioteka!E$4:E$302) -> 0 | AS28: =SUMIF(konwertery!U$2:U$300,A28,Audioteka!O$4:O$302) -> 0 | AU28: =SUMIF(Bookbeat!A$9:A$309,A28,Bookbeat!H$9:H$309) -> 0 | AV28: =SUMIF(Bookbeat!A$9:A$309,A28,Bookbeat!L$9:L$309) -> 0
A29: 9788365156792 | B29: Hetmani i dowódcy I Rzeczpospolitej (audio) | E29: =H29+K29 -> 34 | F29: =I29+L29 -> 174.1834 | H29: =SUMIF(konwertery!A$2:A$300,A29,Histmag!C$2:C$300) -> 1 | I29: =SUMIF(konwertery!A$2:A$300,A29,konwertery!B$2:B$300) * 0.97 -> 8.9434 | K29: =N29+Q29+T29+W29+Z29+AC29+AF29+AI29+AL29+AO29+AR29+AU29 -> 33 | L29: =O29+R29+U29+X29+AA29+AD29+AG29+AJ29+AM29+AP29+AS29+AV29 -> 165.24 | N29: =SUMIF(konwertery!C$2:C$300,A29,Virtualo!L$2:L$300) -> 0 | O29: =(SUMIF(konwertery!C$2:C$300,A29,Virtualo!P$2:P$300)) -> 0 | Q29: =SUMIF(konwertery!D$2:D$300,A29,Empik!M$2:M$300) -> 4 | R29: =SUMIF(konwertery!D$2:D$300,A29,Empik!N$2:N$300) -> 32 | T29: =SUMIF(konwertery!E$2:E$300,A29,Publio!P$2:P$300) -> 0 | U29: =SUMIF(konwertery!E$2:E$300,A29,konwertery!F$2:F$300) -> 0 | W29: =SUMIF(Legimi!D$2:D$300,A29,Legimi!G$2:G$300) -> 1 | X29: =SUMIF(Legimi!D$2:D$300,A29,Legimi!H$2:H$300) -> 11.93 | Z29: =SUMIF(konwertery!G$2:G$302,A29,Nexto!J$2:J$283) -> 0 | AA29: =SUMIF(konwertery!G$2:G$302,A29,Nexto!N$2:P$302) -> 0 | AC29: =SUMIF(Woblink!E$9:E$309,A29,Woblink!I$9:I$309) -> 0 | AD29: =SUMIF(Woblink!E$14:E$314,A29,konwertery!R$2:R$300) -> 0 | AF29: =SUM(SUMIF(konwertery!I$2:I$300,A29,Azymut!H$2:H$298),(SUMIF(konwertery!S$2:S$300,A29,AzymutB!H$2:H325)*2)) -> 0 | AG29: =SUM(SUMIF(konwertery!I$2:I$300,A29,konwertery!J$2:J$300),SUMIF(konwertery!S$2:S$300,A29,konwertery!T$2:T$300)) -> 0 | AI29: =SUMIF(konwertery!K$2:K$300,A29,Ebookpoint!F$14:F$312) -> 0 | AJ29: =SUMIF(konwertery!K$2:K$300,A29,Ebookpoint!M$14:M$312) -> 0 | AL29: =SUMIF(konwertery!L$2:L$300,A29,Nasbi!F$14:F$312) -> 1 | AM29: =SUMIF(konwertery!L$2:L$300,A29,Nasbi!K$14:K$312) -> 10.91 | AO29: =SUMIF(StorytelE!C$2:C$300,A29,konwertery!M$2:M$300)+SUMIF(StorytelA!C$2:C$300,A29,konwertery!N$2:N$300) -> 21 | AP29: =SUMIF(StorytelE!C$2:C$300,A29,konwertery!O$2:O$300)+SUMIF(StorytelA!C$2:C$300,A29,konwertery!P$2:P$300) -> 50.3 | AR29: =SUMIF(konwertery!U$2:U$300,A29,Audioteka!E$4:E$302) -> 6 | AS29: =SUMIF(konwertery!U$2:U$300,A29,Audioteka!O$4:O$302) -> 60.1 | AU29: =SUMIF(Bookbeat!A$9:A$309,A29,Bookbeat!H$9:H$309) -> 0 | AV29: =SUMIF(Bookbeat!A$9:A$309,A29,Bookbeat!L$9:L$309) -> 0
A30: 9788362329984 | B30: Historia, Poradnik maturalny | E30: =H30+K30 -> 2 | F30: =I30+L30 -> 12.7458 | H30: =SUMIF(konwertery!A$2:A$300,A30,Histmag!C$2:C$300) -> 2 | I30: =SUMIF(konwertery!A$2:A$300,A30,konwertery!B$2:B$300) * 0.97 -> 12.7458 | K30: =N30+Q30+T30+W30+Z30+AC30+AF30+AI30+AL30+AO30+AR30+AU30 -> 0 | L30: =O30+R30+U30+X30+AA30+AD30+AG30+AJ30+AM30+AP30+AS30+AV30 -> 0 | N30: =SUMIF(konwertery!C$2:C$300,A30,Virtualo!L$2:L$300) -> 0 | O30: =(SUMIF(konwertery!C$2:C$300,A30,Virtualo!P$2:P$300)) -> 0 | Q30: =SUMIF(konwertery!D$2:D$300,A30,Empik!M$2:M$300) -> 0 | R30: =SUMIF(konwertery!D$2:D$300,A30,Empik!N$2:N$300) -> 0 | T30: =SUMIF(konwertery!E$2:E$300,A30,Publio!P$2:P$300) -> 0 | U30: =SUMIF(konwertery!E$2:E$300,A30,konwertery!F$2:F$300) -> 0 | W30: =SUMIF(Legimi!D$2:D$300,A30,Legimi!G$2:G$300) -> 0 | X30: =SUMIF(Legimi!D$2:D$300,A30,Legimi!H$2:H$300) -> 0 | Z30: =SUMIF(konwertery!G$2:G$302,A30,Nexto!J$2:J$283) -> 0 | AA30: =SUMIF(konwertery!G$2:G$302,A30,Nexto!N$2:P$302) -> 0 | AC30: =SUMIF(Woblink!E$9:E$309,A30,Woblink!I$9:I$309) -> 0 | AD30: =SUMIF(Woblink!E$14:E$314,A30,konwertery!R$2:R$300) -> 0 | AF30: =SUM(SUMIF(konwertery!I$2:I$300,A30,Azymut!H$2:H$298),(SUMIF(konwertery!S$2:S$300,A30,AzymutB!H$2:H326)*2)) -> 0 | AG30: =SUM(SUMIF(konwertery!I$2:I$300,A30,konwertery!J$2:J$300),SUMIF(konwertery!S$2:S$300,A30,konwertery!T$2:T$300)) -> 0 | AI30: =SUMIF(konwertery!K$2:K$300,A30,Ebookpoint!F$14:F$312) -> 0 | AJ30: =SUMIF(konwertery!K$2:K$300,A30,Ebookpoint!M$14:M$312) -> 0 | AL30: =SUMIF(konwertery!L$2:L$300,A30,Nasbi!F$14:F$312) -> 0 | AM30: =SUMIF(konwertery!L$2:L$300,A30,Nasbi!K$14:K$312) -> 0 | AO30: =SUMIF(StorytelE!C$2:C$300,A30,konwertery!M$2:M$300)+SUMIF(StorytelA!C$2:C$300,A30,konwertery!N$2:N$300) -> 0 | AP30: =SUMIF(StorytelE!C$2:C$300,A30,konwertery!O$2:O$300)+SUMIF(StorytelA!C$2:C$300,A30,konwertery!P$2:P$300) -> 0 | AR30: =SUMIF(konwertery!U$2:U$300,A30,Audioteka!E$4:E$302) -> 0 | AS30: =SUMIF(konwertery!U$2:U$300,A30,Audioteka!O$4:O$302) -> 0 | AU30: =SUMIF(Bookbeat!A$9:A$309,A30,Bookbeat!H$9:H$309) -> 0 | AV30: =SUMIF(Bookbeat!A$9:A$309,A30,Bookbeat!L$9:L$309) -> 0
A31: 9788365156389 | B31: II wojna światowa wybuchła w Szymankowie | E31: =H31+K31 -> 3 | F31: =I31+L31 -> 19.51 | H31: =SUMIF(konwertery!A$2:A$300,A31,Histmag!C$2:C$300) -> 0 | I31: =SUMIF(konwertery!A$2:A$300,A31,konwertery!B$2:B$300) * 0.97 -> 0 | K31: =N31+Q31+T31+W31+Z31+AC31+AF31+AI31+AL31+AO31+AR31+AU31 -> 3 | L31: =O31+R31+U31+X31+AA31+AD31+AG31+AJ31+AM31+AP31+AS31+AV31 -> 19.51 | N31: =SUMIF(konwertery!C$2:C$300,A31,Virtualo!L$2:L$300) -> 0 | O31: =(SUMIF(konwertery!C$2:C$300,A31,Virtualo!P$2:P$300)) -> 0 | Q31: =SUMIF(konwertery!D$2:D$300,A31,Empik!M$2:M$300) -> 0 | R31: =SUMIF(konwertery!D$2:D$300,A31,Empik!N$2:N$300) -> 0 | T31: =SUMIF(konwertery!E$2:E$300,A31,Publio!P$2:P$300) -> 1 | U31: =SUMIF(konwertery!E$2:E$300,A31,konwertery!F$2:F$300) -> 6.23 | W31: =SUMIF(Legimi!D$2:D$300,A31,Legimi!G$2:G$300) -> 0 | X31: =SUMIF(Legimi!D$2:D$300,A31,Legimi!H$2:H$300) -> 0 | Z31: =SUMIF(konwertery!G$2:G$302,A31,Nexto!J$2:J$283) -> 0 | AA31: =SUMIF(konwertery!G$2:G$302,A31,Nexto!N$2:P$302) -> 0 | AC31: =SUMIF(Woblink!E$9:E$309,A31,Woblink!I$9:I$309) -> 0 | AD31: =SUMIF(Woblink!E$14:E$314,A31,konwertery!R$2:R$300) -> 0 | AF31: =SUM(SUMIF(konwertery!I$2:I$300,A31,Azymut!H$2:H$298),(SUMIF(konwertery!S$2:S$300,A31,AzymutB!H$2:H327)*2)) -> 0 | AG31: =SUM(SUMIF(konwertery!I$2:I$300,A31,konwertery!J$2:J$300),SUMIF(konwertery!S$2:S$300,A31,konwertery!T$2:T$300)) -> 0 | AI31: =SUMIF(konwertery!K$2:K$300,A31,Ebookpoint!F$14:F$312) -> 2 | AJ31: =SUMIF(konwertery!K$2:K$300,A31,Ebookpoint!M$14:M$312) -> 13.28 | AL31: =SUMIF(konwertery!L$2:L$300,A31,Nasbi!F$14:F$312) -> 0 | AM31: =SUMIF(konwertery!L$2:L$300,A31,Nasbi!K$14:K$312) -> 0 | AO31: =SUMIF(StorytelE!C$2:C$300,A31,konwertery!M$2:M$300)+SUMIF(StorytelA!C$2:C$300,A31,konwertery!N$2:N$300) -> 0 | AP31: =SUMIF(StorytelE!C$2:C$300,A31,konwertery!O$2:O$300)+SUMIF(StorytelA!C$2:C$300,A31,konwertery!P$2:P$300) -> 0 | AR31: =SUMIF(konwertery!U$2:U$300,A31,Audioteka!E$4:E$302) -> 0 | AS31: =SUMIF(konwertery!U$2:U$300,A31,Audioteka!O$4:O$302) -> 0 | AU31: =SUMIF(Bookbeat!A$9:A$309,A31,Bookbeat!H$9:H$309) -> 0 | AV31: =SUMIF(Bookbeat!A$9:A$309,A31,Bookbeat!L$9:L$309) -> 0
... A37: 9788365156839 | B37: Jedz, pij i popuszczaj pasa, Staropolskie obyczaje i rozrywki (audio) | E37: =H37+K37 -> 74 | F37: =I37+L37 -> 164.8589 | H37: =SUMIF(konwertery!A$2:A$300,A37,Histmag!C$2:C$300) -> 1 | I37: =SUMIF(konwertery!A$2:A$300,A37,konwertery!B$2:B$300) * 0.97 -> 7.1489 | K37: =N37+Q37+T37+W37+Z37+AC37+AF37+AI37+AL37+AO37+AR37+AU37 -> 73 | L37: =O37+R37+U37+X37+AA37+AD37+AG37+AJ37+AM37+AP37+AS37+AV37 -> 157.71 | N37: =SUMIF(konwertery!C$2:C$300,A37,Virtualo!L$2:L$300) -> 0 | O37: =(SUMIF(konwertery!C$2:C$300,A37,Virtualo!P$2:P$300)) -> 0 | Q37: =SUMIF(konwertery!D$2:D$300,A37,Empik!M$2:M$300) -> 7 | R37: =SUMIF(konwertery!D$2:D$300,A37,Empik!N$2:N$300) -> 59 | T37: =SUMIF(konwertery!E$2:E$300,A37,Publio!P$2:P$300) -> 0 | U37: =SUMIF(konwertery!E$2:E$300,A37,konwertery!F$2:F$300) -> 0 | W37: =SUMIF(Legimi!D$2:D$300,A37,Legimi!G$2:G$300) -> 1 | X37: =SUMIF(Legimi!D$2:D$300,A37,Legimi!H$2:H$300) -> 9.93 | Z37: =SUMIF(konwertery!G$2:G$302,A37,Nexto!J$2:J$283) -> 0 | AA37: =SUMIF(konwertery!G$2:G$302,A37,Nexto!N$2:P$302) -> 0 | AC37: =SUMIF(Woblink!E$9:E$309,A37,Woblink!I$9:I$309) -> 0 | AD37: =SUMIF(Woblink!E$14:E$314,A37,konwertery!R$2:R$300) -> 0 | AF37: =SUM(SUMIF(konwertery!I$2:I$300,A37,Azymut!H$2:H$298),(SUMIF(konwertery!S$2:S$300,A37,AzymutB!H$2:H333)*2)) -> 0 | AG37: =SUM(SUMIF(konwertery!I$2:I$300,A37,konwertery!J$2:J$300),SUMIF(konwertery!S$2:S$300,A37,konwertery!T$2:T$300)) -> 0 | AI37: =SUMIF(konwertery!K$2:K$300,A37,Ebookpoint!F$14:F$312) -> 0 | AJ37: =SUMIF(konwertery!K$2:K$300,A37,Ebookpoint!M$14:M$312) -> 0 | AL37: =SUMIF(konwertery!L$2:L$300,A37,Nasbi!F$14:F$312) -> 0 | AM37: =SUMIF(konwertery!L$2:L$300,A37,Nasbi!K$14:K$312) -> 0 | AO37: =SUMIF(StorytelE!C$2:C$300,A37,konwertery!M$2:M$300)+SUMIF(StorytelA!C$2:C$300,A37,konwertery!N$2:N$300) -> 63 | AP37: =SUMIF(StorytelE!C$2:C$300,A37,konwertery!O$2:O$300)+SUMIF(StorytelA!C$2:C$300,A37,konwertery!P$2:P$300) -> 85.52 | AR37: =SUMIF(konwertery!U$2:U$300,A37,Audioteka!E$4:E$302) -> 0 | AS37: =SUMIF(konwertery!U$2:U$300,A37,Audioteka!O$4:O$302) -> 0 | AU37: =SUMIF(Bookbeat!A$9:A$309,A37,Bookbeat!H$9:H$309) -> 2 | AV37: =SUMIF(Bookbeat!A$9:A$309,A37,Bookbeat!L$9:L$309) -> 3.26
A38: 9788365156259 | B38: Kobieta w świecie Azteków | E38: =H38+K38 -> 0 | F38: =I38+L38 -> 0 | H38: =SUMIF(konwertery!A$2:A$300,A38,Histmag!C$2:C$300) -> 0 | I38: =SUMIF(konwertery!A$2:A$300,A38,konwertery!B$2:B$300) * 0.97 -> 0 | K38: =N38+Q38+T38+W38+Z38+AC38+AF38+AI38+AL38+AO38+AR38+AU38 -> 0 | L38: =O38+R38+U38+X38+AA38+AD38+AG38+AJ38+AM38+AP38+AS38+AV38 -> 0 | N38: =SUMIF(konwertery!C$2:C$300,A38,Virtualo!L$2:L$300) -> 0 | O38: =(SUMIF(konwertery!C$2:C$300,A38,Virtualo!P$2:P$300)) -> 0 | Q38: =SUMIF(konwertery!D$2:D$300,A38,Empik!M$2:M$300) -> 0 | R38: =SUMIF(konwertery!D$2:D$300,A38,Empik!N$2:N$300) -> 0 | T38: =SUMIF(konwertery!E$2:E$300,A38,Publio!P$2:P$300) -> 0 | U38: =SUMIF(konwertery!E$2:E$300,A38,konwertery!F$2:F$300) -> 0 | W38: =SUMIF(Legimi!D$2:D$300,A38,Legimi!G$2:G$300) -> 0 | X38: =SUMIF(Legimi!D$2:D$300,A38,Legimi!H$2:H$300) -> 0 | Z38: =SUMIF(konwertery!G$2:G$302,A38,Nexto!J$2:J$283) -> 0 | AA38: =SUMIF(konwertery!G$2:G$302,A38,Nexto!N$2:P$302) -> 0 | AC38: =SUMIF(Woblink!E$9:E$309,A38,Woblink!I$9:I$309) -> 0 | AD38: =SUMIF(Woblink!E$14:E$314,A38,konwertery!R$2:R$300) -> 0 | AF38: =SUM(SUMIF(konwertery!I$2:I$300,A38,Azymut!H$2:H$298),(SUMIF(konwertery!S$2:S$300,A38,AzymutB!H$2:H333)*2)) -> 0 | AG38: =SUM(SUMIF(konwertery!I$2:I$300,A38,konwertery!J$2:J$300),SUMIF(konwertery!S$2:S$300,A38,konwertery!T$2:T$300)) -> 0 | AI38: =SUMIF(konwertery!K$2:K$300,A38,Ebookpoint!F$14:F$312) -> 0 | AJ38: =SUMIF(konwertery!K$2:K$300,A38,Ebookpoint!M$14:M$312) -> 0 | AL38: =SUMIF(konwertery!L$2:L$300,A38,Nasbi!F$14:F$312) -> 0 | AM38: =SUMIF(konwertery!L$2:L$300,A38,Nasbi!K$14:K$312) -> 0 | AO38: =SUMIF(StorytelE!C$2:C$300,A38,konwertery!M$2:M$300)+SUMIF(StorytelA!C$2:C$300,A38,konwertery!N$2:N$300) -> 0 | AP38: =SUMIF(StorytelE!C$2:C$300,A38,konwertery!O$2:O$300)+SUMIF(StorytelA!C$2:C$300,A38,konwertery!P$2:P$300) -> 0 | AR38: =SUMIF(konwertery!U$2:U$300,A38,Audioteka!E$4:E$302) -> 0 | AS38: =SUMIF(konwertery!U$2:U$300,A38,Audioteka!O$4:O$302) -> 0 | AU38: =SUMIF(Bookbeat!A$9:A$309,A38,Bookbeat!H$9:H$309) -> 0 | AV38: =SUMIF(Bookbeat!A$9:A$309,A38,Bookbeat!L$9:L$309) -> 0
A39: 9788365156228 | B39: Kobiety króla Kazimierza III Wielkiego | E39: =H39+K39 -> 1 | F39: =I39+L39 -> 1.71 | H39: =SUMIF(konwertery!A$2:A$300,A39,Histmag!C$2:C$300) -> 0 | I39: =SUMIF(konwertery!A$2:A$300,A39,konwertery!B$2:B$300) * 0.97 -> 0 | K39: =N39+Q39+T39+W39+Z39+AC39+AF39+AI39+AL39+AO39+AR39+AU39 -> 1 | L39: =O39+R39+U39+X39+AA39+AD39+AG39+AJ39+AM39+AP39+AS39+AV39 -> 1.71 | N39: =SUMIF(konwertery!C$2:C$300,A39,Virtualo!L$2:L$300) -> 0 | O39: =(SUMIF(konwertery!C$2:C$300,A39,Virtualo!P$2:P$300)) -> 0 | Q39: =SUMIF(konwertery!D$2:D$300,A39,Empik!M$2:M$300) -> 0 | R39: =SUMIF(konwertery!D$2:D$300,A39,Empik!N$2:N$300) -> 0 | T39: =SUMIF(konwertery!E$2:E$300,A39,Publio!P$2:P$300) -> 0 | U39: =SUMIF(konwertery!E$2:E$300,A39,konwertery!F$2:F$300) -> 0 | W39: =SUMIF(Legimi!D$2:D$300,A39,Legimi!G$2:G$300) -> 0 | X39: =SUMIF(Legimi!D$2:D$300,A39,Legimi!H$2:H$300) -> 0 | Z39: =SUMIF(konwertery!G$2:G$302,A39,Nexto!J$2:J$283) -> 0 | AA39: =SUMIF(konwertery!G$2:G$302,A39,Nexto!N$2:P$302) -> 0 | AC39: =SUMIF(Woblink!E$9:E$309,A39,Woblink!I$9:I$309) -> 0 | AD39: =SUMIF(Woblink!E$14:E$314,A39,konwertery!R$2:R$300) -> 0 | AF39: =SUM(SUMIF(konwertery!I$2:I$300,A39,Azymut!H$2:H$298),(SUMIF(konwertery!S$2:S$300,A39,AzymutB!H$2:H334)*2)) -> 0 | AG39: =SUM(SUMIF(konwertery!I$2:I$300,A39,konwertery!J$2:J$300),SUMIF(konwertery!S$2:S$300,A39,konwertery!T$2:T$300)) -> 0 | AI39: =SUMIF(konwertery!K$2:K$300,A39,Ebookpoint!F$14:F$312) -> 0 | AJ39: =SUMIF(konwertery!K$2:K$300,A39,Ebookpoint!M$14:M$312) -> 0 | AL39: =SUMIF(konwertery!L$2:L$300,A39,Nasbi!F$14:F$312) -> 0 | AM39: =SUMIF(konwertery!L$2:L$300,A39,Nasbi!K$14:K$312) -> 0 | AO39: =SUMIF(StorytelE!C$2:C$300,A39,konwertery!M$2:M$300)+SUMIF(StorytelA!C$2:C$300,A39,konwertery!N$2:N$300) -> 1 | AP39: =SUMIF(StorytelE!C$2:C$300,A39,konwertery!O$2:O$300)+SUMIF(StorytelA!C$2:C$300,A39,konwertery!P$2:P$300) -> 1.71 | AR39: =SUMIF(konwertery!U$2:U$300,A39,Audioteka!E$4:E$302) -> 0 | AS39: =SUMIF(konwertery!U$2:U$300,A39,Audioteka!O$4:O$302) -> 0 | AU39: =SUMIF(Bookbeat!A$9:A$309,A39,Bookbeat!H$9:H$309) -> 0 | AV39: =SUMIF(Bookbeat!A$9:A$309,A39,Bookbeat!L$9:L$309) -> 0
A40: 9788365156129 | B40: Kochanki, bastardzi, oszuści, Nieprawe łoża królów Polski: XVI–XVIII wiek | E40: =H40+K40 -> 3 | F40: =I40+L40 -> 24.01 | H40: =SUMIF(konwertery!A$2:A$300,A40,Histmag!C$2:C$300) -> 0 | I40: =SUMIF(konwertery!A$2:A$300,A40,konwertery!B$2:B$300) * 0.97 -> 0 | K40: =N40+Q40+T40+W40+Z40+AC40+AF40+AI40+AL40+AO40+AR40+AU40 -> 3 | L40: =O40+R40+U40+X40+AA40+AD40+AG40+AJ40+AM40+AP40+AS40+AV40 -> 24.01 | N40: =SUMIF(konwertery!C$2:C$300,A40,Virtualo!L$2:L$300) -> 0 | O40: =(SUMIF(konwertery!C$2:C$300,A40,Virtualo!P$2:P$300)) -> 0 | Q40: =SUMIF(konwertery!D$2:D$300,A40,Empik!M$2:M$300) -> 1 | R40: =SUMIF(konwertery!D$2:D$300,A40,Empik!N$2:N$300) -> 5 | T40: =SUMIF(konwertery!E$2:E$300,A40,Publio!P$2:P$300) -> 0 | U40: =SUMIF(konwertery!E$2:E$300,A40,konwertery!F$2:F$300) -> 0 | W40: =SUMIF(Legimi!D$2:D$300,A40,Legimi!G$2:G$300) -> 1 | X40: =SUMIF(Legimi!D$2:D$300,A40,Legimi!H$2:H$300) -> 9.93 | Z40: =SUMIF(konwertery!G$2:G$302,A40,Nexto!J$2:J$283) -> 0 | AA40: =SUMIF(konwertery!G$2:G$302,A40,Nexto!N$2:P$302) -> 0 | AC40: =SUMIF(Woblink!E$9:E$309,A40,Woblink!I$9:I$309) -> 0 | AD40: =SUMIF(Woblink!E$14:E$314,A40,konwertery!R$2:R$300) -> 0 | AF40: =SUM(SUMIF(konwertery!I$2:I$300,A40,Azymut!H$2:H$298),(SUMIF(konwertery!S$2:S$300,A40,AzymutB!H$2:H335)*2)) -> 0 | AG40: =SUM(SUMIF(konwertery!I$2:I$300,A40,konwertery!J$2:J$300),SUMIF(konwertery!S$2:S$300,A40,konwertery!T$2:T$300)) -> 0 | AI40: =SUMIF(konwertery!K$2:K$300,A40,Ebookpoint!F$14:F$312) -> 1 | AJ40: =SUMIF(konwertery!K$2:K$300,A40,Ebookpoint!M$14:M$312) -> 9.08 | AL40: =SUMIF(konwertery!L$2:L$300,A40,Nasbi!F$14:F$312) -> 0 | AM40: =SUMIF(konwertery!L$2:L$300,A40,Nasbi!K$14:K$312) -> 0 | AO40: =SUMIF(StorytelE!C$2:C$300,A40,konwertery!M$2:M$300)+SUMIF(StorytelA!C$2:C$300,A40,konwertery!N$2:N$300) -> 0 | AP40: =SUMIF(StorytelE!C$2:C$300,A40,konwertery!O$2:O$300)+SUMIF(StorytelA!C$2:C$300,A40,konwertery!P$2:P$300) -> 0 | AR40: =SUMIF(konwertery!U$2:U$300,A40,Audioteka!E$4:E$302) -> 0 | AS40: =SUMIF(konwertery!U$2:U$300,A40,Audioteka!O$4:O$302) -> 0 | AU40: =SUMIF(Bookbeat!A$9:A$309,A40,Bookbeat!H$9:H$309) -> 0 | AV40: =SUMIF(Bookbeat!A$9:A$309,A40,Bookbeat!L$9:L$309) -> 0
A41: 9788365156327 | B41: Kochanki, bastardzi, oszuści, Nieprawe łoża królów Polski: XVI–XVIII wiek (audio) | E41: =H41+K41 -> 18 | F41: =I41+L41 -> 29.89 | H41: =SUMIF(konwertery!A$2:A$300,A41,Histmag!C$2:C$300) -> 0 | I41: =SUMIF(konwertery!A$2:A$300,A41,konwertery!B$2:B$300) * 0.97 -> 0 | K41: =N41+Q41+T41+W41+Z41+AC41+AF41+AI41+AL41+AO41+AR41+AU41 -> 18 | L41: =O41+R41+U41+X41+AA41+AD41+AG41+AJ41+AM41+AP41+AS41+AV41 -> 29.89 | N41: =SUMIF(konwertery!C$2:C$300,A41,Virtualo!L$2:L$300) -> 0 | O41: =(SUMIF(konwertery!C$2:C$300,A41,Virtualo!P$2:P$300)) -> 0 | Q41: =SUMIF(konwertery!D$2:D$300,A41,Empik!M$2:M$300) -> 2 | R41: =SUMIF(konwertery!D$2:D$300,A41,Empik!N$2:N$300) -> 14 | T41: =SUMIF(konwertery!E$2:E$300,A41,Publio!P$2:P$300) -> 0 | U41: =SUMIF(konwertery!E$2:E$300,A41,konwertery!F$2:F$300) -> 0 | W41: =SUMIF(Legimi!D$2:D$300,A41,Legimi!G$2:G$300) -> 0 | X41: =SUMIF(Legimi!D$2:D$300,A41,Legimi!H$2:H$300) -> 0 | Z41: =SUMIF(konwertery!G$2:G$302,A41,Nexto!J$2:J$283) -> 0 | AA41: =SUMIF(konwertery!G$2:G$302,A41,Nexto!N$2:P$302) -> 0 | AC41: =SUMIF(Woblink!E$9:E$309,A41,Woblink!I$9:I$309) -> 0 | AD41: =SUMIF(Woblink!E$14:E$314,A41,konwertery!R$2:R$300) -> 0 | AF41: =SUM(SUMIF(konwertery!I$2:I$300,A41,Azymut!H$2:H$298),(SUMIF(konwertery!S$2:S$300,A41,AzymutB!H$2:H336)*2)) -> 0 | AG41: =SUM(SUMIF(konwertery!I$2:I$300,A41,konwertery!J$2:J$300),SUMIF(konwertery!S$2:S$300,A41,konwertery!T$2:T$300)) -> 0 | AI41: =SUMIF(konwertery!K$2:K$300,A41,Ebookpoint!F$14:F$312) -> 0 | AJ41: =SUMIF(konwertery!K$2:K$300,A41,Ebookpoint!M$14:M$312) -> 0 | AL41: =SUMIF(konwertery!L$2:L$300,A41,Nasbi!F$14:F$312) -> 0 | AM41: =SUMIF(konwertery!L$2:L$300,A41,Nasbi!K$14:K$312) -> 0 | AO41: =SUMIF(StorytelE!C$2:C$300,A41,konwertery!M$2:M$300)+SUMIF(StorytelA!C$2:C$300,A41,konwertery!N$2:N$300) -> 16 | AP41: =SUMIF(StorytelE!C$2:C$300,A41,konwertery!O$2:O$300)+SUMIF(StorytelA!C$2:C$300,A41,konwertery!P$2:P$300) -> 15.89 | AR41: =SUMIF(konwertery!U$2:U$300,A41,Audioteka!E$4:E$302) -> 0 | AS41: =SUMIF(konwertery!U$2:U$300,A41,Audioteka!O$4:O$302) -> 0 | AU41: =SUMIF(Bookbeat!A$9:A$309,A41,Bookbeat!H$9:H$309) -> 0 | AV41: =SUMIF(Bookbeat!A$9:A$309,A41,Bookbeat!L$9:L$309) -> 0
A42: 9788365156426 | B42: Konkwista, W imię Boga, złota i Hiszpanii | E42: =H42+K42 -> 3 | F42: =I42+L42 -> 39.297 | H42: =SUMIF(konwertery!A$2:A$300,A42,Histmag!C$2:C$300) -> 1 | I42: =SUMIF(konwertery!A$2:A$300,A42,konwertery!B$2:B$300) * 0.97 -> 15.617 | K42: =N42+Q42+T42+W42+Z42+AC42+AF42+AI42+AL42+AO42+AR42+AU42 -> 2 | L42: =O42+R42+U42+X42+AA42+AD42+AG42+AJ42+AM42+AP42+AS42+AV42 -> 23.68 | N42: =SUMIF(konwertery!C$2:C$300,A42,Virtualo!L$2:L$300) -> 1 | O42: =(SUMIF(konwertery!C$2:C$300,A42,Virtualo!P$2:P$300)) -> 12.31 | Q42: =SUMIF(konwertery!D$2:D$300,A42,Empik!M$2:M$300) -> 0 | R42: =SUMIF(konwertery!D$2:D$300,A42,Empik!N$2:N$300) -> 0 | T42: =SUMIF(konwertery!E$2:E$300,A42,Publio!P$2:P$300) -> 0 | U42: =SUMIF(konwertery!E$2:E$300,A42,konwertery!F$2:F$300) -> 0 | W42: =SUMIF(Legimi!D$2:D$300,A42,Legimi!G$2:G$300) -> 0 | X42: =SUMIF(Legimi!D$2:D$300,A42,Legimi!H$2:H$300) -> 0 | Z42: =SUMIF(konwertery!G$2:G$302,A42,Nexto!J$2:J$283) -> 0 | AA42: =SUMIF(konwertery!G$2:G$302,A42,Nexto!N$2:P$302) -> 0 | AC42: =SUMIF(Woblink!E$9:E$309,A42,Woblink!I$9:I$309) -> 1 | AD42: =SUMIF(Woblink!E$14:E$314,A42,konwertery!R$2:R$300) -> 11.37 | AF42: =SUM(SUMIF(konwertery!I$2:I$300,A42,Azymut!H$2:H$298),(SUMIF(konwertery!S$2:S$300,A42,AzymutB!H$2:H337)*2)) -> 0 | AG42: =SUM(SUMIF(konwertery!I$2:I$300,A42,konwertery!J$2:J$300),SUMIF(konwertery!S$2:S$300,A42,konwertery!T$2:T$300)) -> 0 | AI42: =SUMIF(konwertery!K$2:K$300,A42,Ebookpoint!F$14:F$312) -> 0 | AJ42: =SUMIF(konwertery!K$2:K$300,A42,Ebookpoint!M$14:M$312) -> 0 | AL42: =SUMIF(konwertery!L$2:L$300,A42,Nasbi!F$14:F$312) -> 0 | AM42: =SUMIF(konwertery!L$2:L$300,A42,Nasbi!K$14:K$312) -> 0 | AO42: =SUMIF(StorytelE!C$2:C$300,A42,konwertery!M$2:M$300)+SUMIF(StorytelA!C$2:C$300,A42,konwertery!N$2:N$300) -> 0 | AP42: =SUMIF(StorytelE!C$2:C$300,A42,konwertery!O$2:O$300)+SUMIF(StorytelA!C$2:C$300,A42,konwertery!P$2:P$300) -> 0 | AR42: =SUMIF(konwertery!U$2:U$300,A42,Audioteka!E$4:E$302) -> 0 | AS42: =SUMIF(konwertery!U$2:U$300,A42,Audioteka!O$4:O$302) -> 0 | AU42: =SUMIF(Bookbeat!A$9:A$309,A42,Bookbeat!H$9:H$309) -> 0 | AV42: =SUMIF(Bookbeat!A$9:A$309,A42,Bookbeat!L$9:L$309) -> 0
A43: 9788365156037 | B43: Krwawy Kaukaz: Czeczenia | E43: =H43+K43 -> 1 | F43: =I43+L43 -> 1.25 | H43: =SUMIF(konwertery!A$2:A$300,A43,Histmag!C$2:C$300) -> 0 | I43: =SUMIF(konwertery!A$2:A$300,A43,konwertery!B$2:B$300) * 0.97 -> 0 | K43: =N43+Q43+T43+W43+Z43+AC43+AF43+AI43+AL43+AO43+AR43+AU43 -> 1 | L43: =O43+R43+U43+X43+AA43+AD43+AG43+AJ43+AM43+AP43+AS43+AV43 -> 1.25 | N43: =SUMIF(konwertery!C$2:C$300,A43,Virtualo!L$2:L$300) -> 0 | O43: =(SUMIF(konwertery!C$2:C$300,A43,Virtualo!P$2:P$300)) -> 0 | Q43: =SUMIF(konwertery!D$2:D$300,A43,Empik!M$2:M$300) -> 0 | R43: =SUMIF(konwertery!D$2:D$300,A43,Empik!N$2:N$300) -> 0 | T43: =SUMIF(konwertery!E$2:E$300,A43,Publio!P$2:P$300) -> 0 | U43: =SUMIF(konwertery!E$2:E$300,A43,konwertery!F$2:F$300) -> 0 | W43: =SUMIF(Legimi!D$2:D$300,A43,Legimi!G$2:G$300) -> 0 | X43: =SUMIF(Legimi!D$2:D$300,A43,Legimi!H$2:H$300) -> 0 | Z43: =SUMIF(konwertery!G$2:G$302,A43,Nexto!J$2:J$283) -> 0 | AA43: =SUMIF(konwertery!G$2:G$302,A43,Nexto!N$2:P$302) -> 0 | AC43: =SUMIF(Woblink!E$9:E$309,A43,Woblink!I$9:I$309) -> 0 | AD43: =SUMIF(Woblink!E$14:E$314,A43,konwertery!R$2:R$300) -> 0 | AF43: =SUM(SUMIF(konwertery!I$2:I$300,A43,Azymut!H$2:H$298),(SUMIF(konwertery!S$2:S$300,A43,AzymutB!H$2:H338)*2)) -> 0 | AG43: =SUM(SUMIF(konwertery!I$2:I$300,A43,konwertery!J$2:J$300),SUMIF(konwertery!S$2:S$300,A43,konwertery!T$2:T$300)) -> 0 | AI43: =SUMIF(konwertery!K$2:K$300,A43,Ebookpoint!F$14:F$312) -> 0 | AJ43: =SUMIF(konwertery!K$2:K$300,A43,Ebookpoint!M$14:M$312) -> 0 | AL43: =SUMIF(konwertery!L$2:L$300,A43,Nasbi!F$14:F$312) -> 0 | AM43: =SUMIF(konwertery!L$2:L$300,A43,Nasbi!K$14:K$312) -> 0 | AO43: =SUMIF(StorytelE!C$2:C$300,A43,konwertery!M$2:M$300)+SUMIF(StorytelA!C$2:C$300,A43,konwertery!N$2:N$300) -> 1 | AP43: =SUMIF(StorytelE!C$2:C$300,A43,konwertery!O$2:O$300)+SUMIF(StorytelA!C$2:C$300,A43,konwertery!P$2:P$300) -> 1.25 | AR43: =SUMIF(konwertery!U$2:U$300,A43,Audioteka!E$4:E$302) -> 0 | AS43: =SUMIF(konwertery!U$2:U$300,A43,Audioteka!O$4:O$302) -> 0 | AU43: =SUMIF(Bookbeat!A$9:A$309,A43,Bookbeat!H$9:H$309) -> 0 | AV43: =SUMIF(Bookbeat!A$9:A$309,A43,Bookbeat!L$9:L$309) -> 0
A44: 9788365156563 | B44: Kryminalne Wilno | E44: =H44+K44 -> 3 | F44: =I44+L44 -> 23.8862 | H44: =SUMIF(konwertery!A$2:A$300,A44,Histmag!C$2:C$300) -> 1 | I44: =SUMIF(konwertery!A$2:A$300,A44,konwertery!B$2:B$300) * 0.97 -> 10.1462 | K44: =N44+Q44+T44+W44+Z44+AC44+AF44+AI44+AL44+AO44+AR44+AU44 -> 2 | L44: =O44+R44+U44+X44+AA44+AD44+AG44+AJ44+AM44+AP44+AS44+AV44 -> 13.74 | N44: =SUMIF(konwertery!C$2:C$300,A44,Virtualo!L$2:L$300) -> 0 | O44: =(SUMIF(konwertery!C$2:C$300,A44,Virtualo!P$2:P$300)) -> 0 | Q44: =SUMIF(konwertery!D$2:D$300,A44,Empik!M$2:M$300) -> 0 | R44: =SUMIF(konwertery!D$2:D$300,A44,Empik!N$2:N$300) -> 0 | T44: =SUMIF(konwertery!E$2:E$300,A44,Publio!P$2:P$300) -> 0 | U44: =SUMIF(konwertery!E$2:E$300,A44,konwertery!F$2:F$300) -> 0 | W44: =SUMIF(Legimi!D$2:D$300,A44,Legimi!G$2:G$300) -> 0 | X44: =SUMIF(Legimi!D$2:D$300,A44,Legimi!H$2:H$300) -> 0 | Z44: =SUMIF(konwertery!G$2:G$302,A44,Nexto!J$2:J$283) -> 0 | AA44: =SUMIF(konwertery!G$2:G$302,A44,Nexto!N$2:P$302) -> 0 | AC44: =SUMIF(Woblink!E$9:E$309,A44,Woblink!I$9:I$309) -> 0 | AD44: =SUMIF(Woblink!E$14:E$314,A44,konwertery!R$2:R$300) -> 0 | AF44: =SUM(SUMIF(konwertery!I$2:I$300,A44,Azymut!H$2:H$298),(SUMIF(konwertery!S$2:S$300,A44,AzymutB!H$2:H339)*2)) -> 1 | AG44: =SUM(SUMIF(konwertery!I$2:I$300,A44,konwertery!J$2:J$300),SUMIF(konwertery!S$2:S$300,A44,konwertery!T$2:T$300)) -> 11.37 | AI44: =SUMIF(konwertery!K$2:K$300,A44,Ebookpoint!F$14:F$312) -> 0 | AJ44: =SUMIF(konwertery!K$2:K$300,A44,Ebookpoint!M$14:M$312) -> 0 | AL44: =SUMIF(konwertery!L$2:L$300,A44,Nasbi!F$14:F$312) -> 0 | AM44: =SUMIF(konwertery!L$2:L$300,A44,Nasbi!K$14:K$312) -> 0 | AO44: =SUMIF(StorytelE!C$2:C$300,A44,konwertery!M$2:M$300)+SUMIF(StorytelA!C$2:C$300,A44,konwertery!N$2:N$300) -> 1 | AP44: =SUMIF(StorytelE!C$2:C$300,A44,konwertery!O$2:O$300)+SUMIF(StorytelA!C$2:C$300,A44,konwertery!P$2:P$300) -> 2.37 | AR44: =SUMIF(konwertery!U$2:U$300,A44,Audioteka!E$4:E$302) -> 0 | AS44: =SUMIF(konwertery!U$2:U$300,A44,Audioteka!O$4:O$302) -> 0 | AU44: =SUMIF(Bookbeat!A$9:A$309,A44,Bookbeat!H$9:H$309) -> 0 | AV44: =SUMIF(Bookbeat!A$9:A$309,A44,Bookbeat!L$9:L$309) -> 0
A45: 9788365156778 | B45: Kryminalne Wilno (audio) | E45: =H45+K45 -> 38 | F45: =I45+L45 -> 188.45 | H45: =SUMIF(konwertery!A$2:A$300,A45,Histmag!C$2:C$300) -> 0 | I45: =SUMIF(konwertery!A$2:A$300,A45,konwertery!B$2:B$300) * 0.97 -> 0 | K45: =N45+Q45+T45+W45+Z45+AC45+AF45+AI45+AL45+AO45+AR45+AU45 -> 38 | L45: =O45+R45+U45+X45+AA45+AD45+AG45+AJ45+AM45+AP45+AS45+AV45 -> 188.45 | N45: =SUMIF(konwertery!C$2:C$300,A45,Virtualo!L$2:L$300) -> 0 | O45: =(SUMIF(konwertery!C$2:C$300,A45,Virtualo!P$2:P$300)) -> 0 | Q45: =SUMIF(konwertery!D$2:D$300,A45,Empik!M$2:M$300) -> 14 | R45: =SUMIF(konwertery!D$2:D$300,A45,Empik!N$2:N$300) -> 116 | T45: =SUMIF(konwertery!E$2:E$300,A45,Publio!P$2:P$300) -> 0 | U45: =SUMIF(konwertery!E$2:E$300,A45,konwertery!F$2:F$300) -> 0 | W45: =SUMIF(Legimi!D$2:D$300,A45,Legimi!G$2:G$300) -> 0 | X45: =SUMIF(Legimi!D$2:D$300,A45,Legimi!H$2:H$300) -> 0 | Z45: =SUMIF(konwertery!G$2:G$302,A45,Nexto!J$2:J$283) -> 0 | AA45: =SUMIF(konwertery!G$2:G$302,A45,Nexto!N$2:P$302) -> 0 | AC45: =SUMIF(Woblink!E$9:E$309,A45,Woblink!I$9:I$309) -> 0 | AD45: =SUMIF(Woblink!E$14:E$314,A45,konwertery!R$2:R$300) -> 0 | AF45: =SUM(SUMIF(konwertery!I$2:I$300,A45,Azymut!H$2:H$298),(SUMIF(konwertery!S$2:S$300,A45,AzymutB!H$2:H340)*2)) -> 0 | AG45: =SUM(SUMIF(konwertery!I$2:I$300,A45,konwertery!J$2:J$300),SUMIF(konwertery!S$2:S$300,A45,konwertery!T$2:T$300)) -> 0 | AI45: =SUMIF(konwertery!K$2:K$300,A45,Ebookpoint!F$14:F$312) -> 0 | AJ45: =SUMIF(konwertery!K$2:K$300,A45,Ebookpoint!M$14:M$312) -> 0 | AL45: =SUMIF(konwertery!L$2:L$300,A45,Nasbi!F$14:F$312) -> 0 | AM45: =SUMIF(konwertery!L$2:L$300,A45,Nasbi!K$14:K$312) -> 0 | AO45: =SUMIF(StorytelE!C$2:C$300,A45,konwertery!M$2:M$300)+SUMIF(StorytelA!C$2:C$300,A45,konwertery!N$2:N$300) -> 22 | AP45: =SUMIF(StorytelE!C$2:C$300,A45,konwertery!O$2:O$300)+SUMIF(StorytelA!C$2:C$300,A45,konwertery!P$2:P$300) -> 49.71 | AR45: =SUMIF(konwertery!U$2:U$300,A45,Audioteka!E$4:E$302) -> 2 | AS45: =SUMIF(konwertery!U$2:U$300,A45,Audioteka!O$4:O$302) -> 22.74 | AU45: =SUMIF(Bookbeat!A$9:A$309,A45,Bookbeat!H$9:H$309) -> 0 | AV45: =SUMIF(Bookbeat!A$9:A$309,A45,Bookbeat!L$9:L$309) -> 0
A46: 9788365156471 | B46: Ludowe Wojsko Polskie w cieniu zimnej wojny | E46: =H46+K46 -> 3 | F46: =I46+L46 -> 26.5143 | H46: =SUMIF(konwertery!A$2:A$300,A46,Histmag!C$2:C$300) -> 1 | I46: =SUMIF(konwertery!A$2:A$300,A46,konwertery!B$2:B$300) * 0.97 -> 13.7643 | K46: =N46+Q46+T46+W46+Z46+AC46+AF46+AI46+AL46+AO46+AR46+AU46 -> 2 | L46: =O46+R46+U46+X46+AA46+AD46+AG46+AJ46+AM46+AP46+AS46+AV46 -> 12.75 | N46: =SUMIF(konwertery!C$2:C$300,A46,Virtualo!L$2:L$300) -> 0 | O46: =(SUMIF(konwertery!C$2:C$300,A46,Virtualo!P$2:P$300)) -> 0 | Q46: =SUMIF(konwertery!D$2:D$300,A46,Empik!M$2:M$300) -> 0 | R46: =SUMIF(konwertery!D$2:D$300,A46,Empik!N$2:N$300) -> 0 | T46: =SUMIF(konwertery!E$2:E$300,A46,Publio!P$2:P$300) -> 0 | U46: =SUMIF(konwertery!E$2:E$300,A46,konwertery!F$2:F$300) -> 0 | W46: =SUMIF(Legimi!D$2:D$300,A46,Legimi!G$2:G$300) -> 0 | X46: =SUMIF(Legimi!D$2:D$300,A46,Legimi!H$2:H$300) -> 0 | Z46: =SUMIF(konwertery!G$2:G$302,A46,Nexto!J$2:J$283) -> 0 | AA46: =SUMIF(konwertery!G$2:G$302,A46,Nexto!N$2:P$302) -> 0 | AC46: =SUMIF(Woblink!E$9:E$309,A46,Woblink!I$9:I$309) -> 1 | AD46: =SUMIF(Woblink!E$14:E$314,A46,konwertery!R$2:R$300) -> 10.23 | AF46: =SUM(SUMIF(konwertery!I$2:I$300,A46,Azymut!H$2:H$298),(SUMIF(konwertery!S$2:S$300,A46,AzymutB!H$2:H341)*2)) -> 0 | AG46: =SUM(SUMIF(konwertery!I$2:I$300,A46,konwertery!J$2:J$300),SUMIF(konwertery!S$2:S$300,A46,konwertery!T$2:T$300)) -> 0 | AI46: =SUMIF(konwertery!K$2:K$300,A46,Ebookpoint!F$14:F$312) -> 0 | AJ46: =SUMIF(konwertery!K$2:K$300,A46,Ebookpoint!M$14:M$312) -> 0 | AL46: =SUMIF(konwertery!L$2:L$300,A46,Nasbi!F$14:F$312) -> 0 | AM46: =SUMIF(konwertery!L$2:L$300,A46,Nasbi!K$14:K$312) -> 0 | AO46: =SUMIF(StorytelE!C$2:C$300,A46,konwertery!M$2:M$300)+SUMIF(StorytelA!C$2:C$300,A46,konwertery!N$2:N$300) -> 1 | AP46: =SUMIF(StorytelE!C$2:C$300,A46,konwertery!O$2:O$300)+SUMIF(StorytelA!C$2:C$300,A46,konwertery!P$2:P$300) -> 2.52 | AR46: =SUMIF(konwertery!U$2:U$300,A46,Audioteka!E$4:E$302) -> 0 | AS46: =SUMIF(konwertery!U$2:U$300,A46,Audioteka!O$4:O$302) -> 0 | AU46: =SUMIF(Bookbeat!A$9:A$309,A46,Bookbeat!H$9:H$309) -> 0 | AV46: =SUMIF(Bookbeat!A$9:A$309,A46,Bookbeat!L$9:L$309) -> 0
A47: 9788365156570 | B47: Ludowe Wojsko Polskie w cieniu zimnej wojny (audio) | E47: =H47+K47 -> 27 | F47: =I47+L47 -> 105.7774 | H47: =SUMIF(konwertery!A$2:A$300,A47,Histmag!C$2:C$300) -> 2 | I47: =SUMIF(konwertery!A$2:A$300,A47,konwertery!B$2:B$300) * 0.97 -> 22.7174 | K47: =N47+Q47+T47+W47+Z47+AC47+AF47+AI47+AL47+AO47+AR47+AU47 -> 25 | L47: =O47+R47+U47+X47+AA47+AD47+AG47+AJ47+AM47+AP47+AS47+AV47 -> 83.06 | N47: =SUMIF(konwertery!C$2:C$300,A47,Virtualo!L$2:L$300) -> 0 | O47: =(SUMIF(konwertery!C$2:C$300,A47,Virtualo!P$2:P$300)) -> 0 | Q47: =SUMIF(konwertery!D$2:D$300,A47,Empik!M$2:M$300) -> 4 | R47: =SUMIF(konwertery!D$2:D$300,A47,Empik!N$2:N$300) -> 26 | T47: =SUMIF(konwertery!E$2:E$300,A47,Publio!P$2:P$300) -> 0 | U47: =SUMIF(konwertery!E$2:E$300,A47,konwertery!F$2:F$300) -> 0 | W47: =SUMIF(Legimi!D$2:D$300,A47,Legimi!G$2:G$300) -> 0 | X47: =SUMIF(Legimi!D$2:D$300,A47,Legimi!H$2:H$300) -> 0 | Z47: =SUMIF(konwertery!G$2:G$302,A47,Nexto!J$2:J$283) -> 0 | AA47: =SUMIF(konwertery!G$2:G$302,A47,Nexto!N$2:P$302) -> 0 | AC47: =SUMIF(Woblink!E$9:E$309,A47,Woblink!I$9:I$309) -> 0 | AD47: =SUMIF(Woblink!E$14:E$314,A47,konwertery!R$2:R$300) -> 0 | AF47: =SUM(SUMIF(konwertery!I$2:I$300,A47,Azymut!H$2:H$298),(SUMIF(konwertery!S$2:S$300,A47,AzymutB!H$2:H342)*2)) -> 0 | AG47: =SUM(SUMIF(konwertery!I$2:I$300,A47,konwertery!J$2:J$300),SUMIF(konwertery!S$2:S$300,A47,konwertery!T$2:T$300)) -> 0 | AI47: =SUMIF(konwertery!K$2:K$300,A47,Ebookpoint!F$14:F$312) -> 0 | AJ47: =SUMIF(konwertery!K$2:K$300,A47,Ebookpoint!M$14:M$312) -> 0 | AL47: =SUMIF(konwertery!L$2:L$300,A47,Nasbi!F$14:F$312) -> 0 | AM47: =SUMIF(konwertery!L$2:L$300,A47,Nasbi!K$14:K$312) -> 0 | AO47: =SUMIF(StorytelE!C$2:C$300,A47,konwertery!M$2:M$300)+SUMIF(StorytelA!C$2:C$300,A47,konwertery!N$2:N$300) -> 20 | AP47: =SUMIF(StorytelE!C$2:C$300,A47,konwertery!O$2:O$300)+SUMIF(StorytelA!C$2:C$300,A47,konwertery!P$2:P$300) -> 46.83 | AR47: =SUMIF(konwertery!U$2:U$300,A47,Audioteka!E$4:E$302) -> 1 | AS47: =SUMIF(konwertery!U$2:U$300,A47,Audioteka!O$4:O$302) -> 10.23 | AU47: =SUMIF(Bookbeat!A$9:A$309,A47,Bookbeat!H$9:H$309) -> 0 | AV47: =SUMIF(Bookbeat!A$9:A$309,A47,Bookbeat!L$9:L$309) -> 0
A48: 9788365156822 | B48: Mit blitzkriegu w Polsce. Dlaczego wciąż utrwalamy niemiecką propagandę? | E48: =H48+K48 -> 62 | F48: =I48+L48 -> 441.5709 | H48: =SUMIF(konwertery!A$2:A$300,A48,Histmag!C$2:C$300) -> 6 | I48: =SUMIF(konwertery!A$2:A$300,A48,konwertery!B$2:B$300) * 0.97 -> 88.2409 | K48: =N48+Q48+T48+W48+Z48+AC48+AF48+AI48+AL48+AO48+AR48+AU48 -> 56 | L48: =O48+R48+U48+X48+AA48+AD48+AG48+AJ48+AM48+AP48+AS48+AV48 -> 353.33 | N48: =SUMIF(konwertery!C$2:C$300,A48,Virtualo!L$2:L$300) -> 0 | O48: =(SUMIF(konwertery!C$2:C$300,A48,Virtualo!P$2:P$300)) -> 0 | Q48: =SUMIF(konwertery!D$2:D$300,A48,Empik!M$2:M$300) -> 0 | R48: =SUMIF(konwertery!D$2:D$300,A48,Empik!N$2:N$300) -> 0 | T48: =SUMIF(konwertery!E$2:E$300,A48,Publio!P$2:P$300) -> 3 | U48: =SUMIF(konwertery!E$2:E$300,A48,konwertery!F$2:F$300) -> 28.98 | W48: =SUMIF(Legimi!D$2:D$300,A48,Legimi!G$2:G$300) -> 0 | X48: =SUMIF(Legimi!D$2:D$300,A48,Legimi!H$2:H$300) -> 0 | Z48: =SUMIF(konwertery!G$2:G$302,A48,Nexto!J$2:J$283) -> 0 | AA48: =SUMIF(konwertery!G$2:G$302,A48,Nexto!N$2:P$302) -> 0 | AC48: =SUMIF(Woblink!E$9:E$309,A48,Woblink!I$9:I$309) -> 1 | AD48: =SUMIF(Woblink!E$14:E$314,A48,konwertery!R$2:R$300) -> 11.37 | AF48: =SUM(SUMIF(konwertery!I$2:I$300,A48,Azymut!H$2:H$298),(SUMIF(konwertery!S$2:S$300,A48,AzymutB!H$2:H343)*2)) -> 0 | AG48: =SUM(SUMIF(konwertery!I$2:I$300,A48,konwertery!J$2:J$300),SUMIF(konwertery!S$2:S$300,A48,konwertery!T$2:T$300)) -> 0 | AI48: =SUMIF(konwertery!K$2:K$300,A48,Ebookpoint!F$14:F$312) -> 45 | AJ48: =SUMIF(konwertery!K$2:K$300,A48,Ebookpoint!M$14:M$312) -> 296.16 | AL48: =SUMIF(konwertery!L$2:L$300,A48,Nasbi!F$14:F$312) -> 0 | AM48: =SUMIF(konwertery!L$2:L$300,A48,Nasbi!K$14:K$312) -> 0 | AO48: =SUMIF(StorytelE!C$2:C$300,A48,konwertery!M$2:M$300)+SUMIF(StorytelA!C$2:C$300,A48,konwertery!N$2:N$300) -> 7 | AP48: =SUMIF(StorytelE!C$2:C$300,A48,konwertery!O$2:O$300)+SUMIF(StorytelA!C$2:C$300,A48,konwertery!P$2:P$300) -> 16.82 | AR48: =SUMIF(konwertery!U$2:U$300,A48,Audioteka!E$4:E$302) -> 0 | AS48: =SUMIF(konwertery!U$2:U$300,A48,Audioteka!O$4:O$302) -> 0 | AU48: =SUMIF(Bookbeat!A$9:A$309,A48,Bookbeat!H$9:H$309) -> 0 | AV48: =SUMIF(Bookbeat!A$9:A$309,A48,Bookbeat!L$9:L$309) -> 0
A49: 9788365156853 | B49: Mit blitzkriegu w Polsce. Dlaczego wciąż utrwalamy niemiecką propagandę? (audio) | E49: =H49+K49 -> 98 | F49: =I49+L49 -> 539.6742 | H49: =SUMIF(konwertery!A$2:A$300,A49,Histmag!C$2:C$300) -> 5 | I49: =SUMIF(konwertery!A$2:A$300,A49,konwertery!B$2:B$300) * 0.97 -> 72.6142 | K49: =N49+Q49+T49+W49+Z49+AC49+AF49+AI49+AL49+AO49+AR49+AU49 -> 93 | L49: =O49+R49+U49+X49+AA49+AD49+AG49+AJ49+AM49+AP49+AS49+AV49 -> 467.06 | N49: =SUMIF(konwertery!C$2:C$300,A49,Virtualo!L$2:L$300) -> 0 | O49: =(SUMIF(konwertery!C$2:C$300,A49,Virtualo!P$2:P$300)) -> 0 | Q49: =SUMIF(konwertery!D$2:D$300,A49,Empik!M$2:M$300) -> 8 | R49: =SUMIF(konwertery!D$2:D$300,A49,Empik!N$2:N$300) -> 72 | T49: =SUMIF(konwertery!E$2:E$300,A49,Publio!P$2:P$300) -> 1 | U49: =SUMIF(konwertery!E$2:E$300,A49,konwertery!F$2:F$300) -> 11.37 | W49: =SUMIF(Legimi!D$2:D$300,A49,Legimi!G$2:G$300) -> 1 | X49: =SUMIF(Legimi!D$2:D$300,A49,Legimi!H$2:H$300) -> 13.27 | Z49: =SUMIF(konwertery!G$2:G$302,A49,Nexto!J$2:J$283) -> 1 | AA49: =SUMIF(konwertery!G$2:G$302,A49,Nexto!N$2:P$302) -> 6.63 | AC49: =SUMIF(Woblink!E$9:E$309,A49,Woblink!I$9:I$309) -> 0 | AD49: =SUMIF(Woblink!E$14:E$314,A49,konwertery!R$2:R$300) -> 0 | AF49: =SUM(SUMIF(konwertery!I$2:I$300,A49,Azymut!H$2:H$298),(SUMIF(konwertery!S$2:S$300,A49,AzymutB!H$2:H344)*2)) -> 0 | AG49: =SUM(SUMIF(konwertery!I$2:I$300,A49,konwertery!J$2:J$300),SUMIF(konwertery!S$2:S$300,A49,konwertery!T$2:T$300)) -> 0 | AI49: =SUMIF(konwertery!K$2:K$300,A49,Ebookpoint!F$14:F$312) -> 3 | AJ49: =SUMIF(konwertery!K$2:K$300,A49,Ebookpoint!M$14:M$312) -> 36.39 | AL49: =SUMIF(konwertery!L$2:L$300,A49,Nasbi!F$14:F$312) -> 0 | AM49: =SUMIF(konwertery!L$2:L$300,A49,Nasbi!K$14:K$312) -> 0 | AO49: =SUMIF(StorytelE!C$2:C$300,A49,konwertery!M$2:M$300)+SUMIF(StorytelA!C$2:C$300,A49,konwertery!N$2:N$300) -> 60 | AP49: =SUMIF(StorytelE!C$2:C$300,A49,konwertery!O$2:O$300)+SUMIF(StorytelA!C$2:C$300,A49,konwertery!P$2:P$300) -> 121.49 | AR49: =SUMIF(konwertery!U$2:U$300,A49,Audioteka!E$4:E$302) -> 16 | AS49: =SUMIF(konwertery!U$2:U$300,A49,Audioteka!O$4:O$302) -> 187.54 | AU49: =SUMIF(Bookbeat!A$9:A$309,A49,Bookbeat!H$9:H$309) -> 3 | AV49: =SUMIF(Bookbeat!A$9:A$309,A49,Bookbeat!L$9:L$309) -> 18.37
A50: 9788365156662 | B50: Najwięksi skandaliści złotej ery Hollywood | E50: =H50+K50 -> 0 | F50: =I50+L50 -> 0 | H50: =SUMIF(konwertery!A$2:A$300,A50,Histmag!C$2:C$300) -> 0 | I50: =SUMIF(konwertery!A$2:A$300,A50,konwertery!B$2:B$300) * 0.97 -> 0 | K50: =N50+Q50+T50+W50+Z50+AC50+AF50+AI50+AL50+AO50+AR50+AU50 -> 0 | L50: =O50+R50+U50+X50+AA50+AD50+AG50+AJ50+AM50+AP50+AS50+AV50 -> 0 | N50: =SUMIF(konwertery!C$2:C$300,A50,Virtualo!L$2:L$300) -> 0 | O50: =(SUMIF(konwertery!C$2:C$300,A50,Virtualo!P$2:P$300)) -> 0 | Q50: =SUMIF(konwertery!D$2:D$300,A50,Empik!M$2:M$300) -> 0 | R50: =SUMIF(konwertery!D$2:D$300,A50,Empik!N$2:N$300) -> 0 | T50: =SUMIF(konwertery!E$2:E$300,A50,Publio!P$2:P$300) -> 0 | U50: =SUMIF(konwertery!E$2:E$300,A50,konwertery!F$2:F$300) -> 0 | W50: =SUMIF(Legimi!D$2:D$300,A50,Legimi!G$2:G$300) -> 0 | X50: =SUMIF(Legimi!D$2:D$300,A50,Legimi!H$2:H$300) -> 0 | Z50: =SUMIF(konwertery!G$2:G$302,A50,Nexto!J$2:J$283) -> 0 | AA50: =SUMIF(konwertery!G$2:G$302,A50,Nexto!N$2:P$302) -> 0 | AC50: =SUMIF(Woblink!E$9:E$309,A50,Woblink!I$9:I$309) -> 0 | AD50: =SUMIF(Woblink!E$14:E$314,A50,konwertery!R$2:R$300) -> 0 | AF50: =SUM(SUMIF(konwertery!I$2:I$300,A50,Azymut!H$2:H$298),(SUMIF(konwertery!S$2:S$300,A50,AzymutB!H$2:H343)*2)) -> 0 | AG50: =SUM(SUMIF(konwertery!I$2:I$300,A50,konwertery!J$2:J$300),SUMIF(konwertery!S$2:S$300,A50,konwertery!T$2:T$300)) -> 0 | AI50: =SUMIF(konwertery!K$2:K$300,A50,Ebookpoint!F$14:F$312) -> 0 | AJ50: =SUMIF(konwertery!K$2:K$300,A50,Ebookpoint!M$14:M$312) -> 0 | AL50: =SUMIF(konwertery!L$2:L$300,A50,Nasbi!F$14:F$312) -> 0 | AM50: =SUMIF(konwertery!L$2:L$300,A50,Nasbi!K$14:K$312) -> 0 | AO50: =SUMIF(StorytelE!C$2:C$300,A50,konwertery!M$2:M$300)+SUMIF(StorytelA!C$2:C$300,A50,konwertery!N$2:N$300) -> 0 | AP50: =SUMIF(StorytelE!C$2:C$300,A50,konwertery!O$2:O$300)+SUMIF(StorytelA!C$2:C$300,A50,konwertery!P$2:P$300) -> 0 | AR50: =SUMIF(konwertery!U$2:U$300,A50,Audioteka!E$4:E$302) -> 0 | AS50: =SUMIF(konwertery!U$2:U$300,A50,Audioteka!O$4:O$302) -> 0 | AU50: =SUMIF(Bookbeat!A$9:A$309,A50,Bookbeat!H$9:H$309) -> 0 | AV50: =SUMIF(Bookbeat!A$9:A$309,A50,Bookbeat!L$9:L$309) -> 0
A51: 9788365156518 | B51: Oblicza leninizmu | E51: =H51+K51 -> 1 | F51: =I51+L51 -> 10.9901 | H51: =SUMIF(konwertery!A$2:A$300,A51,Histmag!C$2:C$300) -> 1 | I51: =SUMIF(konwertery!A$2:A$300,A51,konwertery!B$2:B$300) * 0.97 -> 10.9901 | K51: =N51+Q51+T51+W51+Z51+AC51+AF51+AI51+AL51+AO51+AR51+AU51 -> 0 | L51: =O51+R51+U51+X51+AA51+AD51+AG51+AJ51+AM51+AP51+AS51+AV51 -> 0 | N51: =SUMIF(konwertery!C$2:C$300,A51,Virtualo!L$2:L$300) -> 0 | O51: =(SUMIF(konwertery!C$2:C$300,A51,Virtualo!P$2:P$300)) -> 0 | Q51: =SUMIF(konwertery!D$2:D$300,A51,Empik!M$2:M$300) -> 0 | R51: =SUMIF(konwertery!D$2:D$300,A51,Empik!N$2:N$300) -> 0 | T51: =SUMIF(konwertery!E$2:E$300,A51,Publio!P$2:P$300) -> 0 | U51: =SUMIF(konwertery!E$2:E$300,A51,konwertery!F$2:F$300) -> 0 | W51: =SUMIF(Legimi!D$2:D$300,A51,Legimi!G$2:G$300) -> 0 | X51: =SUMIF(Legimi!D$2:D$300,A51,Legimi!H$2:H$300) -> 0 | Z51: =SUMIF(konwertery!G$2:G$302,A51,Nexto!J$2:J$283) -> 0 | AA51: =SUMIF(konwertery!G$2:G$302,A51,Nexto!N$2:P$302) -> 0 | AC51: =SUMIF(Woblink!E$9:E$309,A51,Woblink!I$9:I$309) -> 0 | AD51: =SUMIF(Woblink!E$14:E$314,A51,konwertery!R$2:R$300) -> 0 | AF51: =SUM(SUMIF(konwertery!I$2:I$300,A51,Azymut!H$2:H$298),(SUMIF(konwertery!S$2:S$300,A51,AzymutB!H$2:H344)*2)) -> 0 | AG51: =SUM(SUMIF(konwertery!I$2:I$300,A51,konwertery!J$2:J$300),SUMIF(konwertery!S$2:S$300,A51,konwertery!T$2:T$300)) -> 0 | AI51: =SUMIF(konwertery!K$2:K$300,A51,Ebookpoint!F$14:F$312) -> 0 | AJ51: =SUMIF(konwertery!K$2:K$300,A51,Ebookpoint!M$14:M$312) -> 0 | AL51: =SUMIF(konwertery!L$2:L$300,A51,Nasbi!F$14:F$312) -> 0 | AM51: =SUMIF(konwertery!L$2:L$300,A51,Nasbi!K$14:K$312) -> 0 | AO51: =SUMIF(StorytelE!C$2:C$300,A51,konwertery!M$2:M$300)+SUMIF(StorytelA!C$2:C$300,A51,konwertery!N$2:N$300) -> 0 | AP51: =SUMIF(StorytelE!C$2:C$300,A51,konwertery!O$2:O$300)+SUMIF(StorytelA!C$2:C$300,A51,konwertery!P$2:P$300) -> 0 | AR51: =SUMIF(konwertery!U$2:U$300,A51,Audioteka!E$4:E$302) -> 0 | AS51: =SUMIF(konwertery!U$2:U$300,A51,Audioteka!O$4:O$302) -> 0 | AU51: =SUMIF(Bookbeat!A$9:A$309,A51,Bookbeat!H$9:H$309) -> 0 | AV51: =SUMIF(Bookbeat!A$9:A$309,A51,Bookbeat!L$9:L$309) -> 0
A52: 9788365156051 | B52: Oblicza propagandy PRL | E52: =H52+K52 -> 1 | F52: =I52+L52 -> 10.9901 | H52: =SUMIF(konwertery!A$2:A$300,A52,Histmag!C$2:C$300) -> 1 | I52: =SUMIF(konwertery!A$2:A$300,A52,konwertery!B$2:B$300) * 0.97 -> 10.9901 | K52: =N52+Q52+T52+W52+Z52+AC52+AF52+AI52+AL52+AO52+AR52+AU52 -> 0 | L52: =O52+R52+U52+X52+AA52+AD52+AG52+AJ52+AM52+AP52+AS52+AV52 -> 0 | N52: =SUMIF(konwertery!C$2:C$300,A52,Virtualo!L$2:L$300) -> 0 | O52: =(SUMIF(konwertery!C$2:C$300,A52,Virtualo!P$2:P$300)) -> 0 | Q52: =SUMIF(konwertery!D$2:D$300,A52,Empik!M$2:M$300) -> 0 | R52: =SUMIF(konwertery!D$2:D$300,A52,Empik!N$2:N$300) -> 0 | T52: =SUMIF(konwertery!E$2:E$300,A52,Publio!P$2:P$300) -> 0 | U52: =SUMIF(konwertery!E$2:E$300,A52,konwertery!F$2:F$300) -> 0 | W52: =SUMIF(Legimi!D$2:D$300,A52,Legimi!G$2:G$300) -> 0 | X52: =SUMIF(Legimi!D$2:D$300,A52,Legimi!H$2:H$300) -> 0 | Z52: =SUMIF(konwertery!G$2:G$302,A52,Nexto!J$2:J$283) -> 0 | AA52: =SUMIF(konwertery!G$2:G$302,A52,Nexto!N$2:P$302) -> 0 | AC52: =SUMIF(Woblink!E$9:E$309,A52,Woblink!I$9:I$309) -> 0 | AD52: =SUMIF(Woblink!E$14:E$314,A52,konwertery!R$2:R$300) -> 0 | AF52: =SUM(SUMIF(konwertery!I$2:I$300,A52,Azymut!H$2:H$298),(SUMIF(konwertery!S$2:S$300,A52,AzymutB!H$2:H345)*2)) -> 0 | AG52: =SUM(SUMIF(konwertery!I$2:I$300,A52,konwertery!J$2:J$300),SUMIF(konwertery!S$2:S$300,A52,konwertery!T$2:T$300)) -> 0 | AI52: =SUMIF(konwertery!K$2:K$300,A52,Ebookpoint!F$14:F$312) -> 0 | AJ52: =SUMIF(konwertery!K$2:K$300,A52,Ebookpoint!M$14:M$312) -> 0 | AL52: =SUMIF(konwertery!L$2:L$300,A52,Nasbi!F$14:F$312) -> 0 | AM52: =SUMIF(konwertery!L$2:L$300,A52,Nasbi!K$14:K$312) -> 0 | AO52: =SUMIF(StorytelE!C$2:C$300,A52,konwertery!M$2:M$300)+SUMIF(StorytelA!C$2:C$300,A52,konwertery!N$2:N$300) -> 0 | AP52: =SUMIF(StorytelE!C$2:C$300,A52,konwertery!O$2:O$300)+SUMIF(StorytelA!C$2:C$300,A52,konwertery!P$2:P$300) -> 0 | AR52: =SUMIF(konwertery!U$2:U$300,A52,Audioteka!E$4:E$302) -> 0 | AS52: =SUMIF(konwertery!U$2:U$300,A52,Audioteka!O$4:O$302) -> 0 | AU52: =SUMIF(Bookbeat!A$9:A$309,A52,Bookbeat!H$9:H$309) -> 0 | AV52: =SUMIF(Bookbeat!A$9:A$309,A52,Bookbeat!L$9:L$309) -> 0
A53: 9788365156198 | B53: Oblicza propagandy PRL część II | E53: =H53+K53 -> 0 | F53: =I53+L53 -> 0 | H53: =SUMIF(konwertery!A$2:A$300,A53,Histmag!C$2:C$300) -> 0 | I53: =SUMIF(konwertery!A$2:A$300,A53,konwertery!B$2:B$300) * 0.97 -> 0 | K53: =N53+Q53+T53+W53+Z53+AC53+AF53+AI53+AL53+AO53+AR53+AU53 -> 0 | L53: =O53+R53+U53+X53+AA53+AD53+AG53+AJ53+AM53+AP53+AS53+AV53 -> 0 | N53: =SUMIF(konwertery!C$2:C$300,A53,Virtualo!L$2:L$300) -> 0 | O53: =(SUMIF(konwertery!C$2:C$300,A53,Virtualo!P$2:P$300)) -> 0 | Q53: =SUMIF(konwertery!D$2:D$300,A53,Empik!M$2:M$300) -> 0 | R53: =SUMIF(konwertery!D$2:D$300,A53,Empik!N$2:N$300) -> 0 | T53: =SUMIF(konwertery!E$2:E$300,A53,Publio!P$2:P$300) -> 0 | U53: =SUMIF(konwertery!E$2:E$300,A53,konwertery!F$2:F$300) -> 0 | W53: =SUMIF(Legimi!D$2:D$300,A53,Legimi!G$2:G$300) -> 0 | X53: =SUMIF(Legimi!D$2:D$300,A53,Legimi!H$2:H$300) -> 0 | Z53: =SUMIF(konwertery!G$2:G$302,A53,Nexto!J$2:J$283) -> 0 | AA53: =SUMIF(konwertery!G$2:G$302,A53,Nexto!N$2:P$302) -> 0 | AC53: =SUMIF(Woblink!E$9:E$309,A53,Woblink!I$9:I$309) -> 0 | AD53: =SUMIF(Woblink!E$14:E$314,A53,konwertery!R$2:R$300) -> 0 | AF53: =SUM(SUMIF(konwertery!I$2:I$300,A53,Azymut!H$2:H$298),(SUMIF(konwertery!S$2:S$300,A53,AzymutB!H$2:H346)*2)) -> 0 | AG53: =SUM(SUMIF(konwertery!I$2:I$300,A53,konwertery!J$2:J$300),SUMIF(konwertery!S$2:S$300,A53,konwertery!T$2:T$300)) -> 0 | AI53: =SUMIF(konwertery!K$2:K$300,A53,Ebookpoint!F$14:F$312) -> 0 | AJ53: =SUMIF(konwertery!K$2:K$300,A53,Ebookpoint!M$14:M$312) -> 0 | AL53: =SUMIF(konwertery!L$2:L$300,A53,Nasbi!F$14:F$312) -> 0 | AM53: =SUMIF(konwertery!L$2:L$300,A53,Nasbi!K$14:K$312) -> 0 | AO53: =SUMIF(StorytelE!C$2:C$300,A53,konwertery!M$2:M$300)+SUMIF(StorytelA!C$2:C$300,A53,konwertery!N$2:N$300) -> 0 | AP53: =SUMIF(StorytelE!C$2:C$300,A53,konwertery!O$2:O$300)+SUMIF(StorytelA!C$2:C$300,A53,konwertery!P$2:P$300) -> 0 | AR53: =SUMIF(konwertery!U$2:U$300,A53,Audioteka!E$4:E$302) -> 0 | AS53: =SUMIF(konwertery!U$2:U$300,A53,Audioteka!O$4:O$302) -> 0 | AU53: =SUMIF(Bookbeat!A$9:A$309,A53,Bookbeat!H$9:H$309) -> 0 | AV53: =SUMIF(Bookbeat!A$9:A$309,A53,Bookbeat!L$9:L$309) -> 0
A54: 9788365156747 | B54: Oblicza propagandy PRL (audiobook) | E54: =H54+K54 -> 45 | F54: =I54+L54 -> 136.06 | H54: =SUMIF(konwertery!A$2:A$300,A54,Histmag!C$2:C$300) -> 0 | I54: =SUMIF(konwertery!A$2:A$300,A54,konwertery!B$2:B$300) * 0.97 -> 0 | K54: =N54+Q54+T54+W54+Z54+AC54+AF54+AI54+AL54+AO54+AR54+AU54 -> 45 | L54: =O54+R54+U54+X54+AA54+AD54+AG54+AJ54+AM54+AP54+AS54+AV54 -> 136.06 | N54: =SUMIF(konwertery!C$2:C$300,A54,Virtualo!L$2:L$300) -> 1 | O54: =(SUMIF(konwertery!C$2:C$300,A54,Virtualo!P$2:P$300)) -> 9.22 | Q54: =SUMIF(konwertery!D$2:D$300,A54,Empik!M$2:M$300) -> 6 | R54: =SUMIF(konwertery!D$2:D$300,A54,Empik!N$2:N$300) -> 50 | T54: =SUMIF(konwertery!E$2:E$300,A54,Publio!P$2:P$300) -> 0 | U54: =SUMIF(konwertery!E$2:E$300,A54,konwertery!F$2:F$300) -> 0 | W54: =SUMIF(Legimi!D$2:D$300,A54,Legimi!G$2:G$300) -> 0 | X54: =SUMIF(Legimi!D$2:D$300,A54,Legimi!H$2:H$300) -> 0 | Z54: =SUMIF(konwertery!G$2:G$302,A54,Nexto!J$2:J$283) -> 0 | AA54: =SUMIF(konwertery!G$2:G$302,A54,Nexto!N$2:P$302) -> 0 | AC54: =SUMIF(Woblink!E$9:E$309,A54,Woblink!I$9:I$309) -> 0 | AD54: =SUMIF(Woblink!E$14:E$314,A54,konwertery!R$2:R$300) -> 0 | AF54: =SUM(SUMIF(konwertery!I$2:I$300,A54,Azymut!H$2:H$298),(SUMIF(konwertery!S$2:S$300,A54,AzymutB!H$2:H347)*2)) -> 0 | AG54: =SUM(SUMIF(konwertery!I$2:I$300,A54,konwertery!J$2:J$300),SUMIF(konwertery!S$2:S$300,A54,konwertery!T$2:T$300)) -> 0 | AI54: =SUMIF(konwertery!K$2:K$300,A54,Ebookpoint!F$14:F$312) -> 0 | AJ54: =SUMIF(konwertery!K$2:K$300,A54,Ebookpoint!M$14:M$312) -> 0 | AL54: =SUMIF(konwertery!L$2:L$300,A54,Nasbi!F$14:F$312) -> 0 | AM54: =SUMIF(konwertery!L$2:L$300,A54,Nasbi!K$14:K$312) -> 0 | AO54: =SUMIF(StorytelE!C$2:C$300,A54,konwertery!M$2:M$300)+SUMIF(StorytelA!C$2:C$300,A54,konwertery!N$2:N$300) -> 35 | AP54: =SUMIF(StorytelE!C$2:C$300,A54,konwertery!O$2:O$300)+SUMIF(StorytelA!C$2:C$300,A54,konwertery!P$2:P$300) -> 62.85 | AR54: =SUMIF(konwertery!U$2:U$300,A54,Audioteka!E$4:E$302) -> 1 | AS54: =SUMIF(konwertery!U$2:U$300,A54,Audioteka!O$4:O$302) -> 8.51 | AU54: =SUMIF(Bookbeat!A$9:A$309,A54,Bookbeat!H$9:H$309) -> 2 | AV54: =SUMIF(Bookbeat!A$9:A$309,A54,Bookbeat!L$9:L$309) -> 5.48
A55: 9788365156679 | B55: Pastuch panem Rzymu | E55: =H55+K55 -> 1 | F55: =I55+L55 -> 7.1392 | H55: =SUMIF(konwertery!A$2:A$300,A55,Histmag!C$2:C$300) -> 1 | I55: =SUMIF(konwertery!A$2:A$300,A55,konwertery!B$2:B$300) * 0.97 -> 7.1392 | K55: =N55+Q55+T55+W55+Z55+AC55+AF55+AI55+AL55+AO55+AR55+AU55 -> 0 | L55: =O55+R55+U55+X55+AA55+AD55+AG55+AJ55+AM55+AP55+AS55+AV55 -> 0 | N55: =SUMIF(konwertery!C$2:C$300,A55,Virtualo!L$2:L$300) -> 0 | O55: =(SUMIF(konwertery!C$2:C$300,A55,Virtualo!P$2:P$300)) -> 0 | Q55: =SUMIF(konwertery!D$2:D$300,A55,Empik!M$2:M$300) -> 0 | R55: =SUMIF(konwertery!D$2:D$300,A55,Empik!N$2:N$300) -> 0 | T55: =SUMIF(konwertery!E$2:E$300,A55,Publio!P$2:P$300) -> 0 | U55: =SUMIF(konwertery!E$2:E$300,A55,konwertery!F$2:F$300) -> 0 | W55: =SUMIF(Legimi!D$2:D$300,A55,Legimi!G$2:G$300) -> 0 | X55: =SUMIF(Legimi!D$2:D$300,A55,Legimi!H$2:H$300) -> 0 | Z55: =SUMIF(konwertery!G$2:G$302,A55,Nexto!J$2:J$283) -> 0 | AA55: =SUMIF(konwertery!G$2:G$302,A55,Nexto!N$2:P$302) -> 0 | AC55: =SUMIF(Woblink!E$9:E$309,A55,Woblink!I$9:I$309) -> 0 | AD55: =SUMIF(Woblink!E$14:E$314,A55,konwertery!R$2:R$300) -> 0 | AF55: =SUM(SUMIF(konwertery!I$2:I$300,A55,Azymut!H$2:H$298),(SUMIF(konwertery!S$2:S$300,A55,AzymutB!H$2:H348)*2)) -> 0 | AG55: =SUM(SUMIF(konwertery!I$2:I$300,A55,konwertery!J$2:J$300),SUMIF(konwertery!S$2:S$300,A55,konwertery!T$2:T$300)) -> 0 | AI55: =SUMIF(konwertery!K$2:K$300,A55,Ebookpoint!F$14:F$312) -> 0 | AJ55: =SUMIF(konwertery!K$2:K$300,A55,Ebookpoint!M$14:M$312) -> 0 | AL55: =SUMIF(konwertery!L$2:L$300,A55,Nasbi!F$14:F$312) -> 0 | AM55: =SUMIF(konwertery!L$2:L$300,A55,Nasbi!K$14:K$312) -> 0 | AO55: =SUMIF(StorytelE!C$2:C$300,A55,konwertery!M$2:M$300)+SUMIF(StorytelA!C$2:C$300,A55,konwertery!N$2:N$300) -> 0 | AP55: =SUMIF(StorytelE!C$2:C$300,A55,konwertery!O$2:O$300)+SUMIF(StorytelA!C$2:C$300,A55,konwertery!P$2:P$300) -> 0 | AR55: =SUMIF(konwertery!U$2:U$300,A55,Audioteka!E$4:E$302) -> 0 | AS55: =SUMIF(konwertery!U$2:U$300,A55,Audioteka!O$4:O$302) -> 0 | AU55: =SUMIF(Bookbeat!A$9:A$309,A55,Bookbeat!H$9:H$309) -> 0 | AV55: =SUMIF(Bookbeat!A$9:A$309,A55,Bookbeat!L$9:L$309) -> 0
A56: 9788365156112 | B56: Perły imperium brytyjskiego | E56: =H56+K56 -> 4 | F56: =I56+L56 -> 17.27 | H56: =SUMIF(konwertery!A$2:A$300,A56,Histmag!C$2:C$300) -> 0 | I56: =SUMIF(konwertery!A$2:A$300,A56,konwertery!B$2:B$300) * 0.97 -> 0 | K56: =N56+Q56+T56+W56+Z56+AC56+AF56+AI56+AL56+AO56+AR56+AU56 -> 4 | L56: =O56+R56+U56+X56+AA56+AD56+AG56+AJ56+AM56+AP56+AS56+AV56 -> 17.27 | N56: =SUMIF(konwertery!C$2:C$300,A56,Virtualo!L$2:L$300) -> 0 | O56: =(SUMIF(konwertery!C$2:C$300,A56,Virtualo!P$2:P$300)) -> 0 | Q56: =SUMIF(konwertery!D$2:D$300,A56,Empik!M$2:M$300) -> 0 | R56: =SUMIF(konwertery!D$2:D$300,A56,Empik!N$2:N$300) -> 0 | T56: =SUMIF(konwertery!E$2:E$300,A56,Publio!P$2:P$300) -> 1 | U56: =SUMIF(konwertery!E$2:E$300,A56,konwertery!F$2:F$300) -> 6.28 | W56: =SUMIF(Legimi!D$2:D$300,A56,Legimi!G$2:G$300) -> 0 | X56: =SUMIF(Legimi!D$2:D$300,A56,Legimi!H$2:H$300) -> 0 | Z56: =SUMIF(konwertery!G$2:G$302,A56,Nexto!J$2:J$283) -> 0 | AA56: =SUMIF(konwertery!G$2:G$302,A56,Nexto!N$2:P$302) -> 0 | AC56: =SUMIF(Woblink!E$9:E$309,A56,Woblink!I$9:I$309) -> 0 | AD56: =SUMIF(Woblink!E$14:E$314,A56,konwertery!R$2:R$300) -> 0 | AF56: =SUM(SUMIF(konwertery!I$2:I$300,A56,Azymut!H$2:H$298),(SUMIF(konwertery!S$2:S$300,A56,AzymutB!H$2:H349)*2)) -> 0 | AG56: =SUM(SUMIF(konwertery!I$2:I$300,A56,konwertery!J$2:J$300),SUMIF(konwertery!S$2:S$300,A56,konwertery!T$2:T$300)) -> 0 | AI56: =SUMIF(konwertery!K$2:K$300,A56,Ebookpoint!F$14:F$312) -> 1 | AJ56: =SUMIF(konwertery!K$2:K$300,A56,Ebookpoint!M$14:M$312) -> 7.87 | AL56: =SUMIF(konwertery!L$2:L$300,A56,Nasbi!F$14:F$312) -> 0 | AM56: =SUMIF(konwertery!L$2:L$300,A56,Nasbi!K$14:K$312) -> 0 | AO56: =SUMIF(StorytelE!C$2:C$300,A56,konwertery!M$2:M$300)+SUMIF(StorytelA!C$2:C$300,A56,konwertery!N$2:N$300) -> 2 | AP56: =SUMIF(StorytelE!C$2:C$300,A56,konwertery!O$2:O$300)+SUMIF(StorytelA!C$2:C$300,A56,konwertery!P$2:P$300) -> 3.12 | AR56: =SUMIF(konwertery!U$2:U$300,A56,Audioteka!E$4:E$302) -> 0 | AS56: =SUMIF(konwertery!U$2:U$300,A56,Audioteka!O$4:O$302) -> 0 | AU56: =SUMIF(Bookbeat!A$9:A$309,A56,Bookbeat!H$9:H$309) -> 0 | AV56: =SUMIF(Bookbeat!A$9:A$309,A56,Bookbeat!L$9:L$309) -> 0
A57: 9788365156846 | B57: Perły imperium brytyjskiego (audiobook) | E57: =H57+K57 -> 136 | F57: =I57+L57 -> 316.1732 | H57: =SUMIF(konwertery!A$2:A$300,A57,Histmag!C$2:C$300) -> 2 | I57: =SUMIF(konwertery!A$2:A$300,A57,konwertery!B$2:B$300) * 0.97 -> 15.0932 | K57: =N57+Q57+T57+W57+Z57+AC57+AF57+AI57+AL57+AO57+AR57+AU57 -> 134 | L57: =O57+R57+U57+X57+AA57+AD57+AG57+AJ57+AM57+AP57+AS57+AV57 -> 301.08 | N57: =SUMIF(konwertery!C$2:C$300,A57,Virtualo!L$2:L$300) -> 0 | O57: =(SUMIF(konwertery!C$2:C$300,A57,Virtualo!P$2:P$300)) -> 0 | Q57: =SUMIF(konwertery!D$2:D$300,A57,Empik!M$2:M$300) -> 15 | R57: =SUMIF(konwertery!D$2:D$300,A57,Empik!N$2:N$300) -> 93 | T57: =SUMIF(konwertery!E$2:E$300,A57,Publio!P$2:P$300) -> 0 | U57: =SUMIF(konwertery!E$2:E$300,A57,konwertery!F$2:F$300) -> 0 | W57: =SUMIF(Legimi!D$2:D$300,A57,Legimi!G$2:G$300) -> 0 | X57: =SUMIF(Legimi!D$2:D$300,A57,Legimi!H$2:H$300) -> 0 | Z57: =SUMIF(konwertery!G$2:G$302,A57,Nexto!J$2:J$283) -> 0 | AA57: =SUMIF(konwertery!G$2:G$302,A57,Nexto!N$2:P$302) -> 0 | AC57: =SUMIF(Woblink!E$9:E$309,A57,Woblink!I$9:I$309) -> 0 | AD57: =SUMIF(Woblink!E$14:E$314,A57,konwertery!R$2:R$300) -> 0 | AF57: =SUM(SUMIF(konwertery!I$2:I$300,A57,Azymut!H$2:H$298),(SUMIF(konwertery!S$2:S$300,A57,AzymutB!H$2:H350)*2)) -> 0 | AG57: =SUM(SUMIF(konwertery!I$2:I$300,A57,konwertery!J$2:J$300),SUMIF(konwertery!S$2:S$300,A57,konwertery!T$2:T$300)) -> 0 | AI57: =SUMIF(konwertery!K$2:K$300,A57,Ebookpoint!F$14:F$312) -> 1 | AJ57: =SUMIF(konwertery!K$2:K$300,A57,Ebookpoint!M$14:M$312) -> 7.87 | AL57: =SUMIF(konwertery!L$2:L$300,A57,Nasbi!F$14:F$312) -> 0 | AM57: =SUMIF(konwertery!L$2:L$300,A57,Nasbi!K$14:K$312) -> 0 | AO57: =SUMIF(StorytelE!C$2:C$300,A57,konwertery!M$2:M$300)+SUMIF(StorytelA!C$2:C$300,A57,konwertery!N$2:N$300) -> 111 | AP57: =SUMIF(StorytelE!C$2:C$300,A57,konwertery!O$2:O$300)+SUMIF(StorytelA!C$2:C$300,A57,konwertery!P$2:P$300) -> 151.74 | AR57: =SUMIF(konwertery!U$2:U$300,A57,Audioteka!E$4:E$302) -> 5 | AS57: =SUMIF(konwertery!U$2:U$300,A57,Audioteka!O$4:O$302) -> 44.31 | AU57: =SUMIF(Bookbeat!A$9:A$309,A57,Bookbeat!H$9:H$309) -> 2 | AV57: =SUMIF(Bookbeat!A$9:A$309,A57,Bookbeat!L$9:L$309) -> 4.16
A58: 9788365156075 | B58: Pojedynki, biesiady, modlitwy, Świat średniowiecznych rycerzy | E58: =H58+K58 -> 2 | F58: =I58+L58 -> 12.0474 | H58: =SUMIF(konwertery!A$2:A$300,A58,Histmag!C$2:C$300) -> 2 | I58: =SUMIF(konwertery!A$2:A$300,A58,konwertery!B$2:B$300) * 0.97 -> 12.0474 | K58: =N58+Q58+T58+W58+Z58+AC58+AF58+AI58+AL58+AO58+AR58+AU58 -> 0 | L58: =O58+R58+U58+X58+AA58+AD58+AG58+AJ58+AM58+AP58+AS58+AV58 -> 0 | N58: =SUMIF(konwertery!C$2:C$300,A58,Virtualo!L$2:L$300) -> 0 | O58: =(SUMIF(konwertery!C$2:C$300,A58,Virtualo!P$2:P$300)) -> 0 | Q58: =SUMIF(konwertery!D$2:D$300,A58,Empik!M$2:M$300) -> 0 | R58: =SUMIF(konwertery!D$2:D$300,A58,Empik!N$2:N$300) -> 0 | T58: =SUMIF(konwertery!E$2:E$300,A58,Publio!P$2:P$300) -> 0 | U58: =SUMIF(konwertery!E$2:E$300,A58,konwertery!F$2:F$300) -> 0 | W58: =SUMIF(Legimi!D$2:D$300,A58,Legimi!G$2:G$300) -> 0 | X58: =SUMIF(Legimi!D$2:D$300,A58,Legimi!H$2:H$300) -> 0 | Z58: =SUMIF(konwertery!G$2:G$302,A58,Nexto!J$2:J$283) -> 0 | AA58: =SUMIF(konwertery!G$2:G$302,A58,Nexto!N$2:P$302) -> 0 | AC58: =SUMIF(Woblink!E$9:E$309,A58,Woblink!I$9:I$309) -> 0 | AD58: =SUMIF(Woblink!E$14:E$314,A58,konwertery!R$2:R$300) -> 0 | AF58: =SUM(SUMIF(konwertery!I$2:I$300,A58,Azymut!H$2:H$298),(SUMIF(konwertery!S$2:S$300,A58,AzymutB!H$2:H350)*2)) -> 0 | AG58: =SUM(SUMIF(konwertery!I$2:I$300,A58,konwertery!J$2:J$300),SUMIF(konwertery!S$2:S$300,A58,konwertery!T$2:T$300)) -> 0 | AI58: =SUMIF(konwertery!K$2:K$300,A58,Ebookpoint!F$14:F$312) -> 0 | AJ58: =SUMIF(konwertery!K$2:K$300,A58,Ebookpoint!M$14:M$312) -> 0 | AL58: =SUMIF(konwertery!L$2:L$300,A58,Nasbi!F$14:F$312) -> 0 | AM58: =SUMIF(konwertery!L$2:L$300,A58,Nasbi!K$14:K$312) -> 0 | AO58: =SUMIF(StorytelE!C$2:C$300,A58,konwertery!M$2:M$300)+SUMIF(StorytelA!C$2:C$300,A58,konwertery!N$2:N$300) -> 0 | AP58: =SUMIF(StorytelE!C$2:C$300,A58,konwertery!O$2:O$300)+SUMIF(StorytelA!C$2:C$300,A58,konwertery!P$2:P$300) -> 0 | AR58: =SUMIF(konwertery!U$2:U$300,A58,Audioteka!E$4:E$302) -> 0 | AS58: =SUMIF(konwertery!U$2:U$300,A58,Audioteka!O$4:O$302) -> 0 | AU58: =SUMIF(Bookbeat!A$9:A$309,A58,Bookbeat!H$9:H$309) -> 0 | AV58: =SUMIF(Bookbeat!A$9:A$309,A58,Bookbeat!L$9:L$309) -> 0
A59: 9788365156709 | B59: Pojedynki, biesiady, modlitwy, Świat średniowiecznych rycerzy (audio) | E59: =H59+K59 -> 40 | F59: =I59+L59 -> 82.5774 | H59: =SUMIF(konwertery!A$2:A$300,A59,Histmag!C$2:C$300) -> 2 | I59: =SUMIF(konwertery!A$2:A$300,A59,konwertery!B$2:B$300) * 0.97 -> 12.0474 | K59: =N59+Q59+T59+W59+Z59+AC59+AF59+AI59+AL59+AO59+AR59+AU59 -> 38 | L59: =O59+R59+U59+X59+AA59+AD59+AG59+AJ59+AM59+AP59+AS59+AV59 -> 70.53 | N59: =SUMIF(konwertery!C$2:C$300,A59,Virtualo!L$2:L$300) -> 1 | O59: =(SUMIF(konwertery!C$2:C$300,A59,Virtualo!P$2:P$300)) -> 6.74 | Q59: =SUMIF(konwertery!D$2:D$300,A59,Empik!M$2:M$300) -> 3 | R59: =SUMIF(konwertery!D$2:D$300,A59,Empik!N$2:N$300) -> 25 | T59: =SUMIF(konwertery!E$2:E$300,A59,Publio!P$2:P$300) -> 0 | U59: =SUMIF(konwertery!E$2:E$300,A59,konwertery!F$2:F$300) -> 0 | W59: =SUMIF(Legimi!D$2:D$300,A59,Legimi!G$2:G$300) -> 1 | X59: =SUMIF(Legimi!D$2:D$300,A59,Legimi!H$2:H$300) -> 7.27 | Z59: =SUMIF(konwertery!G$2:G$302,A59,Nexto!J$2:J$283) -> 0 | AA59: =SUMIF(konwertery!G$2:G$302,A59,Nexto!N$2:P$302) -> 0 | AC59: =SUMIF(Woblink!E$9:E$309,A59,Woblink!I$9:I$309) -> 0 | AD59: =SUMIF(Woblink!E$14:E$314,A59,konwertery!R$2:R$300) -> 0 | AF59: =SUM(SUMIF(konwertery!I$2:I$300,A59,Azymut!H$2:H$298),(SUMIF(konwertery!S$2:S$300,A59,AzymutB!H$2:H351)*2)) -> 0 | AG59: =SUM(SUMIF(konwertery!I$2:I$300,A59,konwertery!J$2:J$300),SUMIF(konwertery!S$2:S$300,A59,konwertery!T$2:T$300)) -> 0 | AI59: =SUMIF(konwertery!K$2:K$300,A59,Ebookpoint!F$14:F$312) -> 0 | AJ59: =SUMIF(konwertery!K$2:K$300,A59,Ebookpoint!M$14:M$312) -> 0 | AL59: =SUMIF(konwertery!L$2:L$300,A59,Nasbi!F$14:F$312) -> 0 | AM59: =SUMIF(konwertery!L$2:L$300,A59,Nasbi!K$14:K$312) -> 0 | AO59: =SUMIF(StorytelE!C$2:C$300,A59,konwertery!M$2:M$300)+SUMIF(StorytelA!C$2:C$300,A59,konwertery!N$2:N$300) -> 32 | AP59: =SUMIF(StorytelE!C$2:C$300,A59,konwertery!O$2:O$300)+SUMIF(StorytelA!C$2:C$300,A59,konwertery!P$2:P$300) -> 30.16 | AR59: =SUMIF(konwertery!U$2:U$300,A59,Audioteka!E$4:E$302) -> 0 | AS59: =SUMIF(konwertery!U$2:U$300,A59,Audioteka!O$4:O$302) -> 0 | AU59: =SUMIF(Bookbeat!A$9:A$309,A59,Bookbeat!H$9:H$309) -> 1 | AV59: =SUMIF(Bookbeat!A$9:A$309,A59,Bookbeat!L$9:L$309) -> 1.36
A60: 9788365156174 | B60: Polacy na krańcach świata: średniowiecze i nowożytność | E60: =H60+K60 -> 0 | F60: =I60+L60 -> 0 | H60: =SUMIF(konwertery!A$2:A$300,A60,Histmag!C$2:C$300) -> 0 | I60: =SUMIF(konwertery!A$2:A$300,A60,konwertery!B$2:B$300) * 0.97 -> 0 | K60: =N60+Q60+T60+W60+Z60+AC60+AF60+AI60+AL60+AO60+AR60+AU60 -> 0 | L60: =O60+R60+U60+X60+AA60+AD60+AG60+AJ60+AM60+AP60+AS60+AV60 -> 0 | N60: =SUMIF(konwertery!C$2:C$300,A60,Virtualo!L$2:L$300) -> 0 | O60: =(SUMIF(konwertery!C$2:C$300,A60,Virtualo!P$2:P$300)) -> 0 | Q60: =SUMIF(konwertery!D$2:D$300,A60,Empik!M$2:M$300) -> 0 | R60: =SUMIF(konwertery!D$2:D$300,A60,Empik!N$2:N$300) -> 0 | T60: =SUMIF(konwertery!E$2:E$300,A60,Publio!P$2:P$300) -> 0 | U60: =SUMIF(konwertery!E$2:E$300,A60,konwertery!F$2:F$300) -> 0 | W60: =SUMIF(Legimi!D$2:D$300,A60,Legimi!G$2:G$300) -> 0 | X60: =SUMIF(Legimi!D$2:D$300,A60,Legimi!H$2:H$300) -> 0 | Z60: =SUMIF(konwertery!G$2:G$302,A60,Nexto!J$2:J$283) -> 0 | AA60: =SUMIF(konwertery!G$2:G$302,A60,Nexto!N$2:P$302) -> 0 | AC60: =SUMIF(Woblink!E$9:E$309,A60,Woblink!I$9:I$309) -> 0 | AD60: =SUMIF(Woblink!E$14:E$314,A60,konwertery!R$2:R$300) -> 0 | AF60: =SUM(SUMIF(konwertery!I$2:I$300,A60,Azymut!H$2:H$298),(SUMIF(konwertery!S$2:S$300,A60,AzymutB!H$2:H352)*2)) -> 0 | AG60: =SUM(SUMIF(konwertery!I$2:I$300,A60,konwertery!J$2:J$300),SUMIF(konwertery!S$2:S$300,A60,konwertery!T$2:T$300)) -> 0 | AI60: =SUMIF(konwertery!K$2:K$300,A60,Ebookpoint!F$14:F$312) -> 0 | AJ60: =SUMIF(konwertery!K$2:K$300,A60,Ebookpoint!M$14:M$312) -> 0 | AL60: =SUMIF(konwertery!L$2:L$300,A60,Nasbi!F$14:F$312) -> 0 | AM60: =SUMIF(konwertery!L$2:L$300,A60,Nasbi!K$14:K$312) -> 0 | AO60: =SUMIF(StorytelE!C$2:C$300,A60,konwertery!M$2:M$300)+SUMIF(StorytelA!C$2:C$300,A60,konwertery!N$2:N$300) -> 0 | AP60: =SUMIF(StorytelE!C$2:C$300,A60,konwertery!O$2:O$300)+SUMIF(StorytelA!C$2:C$300,A60,konwertery!P$2:P$300) -> 0 | AR60: =SUMIF(konwertery!U$2:U$300,A60,Audioteka!E$4:E$302) -> 0 | AS60: =SUMIF(konwertery!U$2:U$300,A60,Audioteka!O$4:O$302) -> 0 | AU60: =SUMIF(Bookbeat!A$9:A$309,A60,Bookbeat!H$9:H$309) -> 0 | AV60: =SUMIF(Bookbeat!A$9:A$309,A60,Bookbeat!L$9:L$309) -> 0
A61: 9788365156297 | B61: Polacy na krańcach świata: średniowiecze i nowożytność, Część 2 | E61: =H61+K61 -> 0 | F61: =I61+L61 -> 0 | H61: =SUMIF(konwertery!A$2:A$300,A61,Histmag!C$2:C$300) -> 0 | I61: =SUMIF(konwertery!A$2:A$300,A61,konwertery!B$2:B$300) * 0.97 -> 0 | K61: =N61+Q61+T61+W61+Z61+AC61+AF61+AI61+AL61+AO61+AR61+AU61 -> 0 | L61: =O61+R61+U61+X61+AA61+AD61+AG61+AJ61+AM61+AP61+AS61+AV61 -> 0 | N61: =SUMIF(konwertery!C$2:C$300,A61,Virtualo!L$2:L$300) -> 0 | O61: =(SUMIF(konwertery!C$2:C$300,A61,Virtualo!P$2:P$300)) -> 0 | Q61: =SUMIF(konwertery!D$2:D$300,A61,Empik!M$2:M$300) -> 0 | R61: =SUMIF(konwertery!D$2:D$300,A61,Empik!N$2:N$300) -> 0 | T61: =SUMIF(konwertery!E$2:E$300,A61,Publio!P$2:P$300) -> 0 | U61: =SUMIF(konwertery!E$2:E$300,A61,konwertery!F$2:F$300) -> 0 | W61: =SUMIF(Legimi!D$2:D$300,A61,Legimi!G$2:G$300) -> 0 | X61: =SUMIF(Legimi!D$2:D$300,A61,Legimi!H$2:H$300) -> 0 | Z61: =SUMIF(konwertery!G$2:G$302,A61,Nexto!J$2:J$283) -> 0 | AA61: =SUMIF(konwertery!G$2:G$302,A61,Nexto!N$2:P$302) -> 0 | AC61: =SUMIF(Woblink!E$9:E$309,A61,Woblink!I$9:I$309) -> 0 | AD61: =SUMIF(Woblink!E$14:E$314,A61,konwertery!R$2:R$300) -> 0 | AF61: =SUM(SUMIF(konwertery!I$2:I$300,A61,Azymut!H$2:H$298),(SUMIF(konwertery!S$2:S$300,A61,AzymutB!H$2:H353)*2)) -> 0 | AG61: =SUM(SUMIF(konwertery!I$2:I$300,A61,konwertery!J$2:J$300),SUMIF(konwertery!S$2:S$300,A61,konwertery!T$2:T$300)) -> 0 | AI61: =SUMIF(konwertery!K$2:K$300,A61,Ebookpoint!F$14:F$312) -> 0 | AJ61: =SUMIF(konwertery!K$2:K$300,A61,Ebookpoint!M$14:M$312) -> 0 | AL61: =SUMIF(konwertery!L$2:L$300,A61,Nasbi!F$14:F$312) -> 0 | AM61: =SUMIF(konwertery!L$2:L$300,A61,Nasbi!K$14:K$312) -> 0 | AO61: =SUMIF(StorytelE!C$2:C$300,A61,konwertery!M$2:M$300)+SUMIF(StorytelA!C$2:C$300,A61,konwertery!N$2:N$300) -> 0 | AP61: =SUMIF(StorytelE!C$2:C$300,A61,konwertery!O$2:O$300)+SUMIF(StorytelA!C$2:C$300,A61,konwertery!P$2:P$300) -> 0 | AR61: =SUMIF(konwertery!U$2:U$300,A61,Audioteka!E$4:E$302) -> 0 | AS61: =SUMIF(konwertery!U$2:U$300,A61,Audioteka!O$4:O$302) -> 0 | AU61: =SUMIF(Bookbeat!A$9:A$309,A61,Bookbeat!H$9:H$309) -> 0 | AV61: =SUMIF(Bookbeat!A$9:A$309,A61,Bookbeat!L$9:L$309) -> 0
A62: 9788365156013 | B62: Polacy na krańcach świata: XIX wiek | E62: =H62+K62 -> 1 | F62: =I62+L62 -> 9.08 | H62: =SUMIF(konwertery!A$2:A$300,A62,Histmag!C$2:C$300) -> 0 | I62: =SUMIF(konwertery!A$2:A$300,A62,konwertery!B$2:B$300) * 0.97 -> 0 | K62: =N62+Q62+T62+W62+Z62+AC62+AF62+AI62+AL62+AO62+AR62+AU62 -> 1 | L62: =O62+R62+U62+X62+AA62+AD62+AG62+AJ62+AM62+AP62+AS62+AV62 -> 9.08 | N62: =SUMIF(konwertery!C$2:C$300,A62,Virtualo!L$2:L$300) -> 0 | O62: =(SUMIF(konwertery!C$2:C$300,A62,Virtualo!P$2:P$300)) -> 0 | Q62: =SUMIF(konwertery!D$2:D$300,A62,Empik!M$2:M$300) -> 0 | R62: =SUMIF(konwertery!D$2:D$300,A62,Empik!N$2:N$300) -> 0 | T62: =SUMIF(konwertery!E$2:E$300,A62,Publio!P$2:P$300) -> 0 | U62: =SUMIF(konwertery!E$2:E$300,A62,konwertery!F$2:F$300) -> 0 | W62: =SUMIF(Legimi!D$2:D$300,A62,Legimi!G$2:G$300) -> 0 | X62: =SUMIF(Legimi!D$2:D$300,A62,Legimi!H$2:H$300) -> 0 | Z62: =SUMIF(konwertery!G$2:G$302,A62,Nexto!J$2:J$283) -> 0 | AA62: =SUMIF(konwertery!G$2:G$302,A62,Nexto!N$2:P$302) -> 0 | AC62: =SUMIF(Woblink!E$9:E$309,A62,Woblink!I$9:I$309) -> 0 | AD62: =SUMIF(Woblink!E$14:E$314,A62,konwertery!R$2:R$300) -> 0 | AF62: =SUM(SUMIF(konwertery!I$2:I$300,A62,Azymut!H$2:H$298),(SUMIF(konwertery!S$2:S$300,A62,AzymutB!H$2:H354)*2)) -> 0 | AG62: =SUM(SUMIF(konwertery!I$2:I$300,A62,konwertery!J$2:J$300),SUMIF(konwertery!S$2:S$300,A62,konwertery!T$2:T$300)) -> 0 | AI62: =SUMIF(konwertery!K$2:K$300,A62,Ebookpoint!F$14:F$312) -> 1 | AJ62: =SUMIF(konwertery!K$2:K$300,A62,Ebookpoint!M$14:M$312) -> 9.08 | AL62: =SUMIF(konwertery!L$2:L$300,A62,Nasbi!F$14:F$312) -> 0 | AM62: =SUMIF(konwertery!L$2:L$300,A62,Nasbi!K$14:K$312) -> 0 | AO62: =SUMIF(StorytelE!C$2:C$300,A62,konwertery!M$2:M$300)+SUMIF(StorytelA!C$2:C$300,A62,konwertery!N$2:N$300) -> 0 | AP62: =SUMIF(StorytelE!C$2:C$300,A62,konwertery!O$2:O$300)+SUMIF(StorytelA!C$2:C$300,A62,konwertery!P$2:P$300) -> 0 | AR62: =SUMIF(konwertery!U$2:U$300,A62,Audioteka!E$4:E$302) -> 0 | AS62: =SUMIF(konwertery!U$2:U$300,A62,Audioteka!O$4:O$302) -> 0 | AU62: =SUMIF(Bookbeat!A$9:A$309,A62,Bookbeat!H$9:H$309) -> 0 | AV62: =SUMIF(Bookbeat!A$9:A$309,A62,Bookbeat!L$9:L$309) -> 0
A63: 9788365156020 | B63: Polacy na krańcach świata: XIX wiek, Część II | E63: =H63+K63 -> 0 | F63: =I63+L63 -> 0 | H63: =SUMIF(konwertery!A$2:A$300,A63,Histmag!C$2:C$300) -> 0 | I63: =SUMIF(konwertery!A$2:A$300,A63,konwertery!B$2:B$300) * 0.97 -> 0 | K63: =N63+Q63+T63+W63+Z63+AC63+AF63+AI63+AL63+AO63+AR63+AU63 -> 0 | L63: =O63+R63+U63+X63+AA63+AD63+AG63+AJ63+AM63+AP63+AS63+AV63 -> 0 | N63: =SUMIF(konwertery!C$2:C$300,A63,Virtualo!L$2:L$300) -> 0 | O63: =(SUMIF(konwertery!C$2:C$300,A63,Virtualo!P$2:P$300)) -> 0 | Q63: =SUMIF(konwertery!D$2:D$300,A63,Empik!M$2:M$300) -> 0 | R63: =SUMIF(konwertery!D$2:D$300,A63,Empik!N$2:N$300) -> 0 | T63: =SUMIF(konwertery!E$2:E$300,A63,Publio!P$2:P$300) -> 0 | U63: =SUMIF(konwertery!E$2:E$300,A63,konwertery!F$2:F$300) -> 0 | W63: =SUMIF(Legimi!D$2:D$300,A63,Legimi!G$2:G$300) -> 0 | X63: =SUMIF(Legimi!D$2:D$300,A63,Legimi!H$2:H$300) -> 0 | Z63: =SUMIF(konwertery!G$2:G$302,A63,Nexto!J$2:J$283) -> 0 | AA63: =SUMIF(konwertery!G$2:G$302,A63,Nexto!N$2:P$302) -> 0 | AC63: =SUMIF(Woblink!E$9:E$309,A63,Woblink!I$9:I$309) -> 0 | AD63: =SUMIF(Woblink!E$14:E$314,A63,konwertery!R$2:R$300) -> 0 | AF63: =SUM(SUMIF(konwertery!I$2:I$300,A63,Azymut!H$2:H$298),(SUMIF(konwertery!S$2:S$300,A63,AzymutB!H$2:H355)*2)) -> 0 | AG63: =SUM(SUMIF(konwertery!I$2:I$300,A63,konwertery!J$2:J$300),SUMIF(konwertery!S$2:S$300,A63,konwertery!T$2:T$300)) -> 0 | AI63: =SUMIF(konwertery!K$2:K$300,A63,Ebookpoint!F$14:F$312) -> 0 | AJ63: =SUMIF(konwertery!K$2:K$300,A63,Ebookpoint!M$14:M$312) -> 0 | AL63: =SUMIF(konwertery!L$2:L$300,A63,Nasbi!F$14:F$312) -> 0 | AM63: =SUMIF(konwertery!L$2:L$300,A63,Nasbi!K$14:K$312) -> 0 | AO63: =SUMIF(StorytelE!C$2:C$300,A63,konwertery!M$2:M$300)+SUMIF(StorytelA!C$2:C$300,A63,konwertery!N$2:N$300) -> 0 | AP63: =SUMIF(StorytelE!C$2:C$300,A63,konwertery!O$2:O$300)+SUMIF(StorytelA!C$2:C$300,A63,konwertery!P$2:P$300) -> 0 | AR63: =SUMIF(konwertery!U$2:U$300,A63,Audioteka!E$4:E$302) -> 0 | AS63: =SUMIF(konwertery!U$2:U$300,A63,Audioteka!O$4:O$302) -> 0 | AU63: =SUMIF(Bookbeat!A$9:A$309,A63,Bookbeat!H$9:H$309) -> 0 | AV63: =SUMIF(Bookbeat!A$9:A$309,A63,Bookbeat!L$9:L$309) -> 0
A64: 9788365156082 | B64: Polacy na krańcach świata: XIX wiek, Część III | E64: =H64+K64 -> 0 | F64: =I64+L64 -> 0 | H64: =SUMIF(konwertery!A$2:A$300,A64,Histmag!C$2:C$300) -> 0 | I64: =SUMIF(konwertery!A$2:A$300,A64,konwertery!B$2:B$300) * 0.97 -> 0 | K64: =N64+Q64+T64+W64+Z64+AC64+AF64+AI64+AL64+AO64+AR64+AU64 -> 0 | L64: =O64+R64+U64+X64+AA64+AD64+AG64+AJ64+AM64+AP64+AS64+AV64 -> 0 | N64: =SUMIF(konwertery!C$2:C$300,A64,Virtualo!L$2:L$300) -> 0 | O64: =(SUMIF(konwertery!C$2:C$300,A64,Virtualo!P$2:P$300)) -> 0 | Q64: =SUMIF(konwertery!D$2:D$300,A64,Empik!M$2:M$300) -> 0 | R64: =SUMIF(konwertery!D$2:D$300,A64,Empik!N$2:N$300) -> 0 | T64: =SUMIF(konwertery!E$2:E$300,A64,Publio!P$2:P$300) -> 0 | U64: =SUMIF(konwertery!E$2:E$300,A64,konwertery!F$2:F$300) -> 0 | W64: =SUMIF(Legimi!D$2:D$300,A64,Legimi!G$2:G$300) -> 0 | X64: =SUMIF(Legimi!D$2:D$300,A64,Legimi!H$2:H$300) -> 0 | Z64: =SUMIF(konwertery!G$2:G$302,A64,Nexto!J$2:J$283) -> 0 | AA64: =SUMIF(konwertery!G$2:G$302,A64,Nexto!N$2:P$302) -> 0 | AC64: =SUMIF(Woblink!E$9:E$309,A64,Woblink!I$9:I$309) -> 0 | AD64: =SUMIF(Woblink!E$14:E$314,A64,konwertery!R$2:R$300) -> 0 | AF64: =SUM(SUMIF(konwertery!I$2:I$300,A64,Azymut!H$2:H$298),(SUMIF(konwertery!S$2:S$300,A64,AzymutB!H$2:H356)*2)) -> 0 | AG64: =SUM(SUMIF(konwertery!I$2:I$300,A64,konwertery!J$2:J$300),SUMIF(konwertery!S$2:S$300,A64,konwertery!T$2:T$300)) -> 0 | AI64: =SUMIF(konwertery!K$2:K$300,A64,Ebookpoint!F$14:F$312) -> 0 | AJ64: =SUMIF(konwertery!K$2:K$300,A64,Ebookpoint!M$14:M$312) -> 0 | AL64: =SUMIF(konwertery!L$2:L$300,A64,Nasbi!F$14:F$312) -> 0 | AM64: =SUMIF(konwertery!L$2:L$300,A64,Nasbi!K$14:K$312) -> 0 | AO64: =SUMIF(StorytelE!C$2:C$300,A64,konwertery!M$2:M$300)+SUMIF(StorytelA!C$2:C$300,A64,konwertery!N$2:N$300) -> 0 | AP64: =SUMIF(StorytelE!C$2:C$300,A64,konwertery!O$2:O$300)+SUMIF(StorytelA!C$2:C$300,A64,konwertery!P$2:P$300) -> 0 | AR64: =SUMIF(konwertery!U$2:U$300,A64,Audioteka!E$4:E$302) -> 0 | AS64: =SUMIF(konwertery!U$2:U$300,A64,Audioteka!O$4:O$302) -> 0 | AU64: =SUMIF(Bookbeat!A$9:A$309,A64,Bookbeat!H$9:H$309) -> 0 | AV64: =SUMIF(Bookbeat!A$9:A$309,A64,Bookbeat!L$9:L$309) -> 0
A65: 9788365156488 | B65: Polacy na krańcach świata: XX wiek | E65: =H65+K65 -> 0 | F65: =I65+L65 -> 0 | H65: =SUMIF(konwertery!A$2:A$300,A65,Histmag!C$2:C$300) -> 0 | I65: =SUMIF(konwertery!A$2:A$300,A65,konwertery!B$2:B$300) * 0.97 -> 0 | K65: =N65+Q65+T65+W65+Z65+AC65+AF65+AI65+AL65+AO65+AR65+AU65 -> 0 | L65: =O65+R65+U65+X65+AA65+AD65+AG65+AJ65+AM65+AP65+AS65+AV65 -> 0 | N65: =SUMIF(konwertery!C$2:C$300,A65,Virtualo!L$2:L$300) -> 0 | O65: =(SUMIF(konwertery!C$2:C$300,A65,Virtualo!P$2:P$300)) -> 0 | Q65: =SUMIF(konwertery!D$2:D$300,A65,Empik!M$2:M$300) -> 0 | R65: =SUMIF(konwertery!D$2:D$300,A65,Empik!N$2:N$300) -> 0 | T65: =SUMIF(konwertery!E$2:E$300,A65,Publio!P$2:P$300) -> 0 | U65: =SUMIF(konwertery!E$2:E$300,A65,konwertery!F$2:F$300) -> 0 | W65: =SUMIF(Legimi!D$2:D$300,A65,Legimi!G$2:G$300) -> 0 | X65: =SUMIF(Legimi!D$2:D$300,A65,Legimi!H$2:H$300) -> 0 | Z65: =SUMIF(konwertery!G$2:G$302,A65,Nexto!J$2:J$283) -> 0 | AA65: =SUMIF(konwertery!G$2:G$302,A65,Nexto!N$2:P$302) -> 0 | AC65: =SUMIF(Woblink!E$9:E$309,A65,Woblink!I$9:I$309) -> 0 | AD65: =SUMIF(Woblink!E$14:E$314,A65,konwertery!R$2:R$300) -> 0 | AF65: =SUM(SUMIF(konwertery!I$2:I$300,A65,Azymut!H$2:H$298),(SUMIF(konwertery!S$2:S$300,A65,AzymutB!H$2:H357)*2)) -> 0 | AG65: =SUM(SUMIF(konwertery!I$2:I$300,A65,konwertery!J$2:J$300),SUMIF(konwertery!S$2:S$300,A65,konwertery!T$2:T$300)) -> 0 | AI65: =SUMIF(konwertery!K$2:K$300,A65,Ebookpoint!F$14:F$312) -> 0 | AJ65: =SUMIF(konwertery!K$2:K$300,A65,Ebookpoint!M$14:M$312) -> 0 | AL65: =SUMIF(konwertery!L$2:L$300,A65,Nasbi!F$14:F$312) -> 0 | AM65: =SUMIF(konwertery!L$2:L$300,A65,Nasbi!K$14:K$312) -> 0 | AO65: =SUMIF(StorytelE!C$2:C$300,A65,konwertery!M$2:M$300)+SUMIF(StorytelA!C$2:C$300,A65,konwertery!N$2:N$300) -> 0 | AP65: =SUMIF(StorytelE!C$2:C$300,A65,konwertery!O$2:O$300)+SUMIF(StorytelA!C$2:C$300,A65,konwertery!P$2:P$300) -> 0 | AR65: =SUMIF(konwertery!U$2:U$300,A65,Audioteka!E$4:E$302) -> 0 | AS65: =SUMIF(konwertery!U$2:U$300,A65,Audioteka!O$4:O$302) -> 0 | AU65: =SUMIF(Bookbeat!A$9:A$309,A65,Bookbeat!H$9:H$309) -> 0 | AV65: =SUMIF(Bookbeat!A$9:A$309,A65,Bookbeat!L$9:L$309) -> 0
A66: 9788365156693 | B66: Polacy na krańcach świata: XX wiek, Część II | E66: =H66+K66 -> 0 | F66: =I66+L66 -> 0 | H66: =SUMIF(konwertery!A$2:A$300,A66,Histmag!C$2:C$300) -> 0 | I66: =SUMIF(konwertery!A$2:A$300,A66,konwertery!B$2:B$300) * 0.97 -> 0 | K66: =N66+Q66+T66+W66+Z66+AC66+AF66+AI66+AL66+AO66+AR66+AU66 -> 0 | L66: =O66+R66+U66+X66+AA66+AD66+AG66+AJ66+AM66+AP66+AS66+AV66 -> 0 | N66: =SUMIF(konwertery!C$2:C$300,A66,Virtualo!L$2:L$300) -> 0 | O66: =(SUMIF(konwertery!C$2:C$300,A66,Virtualo!P$2:P$300)) -> 0 | Q66: =SUMIF(konwertery!D$2:D$300,A66,Empik!M$2:M$300) -> 0 | R66: =SUMIF(konwertery!D$2:D$300,A66,Empik!N$2:N$300) -> 0 | T66: =SUMIF(konwertery!E$2:E$300,A66,Publio!P$2:P$300) -> 0 | U66: =SUMIF(konwertery!E$2:E$300,A66,konwertery!F$2:F$300) -> 0 | W66: =SUMIF(Legimi!D$2:D$300,A66,Legimi!G$2:G$300) -> 0 | X66: =SUMIF(Legimi!D$2:D$300,A66,Legimi!H$2:H$300) -> 0 | Z66: =SUMIF(konwertery!G$2:G$302,A66,Nexto!J$2:J$283) -> 0 | AA66: =SUMIF(konwertery!G$2:G$302,A66,Nexto!N$2:P$302) -> 0 | AC66: =SUMIF(Woblink!E$9:E$309,A66,Woblink!I$9:I$309) -> 0 | AD66: =SUMIF(Woblink!E$14:E$314,A66,konwertery!R$2:R$300) -> 0 | AF66: =SUM(SUMIF(konwertery!I$2:I$300,A66,Azymut!H$2:H$298),(SUMIF(konwertery!S$2:S$300,A66,AzymutB!H$2:H358)*2)) -> 0 | AG66: =SUM(SUMIF(konwertery!I$2:I$300,A66,konwertery!J$2:J$300),SUMIF(konwertery!S$2:S$300,A66,konwertery!T$2:T$300)) -> 0 | AI66: =SUMIF(konwertery!K$2:K$300,A66,Ebookpoint!F$14:F$312) -> 0 | AJ66: =SUMIF(konwertery!K$2:K$300,A66,Ebookpoint!M$14:M$312) -> 0 | AL66: =SUMIF(konwertery!L$2:L$300,A66,Nasbi!F$14:F$312) -> 0 | AM66: =SUMIF(konwertery!L$2:L$300,A66,Nasbi!K$14:K$312) -> 0 | AO66: =SUMIF(StorytelE!C$2:C$300,A66,konwertery!M$2:M$300)+SUMIF(StorytelA!C$2:C$300,A66,konwertery!N$2:N$300) -> 0 | AP66: =SUMIF(StorytelE!C$2:C$300,A66,konwertery!O$2:O$300)+SUMIF(StorytelA!C$2:C$300,A66,konwertery!P$2:P$300) -> 0 | AR66: =SUMIF(konwertery!U$2:U$300,A66,Audioteka!E$4:E$302) -> 0 | AS66: =SUMIF(konwertery!U$2:U$300,A66,Audioteka!O$4:O$302) -> 0 | AU66: =SUMIF(Bookbeat!A$9:A$309,A66,Bookbeat!H$9:H$309) -> 0 | AV66: =SUMIF(Bookbeat!A$9:A$309,A66,Bookbeat!L$9:L$309) -> 0
A67: 9788393463091 | B67: Polowanie na stalowe słonie, Karabiny przeciwpancerne 1917 – 1945 | E67: =H67+K67 -> 1 | F67: =I67+L67 -> 7.98 | H67: =SUMIF(konwertery!A$2:A$300,A67,Histmag!C$2:C$300) -> 0 | I67: =SUMIF(konwertery!A$2:A$300,A67,konwertery!B$2:B$300) * 0.97 -> 0 | K67: =N67+Q67+T67+W67+Z67+AC67+AF67+AI67+AL67+AO67+AR67+AU67 -> 1 | L67: =O67+R67+U67+X67+AA67+AD67+AG67+AJ67+AM67+AP67+AS67+AV67 -> 7.98 | N67: =SUMIF(konwertery!C$2:C$300,A67,Virtualo!L$2:L$300) -> 1 | O67: =(SUMIF(konwertery!C$2:C$300,A67,Virtualo!P$2:P$300)) -> 7.98 | Q67: =SUMIF(konwertery!D$2:D$300,A67,Empik!M$2:M$300) -> 0 | R67: =SUMIF(konwertery!D$2:D$300,A67,Empik!N$2:N$300) -> 0 | T67: =SUMIF(konwertery!E$2:E$300,A67,Publio!P$2:P$300) -> 0 | U67: =SUMIF(konwertery!E$2:E$300,A67,konwertery!F$2:F$300) -> 0 | W67: =SUMIF(Legimi!D$2:D$300,A67,Legimi!G$2:G$300) -> 0 | X67: =SUMIF(Legimi!D$2:D$300,A67,Legimi!H$2:H$300) -> 0 | Z67: =SUMIF(konwertery!G$2:G$302,A67,Nexto!J$2:J$283) -> 0 | AA67: =SUMIF(konwertery!G$2:G$302,A67,Nexto!N$2:P$302) -> 0 | AC67: =SUMIF(Woblink!E$9:E$309,A67,Woblink!I$9:I$309) -> 0 | AD67: =SUMIF(Woblink!E$14:E$314,A67,konwertery!R$2:R$300) -> 0 | AF67: =SUM(SUMIF(konwertery!I$2:I$300,A67,Azymut!H$2:H$298),(SUMIF(konwertery!S$2:S$300,A67,AzymutB!H$2:H359)*2)) -> 0 | AG67: =SUM(SUMIF(konwertery!I$2:I$300,A67,konwertery!J$2:J$300),SUMIF(konwertery!S$2:S$300,A67,konwertery!T$2:T$300)) -> 0 | AI67: =SUMIF(konwertery!K$2:K$300,A67,Ebookpoint!F$14:F$312) -> 0 | AJ67: =SUMIF(konwertery!K$2:K$300,A67,Ebookpoint!M$14:M$312) -> 0 | AL67: =SUMIF(konwertery!L$2:L$300,A67,Nasbi!F$14:F$312) -> 0 | AM67: =SUMIF(konwertery!L$2:L$300,A67,Nasbi!K$14:K$312) -> 0 | AO67: =SUMIF(StorytelE!C$2:C$300,A67,konwertery!M$2:M$300)+SUMIF(StorytelA!C$2:C$300,A67,konwertery!N$2:N$300) -> 0 | AP67: =SUMIF(StorytelE!C$2:C$300,A67,konwertery!O$2:O$300)+SUMIF(StorytelA!C$2:C$300,A67,konwertery!P$2:P$300) -> 0 | AR67: =SUMIF(konwertery!U$2:U$300,A67,Audioteka!E$4:E$302) -> 0 | AS67: =SUMIF(konwertery!U$2:U$300,A67,Audioteka!O$4:O$302) -> 0 | AU67: =SUMIF(Bookbeat!A$9:A$309,A67,Bookbeat!H$9:H$309) -> 0 | AV67: =SUMIF(Bookbeat!A$9:A$309,A67,Bookbeat!L$9:L$309) -> 0
A68: 9788365156655 | B68: Polscy Hipokratesi. Najświetniejsi lekarze Rzeczypospolitej | E68: =H68+K68 -> 3 | F68: =I68+L68 -> 34.6119 | H68: =SUMIF(konwertery!A$2:A$300,A68,Histmag!C$2:C$300) -> 1 | I68: =SUMIF(konwertery!A$2:A$300,A68,konwertery!B$2:B$300) * 0.97 -> 10.9319 | K68: =N68+Q68+T68+W68+Z68+AC68+AF68+AI68+AL68+AO68+AR68+AU68 -> 2 | L68: =O68+R68+U68+X68+AA68+AD68+AG68+AJ68+AM68+AP68+AS68+AV68 -> 23.68 | N68: =SUMIF(konwertery!C$2:C$300,A68,Virtualo!L$2:L$300) -> 1 | O68: =(SUMIF(konwertery!C$2:C$300,A68,Virtualo!P$2:P$300)) -> 12.31 | Q68: =SUMIF(konwertery!D$2:D$300,A68,Empik!M$2:M$300) -> 0 | R68: =SUMIF(konwertery!D$2:D$300,A68,Empik!N$2:N$300) -> 0 | T68: =SUMIF(konwertery!E$2:E$300,A68,Publio!P$2:P$300) -> 0 | U68: =SUMIF(konwertery!E$2:E$300,A68,konwertery!F$2:F$300) -> 0 | W68: =SUMIF(Legimi!D$2:D$300,A68,Legimi!G$2:G$300) -> 0 | X68: =SUMIF(Legimi!D$2:D$300,A68,Legimi!H$2:H$300) -> 0 | Z68: =SUMIF(konwertery!G$2:G$302,A68,Nexto!J$2:J$283) -> 0 | AA68: =SUMIF(konwertery!G$2:G$302,A68,Nexto!N$2:P$302) -> 0 | AC68: =SUMIF(Woblink!E$9:E$309,A68,Woblink!I$9:I$309) -> 1 | AD68: =SUMIF(Woblink!E$14:E$314,A68,konwertery!R$2:R$300) -> 11.37 | AF68: =SUM(SUMIF(konwertery!I$2:I$300,A68,Azymut!H$2:H$298),(SUMIF(konwertery!S$2:S$300,A68,AzymutB!H$2:H360)*2)) -> 0 | AG68: =SUM(SUMIF(konwertery!I$2:I$300,A68,konwertery!J$2:J$300),SUMIF(konwertery!S$2:S$300,A68,konwertery!T$2:T$300)) -> 0 | AI68: =SUMIF(konwertery!K$2:K$300,A68,Ebookpoint!F$14:F$312) -> 0 | AJ68: =SUMIF(konwertery!K$2:K$300,A68,Ebookpoint!M$14:M$312) -> 0 | AL68: =SUMIF(konwertery!L$2:L$300,A68,Nasbi!F$14:F$312) -> 0 | AM68: =SUMIF(konwertery!L$2:L$300,A68,Nasbi!K$14:K$312) -> 0 | AO68: =SUMIF(StorytelE!C$2:C$300,A68,konwertery!M$2:M$300)+SUMIF(StorytelA!C$2:C$300,A68,konwertery!N$2:N$300) -> 0 | AP68: =SUMIF(StorytelE!C$2:C$300,A68,konwertery!O$2:O$300)+SUMIF(StorytelA!C$2:C$300,A68,konwertery!P$2:P$300) -> 0 | AR68: =SUMIF(konwertery!U$2:U$300,A68,Audioteka!E$4:E$302) -> 0 | AS68: =SUMIF(konwertery!U$2:U$300,A68,Audioteka!O$4:O$302) -> 0 | AU68: =SUMIF(Bookbeat!A$9:A$309,A68,Bookbeat!H$9:H$309) -> 0 | AV68: =SUMIF(Bookbeat!A$9:A$309,A68,Bookbeat!L$9:L$309) -> 0
A69: 9788365156877 | B69: Polscy Hipokratesi. Najświetniejsi lekarze Rzeczypospolitej (audio) | E69: =H69+K69 -> 5 | F69: =I69+L69 -> 41.737 | H69: =SUMIF(konwertery!A$2:A$300,A69,Histmag!C$2:C$300) -> 1 | I69: =SUMIF(konwertery!A$2:A$300,A69,konwertery!B$2:B$300) * 0.97 -> 15.617 | K69: =N69+Q69+T69+W69+Z69+AC69+AF69+AI69+AL69+AO69+AR69+AU69 -> 4 | L69: =O69+R69+U69+X69+AA69+AD69+AG69+AJ69+AM69+AP69+AS69+AV69 -> 26.12 | N69: =SUMIF(konwertery!C$2:C$300,A69,Virtualo!L$2:L$300) -> 0 | O69: =(SUMIF(konwertery!C$2:C$300,A69,Virtualo!P$2:P$300)) -> 0 | Q69: =SUMIF(konwertery!D$2:D$300,A69,Empik!M$2:M$300) -> 0 | R69: =SUMIF(konwertery!D$2:D$300,A69,Empik!N$2:N$300) -> 0 | T69: =SUMIF(konwertery!E$2:E$300,A69,Publio!P$2:P$300) -> 1 | U69: =SUMIF(konwertery!E$2:E$300,A69,konwertery!F$2:F$300) -> 11.37 | W69: =SUMIF(Legimi!D$2:D$300,A69,Legimi!G$2:G$300) -> 0 | X69: =SUMIF(Legimi!D$2:D$300,A69,Legimi!H$2:H$300) -> 0 | Z69: =SUMIF(konwertery!G$2:G$302,A69,Nexto!J$2:J$283) -> 0 | AA69: =SUMIF(konwertery!G$2:G$302,A69,Nexto!N$2:P$302) -> 0 | AC69: =SUMIF(Woblink!E$9:E$309,A69,Woblink!I$9:I$309) -> 0 | AD69: =SUMIF(Woblink!E$14:E$314,A69,konwertery!R$2:R$300) -> 0 | AF69: =SUM(SUMIF(konwertery!I$2:I$300,A69,Azymut!H$2:H$298),(SUMIF(konwertery!S$2:S$300,A69,AzymutB!H$2:H361)*2)) -> 0 | AG69: =SUM(SUMIF(konwertery!I$2:I$300,A69,konwertery!J$2:J$300),SUMIF(konwertery!S$2:S$300,A69,konwertery!T$2:T$300)) -> 0 | AI69: =SUMIF(konwertery!K$2:K$300,A69,Ebookpoint!F$14:F$312) -> 0 | AJ69: =SUMIF(konwertery!K$2:K$300,A69,Ebookpoint!M$14:M$312) -> 0 | AL69: =SUMIF(konwertery!L$2:L$300,A69,Nasbi!F$14:F$312) -> 0 | AM69: =SUMIF(konwertery!L$2:L$300,A69,Nasbi!K$14:K$312) -> 0 | AO69: =SUMIF(StorytelE!C$2:C$300,A69,konwertery!M$2:M$300)+SUMIF(StorytelA!C$2:C$300,A69,konwertery!N$2:N$300) -> 1 | AP69: =SUMIF(StorytelE!C$2:C$300,A69,konwertery!O$2:O$300)+SUMIF(StorytelA!C$2:C$300,A69,konwertery!P$2:P$300) -> 3.66 | AR69: =SUMIF(konwertery!U$2:U$300,A69,Audioteka!E$4:E$302) -> 0 | AS69: =SUMIF(konwertery!U$2:U$300,A69,Audioteka!O$4:O$302) -> 0 | AU69: =SUMIF(Bookbeat!A$9:A$309,A69,Bookbeat!H$9:H$309) -> 2 | AV69: =SUMIF(Bookbeat!A$9:A$309,A69,Bookbeat!L$9:L$309) -> 11.09
A70: 9788365156440 | B70: Poradnik młodego humanisty, Studia bez tajemnic | E70: =H70+K70 -> 1 | F70: =I70+L70 -> 10.9901 | H70: =SUMIF(konwertery!A$2:A$300,A70,Histmag!C$2:C$300) -> 1 | I70: =SUMIF(konwertery!A$2:A$300,A70,konwertery!B$2:B$300) * 0.97 -> 10.9901 | K70: =N70+Q70+T70+W70+Z70+AC70+AF70+AI70+AL70+AO70+AR70+AU70 -> 0 | L70: =O70+R70+U70+X70+AA70+AD70+AG70+AJ70+AM70+AP70+AS70+AV70 -> 0 | N70: =SUMIF(konwertery!C$2:C$300,A70,Virtualo!L$2:L$300) -> 0 | O70: =(SUMIF(konwertery!C$2:C$300,A70,Virtualo!P$2:P$300)) -> 0 | Q70: =SUMIF(konwertery!D$2:D$300,A70,Empik!M$2:M$300) -> 0 | R70: =SUMIF(konwertery!D$2:D$300,A70,Empik!N$2:N$300) -> 0 | T70: =SUMIF(konwertery!E$2:E$300,A70,Publio!P$2:P$300) -> 0 | U70: =SUMIF(konwertery!E$2:E$300,A70,konwertery!F$2:F$300) -> 0 | W70: =SUMIF(Legimi!D$2:D$300,A70,Legimi!G$2:G$300) -> 0 | X70: =SUMIF(Legimi!D$2:D$300,A70,Legimi!H$2:H$300) -> 0 | Z70: =SUMIF(konwertery!G$2:G$302,A70,Nexto!J$2:J$283) -> 0 | AA70: =SUMIF(konwertery!G$2:G$302,A70,Nexto!N$2:P$302) -> 0 | AC70: =SUMIF(Woblink!E$9:E$309,A70,Woblink!I$9:I$309) -> 0 | AD70: =SUMIF(Woblink!E$14:E$314,A70,konwertery!R$2:R$300) -> 0 | AF70: =SUM(SUMIF(konwertery!I$2:I$300,A70,Azymut!H$2:H$298),(SUMIF(konwertery!S$2:S$300,A70,AzymutB!H$2:H361)*2)) -> 0 | AG70: =SUM(SUMIF(konwertery!I$2:I$300,A70,konwertery!J$2:J$300),SUMIF(konwertery!S$2:S$300,A70,konwertery!T$2:T$300)) -> 0 | AI70: =SUMIF(konwertery!K$2:K$300,A70,Ebookpoint!F$14:F$312) -> 0 | AJ70: =SUMIF(konwertery!K$2:K$300,A70,Ebookpoint!M$14:M$312) -> 0 | AL70: =SUMIF(konwertery!L$2:L$300,A70,Nasbi!F$14:F$312) -> 0 | AM70: =SUMIF(konwertery!L$2:L$300,A70,Nasbi!K$14:K$312) -> 0 | AO70: =SUMIF(StorytelE!C$2:C$300,A70,konwertery!M$2:M$300)+SUMIF(StorytelA!C$2:C$300,A70,konwertery!N$2:N$300) -> 0 | AP70: =SUMIF(StorytelE!C$2:C$300,A70,konwertery!O$2:O$300)+SUMIF(StorytelA!C$2:C$300,A70,konwertery!P$2:P$300) -> 0 | AR70: =SUMIF(konwertery!U$2:U$300,A70,Audioteka!E$4:E$302) -> 0 | AS70: =SUMIF(konwertery!U$2:U$300,A70,Audioteka!O$4:O$302) -> 0 | AU70: =SUMIF(Bookbeat!A$9:A$309,A70,Bookbeat!H$9:H$309) -> 0 | AV70: =SUMIF(Bookbeat!A$9:A$309,A70,Bookbeat!L$9:L$309) -> 0
A71: 9788365156235 | B71: Powaby totalitaryzmu, Zarys historii intelektualnej komunizmu i faszyzmu | E71: =H71+K71 -> 3 | F71: =I71+L71 -> 19.83 | H71: =SUMIF(konwertery!A$2:A$300,A71,Histmag!C$2:C$300) -> 0 | I71: =SUMIF(konwertery!A$2:A$300,A71,konwertery!B$2:B$300) * 0.97 -> 0 | K71: =N71+Q71+T71+W71+Z71+AC71+AF71+AI71+AL71+AO71+AR71+AU71 -> 3 | L71: =O71+R71+U71+X71+AA71+AD71+AG71+AJ71+AM71+AP71+AS71+AV71 -> 19.83 | N71: =SUMIF(konwertery!C$2:C$300,A71,Virtualo!L$2:L$300) -> 1 | O71: =(SUMIF(konwertery!C$2:C$300,A71,Virtualo!P$2:P$300)) -> 9.22 | Q71: =SUMIF(konwertery!D$2:D$300,A71,Empik!M$2:M$300) -> 0 | R71: =SUMIF(konwertery!D$2:D$300,A71,Empik!N$2:N$300) -> 0 | T71: =SUMIF(konwertery!E$2:E$300,A71,Publio!P$2:P$300) -> 0 | U71: =SUMIF(konwertery!E$2:E$300,A71,konwertery!F$2:F$300) -> 0 | W71: =SUMIF(Legimi!D$2:D$300,A71,Legimi!G$2:G$300) -> 0 | X71: =SUMIF(Legimi!D$2:D$300,A71,Legimi!H$2:H$300) -> 0 | Z71: =SUMIF(konwertery!G$2:G$302,A71,Nexto!J$2:J$283) -> 0 | AA71: =SUMIF(konwertery!G$2:G$302,A71,Nexto!N$2:P$302) -> 0 | AC71: =SUMIF(Woblink!E$9:E$309,A71,Woblink!I$9:I$309) -> 0 | AD71: =SUMIF(Woblink!E$14:E$314,A71,konwertery!R$2:R$300) -> 0 | AF71: =SUM(SUMIF(konwertery!I$2:I$300,A71,Azymut!H$2:H$298),(SUMIF(konwertery!S$2:S$300,A71,AzymutB!H$2:H362)*2)) -> 0 | AG71: =SUM(SUMIF(konwertery!I$2:I$300,A71,konwertery!J$2:J$300),SUMIF(konwertery!S$2:S$300,A71,konwertery!T$2:T$300)) -> 0 | AI71: =SUMIF(konwertery!K$2:K$300,A71,Ebookpoint!F$14:F$312) -> 1 | AJ71: =SUMIF(konwertery!K$2:K$300,A71,Ebookpoint!M$14:M$312) -> 9.08 | AL71: =SUMIF(konwertery!L$2:L$300,A71,Nasbi!F$14:F$312) -> 0 | AM71: =SUMIF(konwertery!L$2:L$300,A71,Nasbi!K$14:K$312) -> 0 | AO71: =SUMIF(StorytelE!C$2:C$300,A71,konwertery!M$2:M$300)+SUMIF(StorytelA!C$2:C$300,A71,konwertery!N$2:N$300) -> 1 | AP71: =SUMIF(StorytelE!C$2:C$300,A71,konwertery!O$2:O$300)+SUMIF(StorytelA!C$2:C$300,A71,konwertery!P$2:P$300) -> 1.53 | AR71: =SUMIF(konwertery!U$2:U$300,A71,Audioteka!E$4:E$302) -> 0 | AS71: =SUMIF(konwertery!U$2:U$300,A71,Audioteka!O$4:O$302) -> 0 | AU71: =SUMIF(Bookbeat!A$9:A$309,A71,Bookbeat!H$9:H$309) -> 0 | AV71: =SUMIF(Bookbeat!A$9:A$309,A71,Bookbeat!L$9:L$309) -> 0
A72: 9788365156273 | B72: Przewodnik po Polskim Państwie Podziemnym 1939-45 | E72: =H72+K72 -> 3 | F72: =I72+L72 -> 25.2879 | H72: =SUMIF(konwertery!A$2:A$300,A72,Histmag!C$2:C$300) -> 3 | I72: =SUMIF(konwertery!A$2:A$300,A72,konwertery!B$2:B$300) * 0.97 -> 25.2879 | K72: =N72+Q72+T72+W72+Z72+AC72+AF72+AI72+AL72+AO72+AR72+AU72 -> 0 | L72: =O72+R72+U72+X72+AA72+AD72+AG72+AJ72+AM72+AP72+AS72+AV72 -> 0 | N72: =SUMIF(konwertery!C$2:C$300,A72,Virtualo!L$2:L$300) -> 0 | O72: =(SUMIF(konwertery!C$2:C$300,A72,Virtualo!P$2:P$300)) -> 0 | Q72: =SUMIF(konwertery!D$2:D$300,A72,Empik!M$2:M$300) -> 0 | R72: =SUMIF(konwertery!D$2:D$300,A72,Empik!N$2:N$300) -> 0 | T72: =SUMIF(konwertery!E$2:E$300,A72,Publio!P$2:P$300) -> 0 | U72: =SUMIF(konwertery!E$2:E$300,A72,konwertery!F$2:F$300) -> 0 | W72: =SUMIF(Legimi!D$2:D$300,A72,Legimi!G$2:G$300) -> 0 | X72: =SUMIF(Legimi!D$2:D$300,A72,Legimi!H$2:H$300) -> 0 | Z72: =SUMIF(konwertery!G$2:G$302,A72,Nexto!J$2:J$283) -> 0 | AA72: =SUMIF(konwertery!G$2:G$302,A72,Nexto!N$2:P$302) -> 0 | AC72: =SUMIF(Woblink!E$9:E$309,A72,Woblink!I$9:I$309) -> 0 | AD72: =SUMIF(Woblink!E$14:E$314,A72,konwertery!R$2:R$300) -> 0 | AF72: =SUM(SUMIF(konwertery!I$2:I$300,A72,Azymut!H$2:H$298),(SUMIF(konwertery!S$2:S$300,A72,AzymutB!H$2:H363)*2)) -> 0 | AG72: =SUM(SUMIF(konwertery!I$2:I$300,A72,konwertery!J$2:J$300),SUMIF(konwertery!S$2:S$300,A72,konwertery!T$2:T$300)) -> 0 | AI72: =SUMIF(konwertery!K$2:K$300,A72,Ebookpoint!F$14:F$312) -> 0 | AJ72: =SUMIF(konwertery!K$2:K$300,A72,Ebookpoint!M$14:M$312) -> 0 | AL72: =SUMIF(konwertery!L$2:L$300,A72,Nasbi!F$14:F$312) -> 0 | AM72: =SUMIF(konwertery!L$2:L$300,A72,Nasbi!K$14:K$312) -> 0 | AO72: =SUMIF(StorytelE!C$2:C$300,A72,konwertery!M$2:M$300)+SUMIF(StorytelA!C$2:C$300,A72,konwertery!N$2:N$300) -> 0 | AP72: =SUMIF(StorytelE!C$2:C$300,A72,konwertery!O$2:O$300)+SUMIF(StorytelA!C$2:C$300,A72,konwertery!P$2:P$300) -> 0 | AR72: =SUMIF(konwertery!U$2:U$300,A72,Audioteka!E$4:E$302) -> 0 | AS72: =SUMIF(konwertery!U$2:U$300,A72,Audioteka!O$4:O$302) -> 0 | AU72: =SUMIF(Bookbeat!A$9:A$309,A72,Bookbeat!H$9:H$309) -> 0 | AV72: =SUMIF(Bookbeat!A$9:A$309,A72,Bookbeat!L$9:L$309) -> 0
A73: 9788365156860 | B73: Seryjni mordercy. Oblicza najstraszniejszych zbrodni | E73: =H73+K73 -> 22 | F73: =I73+L73 -> 266.993 | H73: =SUMIF(konwertery!A$2:A$300,A73,Histmag!C$2:C$300) -> 9 | I73: =SUMIF(konwertery!A$2:A$300,A73,konwertery!B$2:B$300) * 0.97 -> 140.553 | K73: =N73+Q73+T73+W73+Z73+AC73+AF73+AI73+AL73+AO73+AR73+AU73 -> 13 | L73: =O73+R73+U73+X73+AA73+AD73+AG73+AJ73+AM73+AP73+AS73+AV73 -> 126.44 | N73: =SUMIF(konwertery!C$2:C$300,A73,Virtualo!L$2:L$300) -> 1 | O73: =(SUMIF(konwertery!C$2:C$300,A73,Virtualo!P$2:P$300)) -> 12.31 | Q73: =SUMIF(konwertery!D$2:D$300,A73,Empik!M$2:M$300) -> 0 | R73: =SUMIF(konwertery!D$2:D$300,A73,Empik!N$2:N$300) -> 0 | T73: =SUMIF(konwertery!E$2:E$300,A73,Publio!P$2:P$300) -> 5 | U73: =SUMIF(konwertery!E$2:E$300,A73,konwertery!F$2:F$300) -> 56.85 | W73: =SUMIF(Legimi!D$2:D$300,A73,Legimi!G$2:G$300) -> 1 | X73: =SUMIF(Legimi!D$2:D$300,A73,Legimi!H$2:H$300) -> 13.27 | Z73: =SUMIF(konwertery!G$2:G$302,A73,Nexto!J$2:J$283) -> 0 | AA73: =SUMIF(konwertery!G$2:G$302,A73,Nexto!N$2:P$302) -> 0 | AC73: =SUMIF(Woblink!E$9:E$309,A73,Woblink!I$9:I$309) -> 0 | AD73: =SUMIF(Woblink!E$14:E$314,A73,konwertery!R$2:R$300) -> 0 | AF73: =SUM(SUMIF(konwertery!I$2:I$300,A73,Azymut!H$2:H$298),(SUMIF(konwertery!S$2:S$300,A73,AzymutB!H$2:H364)*2)) -> 1 | AG73: =SUM(SUMIF(konwertery!I$2:I$300,A73,konwertery!J$2:J$300),SUMIF(konwertery!S$2:S$300,A73,konwertery!T$2:T$300)) -> 11.37 | AI73: =SUMIF(konwertery!K$2:K$300,A73,Ebookpoint!F$14:F$312) -> 2 | AJ73: =SUMIF(konwertery!K$2:K$300,A73,Ebookpoint!M$14:M$312) -> 24.26 | AL73: =SUMIF(konwertery!L$2:L$300,A73,Nasbi!F$14:F$312) -> 0 | AM73: =SUMIF(konwertery!L$2:L$300,A73,Nasbi!K$14:K$312) -> 0 | AO73: =SUMIF(StorytelE!C$2:C$300,A73,konwertery!M$2:M$300)+SUMIF(StorytelA!C$2:C$300,A73,konwertery!N$2:N$300) -> 3 | AP73: =SUMIF(StorytelE!C$2:C$300,A73,konwertery!O$2:O$300)+SUMIF(StorytelA!C$2:C$300,A73,konwertery!P$2:P$300) -> 8.38 | AR73: =SUMIF(konwertery!U$2:U$300,A73,Audioteka!E$4:E$302) -> 0 | AS73: =SUMIF(konwertery!U$2:U$300,A73,Audioteka!O$4:O$302) -> 0 | AU73: =SUMIF(Bookbeat!A$9:A$309,A73,Bookbeat!H$9:H$309) -> 0 | AV73: =SUMIF(Bookbeat!A$9:A$309,A73,Bookbeat!L$9:L$309) -> 0
A74: 9788365156396 | B74: Sojusznik czy wróg? Relacje polsko-niemieckie w czasach Mieszka I i Bolesława Chrobrego | E74: =H74+K74 -> 1 | F74: =I74+L74 -> 5.9461 | H74: =SUMIF(konwertery!A$2:A$300,A74,Histmag!C$2:C$300) -> 1 | I74: =SUMIF(konwertery!A$2:A$300,A74,konwertery!B$2:B$300) * 0.97 -> 5.9461 | K74: =N74+Q74+T74+W74+Z74+AC74+AF74+AI74+AL74+AO74+AR74+AU74 -> 0 | L74: =O74+R74+U74+X74+AA74+AD74+AG74+AJ74+AM74+AP74+AS74+AV74 -> 0 | N74: =SUMIF(konwertery!C$2:C$300,A74,Virtualo!L$2:L$300) -> 0 | O74: =(SUMIF(konwertery!C$2:C$300,A74,Virtualo!P$2:P$300)) -> 0 | Q74: =SUMIF(konwertery!D$2:D$300,A74,Empik!M$2:M$300) -> 0 | R74: =SUMIF(konwertery!D$2:D$300,A74,Empik!N$2:N$300) -> 0 | T74: =SUMIF(konwertery!E$2:E$300,A74,Publio!P$2:P$300) -> 0 | U74: =SUMIF(konwertery!E$2:E$300,A74,konwertery!F$2:F$300) -> 0 | W74: =SUMIF(Legimi!D$2:D$300,A74,Legimi!G$2:G$300) -> 0 | X74: =SUMIF(Legimi!D$2:D$300,A74,Legimi!H$2:H$300) -> 0 | Z74: =SUMIF(konwertery!G$2:G$302,A74,Nexto!J$2:J$283) -> 0 | AA74: =SUMIF(konwertery!G$2:G$302,A74,Nexto!N$2:P$302) -> 0 | AC74: =SUMIF(Woblink!E$9:E$309,A74,Woblink!I$9:I$309) -> 0 | AD74: =SUMIF(Woblink!E$14:E$314,A74,konwertery!R$2:R$300) -> 0 | AF74: =SUM(SUMIF(konwertery!I$2:I$300,A74,Azymut!H$2:H$298),(SUMIF(konwertery!S$2:S$300,A74,AzymutB!H$2:H364)*2)) -> 0 | AG74: =SUM(SUMIF(konwertery!I$2:I$300,A74,konwertery!J$2:J$300),SUMIF(konwertery!S$2:S$300,A74,konwertery!T$2:T$300)) -> 0 | AI74: =SUMIF(konwertery!K$2:K$300,A74,Ebookpoint!F$14:F$312) -> 0 | AJ74: =SUMIF(konwertery!K$2:K$300,A74,Ebookpoint!M$14:M$312) -> 0 | AL74: =SUMIF(konwertery!L$2:L$300,A74,Nasbi!F$14:F$312) -> 0 | AM74: =SUMIF(konwertery!L$2:L$300,A74,Nasbi!K$14:K$312) -> 0 | AO74: =SUMIF(StorytelE!C$2:C$300,A74,konwertery!M$2:M$300)+SUMIF(StorytelA!C$2:C$300,A74,konwertery!N$2:N$300) -> 0 | AP74: =SUMIF(StorytelE!C$2:C$300,A74,konwertery!O$2:O$300)+SUMIF(StorytelA!C$2:C$300,A74,konwertery!P$2:P$300) -> 0 | AR74: =SUMIF(konwertery!U$2:U$300,A74,Audioteka!E$4:E$302) -> 0 | AS74: =SUMIF(konwertery!U$2:U$300,A74,Audioteka!O$4:O$302) -> 0 | AU74: =SUMIF(Bookbeat!A$9:A$309,A74,Bookbeat!H$9:H$309) -> 0 | AV74: =SUMIF(Bookbeat!A$9:A$309,A74,Bookbeat!L$9:L$309) -> 0
A75: 9788365156150 | B75: Sportowa Warszawa przed I wojną światową | E75: =H75+K75 -> 1 | F75: =I75+L75 -> 9.08 | H75: =SUMIF(konwertery!A$2:A$300,A75,Histmag!C$2:C$300) -> 0 | I75: =SUMIF(konwertery!A$2:A$300,A75,konwertery!B$2:B$300) * 0.97 -> 0 | K75: =N75+Q75+T75+W75+Z75+AC75+AF75+AI75+AL75+AO75+AR75+AU75 -> 1 | L75: =O75+R75+U75+X75+AA75+AD75+AG75+AJ75+AM75+AP75+AS75+AV75 -> 9.08 | N75: =SUMIF(konwertery!C$2:C$300,A75,Virtualo!L$2:L$300) -> 0 | O75: =(SUMIF(konwertery!C$2:C$300,A75,Virtualo!P$2:P$300)) -> 0 | Q75: =SUMIF(konwertery!D$2:D$300,A75,Empik!M$2:M$300) -> 0 | R75: =SUMIF(konwertery!D$2:D$300,A75,Empik!N$2:N$300) -> 0 | T75: =SUMIF(konwertery!E$2:E$300,A75,Publio!P$2:P$300) -> 0 | U75: =SUMIF(konwertery!E$2:E$300,A75,konwertery!F$2:F$300) -> 0 | W75: =SUMIF(Legimi!D$2:D$300,A75,Legimi!G$2:G$300) -> 0 | X75: =SUMIF(Legimi!D$2:D$300,A75,Legimi!H$2:H$300) -> 0 | Z75: =SUMIF(konwertery!G$2:G$302,A75,Nexto!J$2:J$283) -> 0 | AA75: =SUMIF(konwertery!G$2:G$302,A75,Nexto!N$2:P$302) -> 0 | AC75: =SUMIF(Woblink!E$9:E$309,A75,Woblink!I$9:I$309) -> 0 | AD75: =SUMIF(Woblink!E$14:E$314,A75,konwertery!R$2:R$300) -> 0 | AF75: =SUM(SUMIF(konwertery!I$2:I$300,A75,Azymut!H$2:H$298),(SUMIF(konwertery!S$2:S$300,A75,AzymutB!H$2:H365)*2)) -> 0 | AG75: =SUM(SUMIF(konwertery!I$2:I$300,A75,konwertery!J$2:J$300),SUMIF(konwertery!S$2:S$300,A75,konwertery!T$2:T$300)) -> 0 | AI75: =SUMIF(konwertery!K$2:K$300,A75,Ebookpoint!F$14:F$312) -> 1 | AJ75: =SUMIF(konwertery!K$2:K$300,A75,Ebookpoint!M$14:M$312) -> 9.08 | AL75: =SUMIF(konwertery!L$2:L$300,A75,Nasbi!F$14:F$312) -> 0 | AM75: =SUMIF(konwertery!L$2:L$300,A75,Nasbi!K$14:K$312) -> 0 | AO75: =SUMIF(StorytelE!C$2:C$300,A75,konwertery!M$2:M$300)+SUMIF(StorytelA!C$2:C$300,A75,konwertery!N$2:N$300) -> 0 | AP75: =SUMIF(StorytelE!C$2:C$300,A75,konwertery!O$2:O$300)+SUMIF(StorytelA!C$2:C$300,A75,konwertery!P$2:P$300) -> 0 | AR75: =SUMIF(konwertery!U$2:U$300,A75,Audioteka!E$4:E$302) -> 0 | AS75: =SUMIF(konwertery!U$2:U$300,A75,Audioteka!O$4:O$302) -> 0 | AU75: =SUMIF(Bookbeat!A$9:A$309,A75,Bookbeat!H$9:H$309) -> 0 | AV75: =SUMIF(Bookbeat!A$9:A$309,A75,Bookbeat!L$9:L$309) -> 0
A76: 9788365156600 | B76: Sto lat Nosferatu | E76: =H76+K76 -> 2 | F76: =I76+L76 -> 21.99 | H76: =SUMIF(konwertery!A$2:A$300,A76,Histmag!C$2:C$300) -> 0 | I76: =SUMIF(konwertery!A$2:A$300,A76,konwertery!B$2:B$300) * 0.97 -> 0 | K76: =N76+Q76+T76+W76+Z76+AC76+AF76+AI76+AL76+AO76+AR76+AU76 -> 2 | L76: =O76+R76+U76+X76+AA76+AD76+AG76+AJ76+AM76+AP76+AS76+AV76 -> 21.99 | N76: =SUMIF(konwertery!C$2:C$300,A76,Virtualo!L$2:L$300) -> 1 | O76: =(SUMIF(konwertery!C$2:C$300,A76,Virtualo!P$2:P$300)) -> 11.08 | Q76: =SUMIF(konwertery!D$2:D$300,A76,Empik!M$2:M$300) -> 0 | R76: =SUMIF(konwertery!D$2:D$300,A76,Empik!N$2:N$300) -> 0 | T76: =SUMIF(konwertery!E$2:E$300,A76,Publio!P$2:P$300) -> 0 | U76: =SUMIF(konwertery!E$2:E$300,A76,konwertery!F$2:F$300) -> 0 | W76: =SUMIF(Legimi!D$2:D$300,A76,Legimi!G$2:G$300) -> 0 | X76: =SUMIF(Legimi!D$2:D$300,A76,Legimi!H$2:H$300) -> 0 | Z76: =SUMIF(konwertery!G$2:G$302,A76,Nexto!J$2:J$283) -> 0 | AA76: =SUMIF(konwertery!G$2:G$302,A76,Nexto!N$2:P$302) -> 0 | AC76: =SUMIF(Woblink!E$9:E$309,A76,Woblink!I$9:I$309) -> 0 | AD76: =SUMIF(Woblink!E$14:E$314,A76,konwertery!R$2:R$300) -> 0 | AF76: =SUM(SUMIF(konwertery!I$2:I$300,A76,Azymut!H$2:H$298),(SUMIF(konwertery!S$2:S$300,A76,AzymutB!H$2:H366)*2)) -> 0 | AG76: =SUM(SUMIF(konwertery!I$2:I$300,A76,konwertery!J$2:J$300),SUMIF(konwertery!S$2:S$300,A76,konwertery!T$2:T$300)) -> 0 | AI76: =SUMIF(konwertery!K$2:K$300,A76,Ebookpoint!F$14:F$312) -> 1 | AJ76: =SUMIF(konwertery!K$2:K$300,A76,Ebookpoint!M$14:M$312) -> 10.91 | AL76: =SUMIF(konwertery!L$2:L$300,A76,Nasbi!F$14:F$312) -> 0 | AM76: =SUMIF(konwertery!L$2:L$300,A76,Nasbi!K$14:K$312) -> 0 | AO76: =SUMIF(StorytelE!C$2:C$300,A76,konwertery!M$2:M$300)+SUMIF(StorytelA!C$2:C$300,A76,konwertery!N$2:N$300) -> 0 | AP76: =SUMIF(StorytelE!C$2:C$300,A76,konwertery!O$2:O$300)+SUMIF(StorytelA!C$2:C$300,A76,konwertery!P$2:P$300) -> 0 | AR76: =SUMIF(konwertery!U$2:U$300,A76,Audioteka!E$4:E$302) -> 0 | AS76: =SUMIF(konwertery!U$2:U$300,A76,Audioteka!O$4:O$302) -> 0 | AU76: =SUMIF(Bookbeat!A$9:A$309,A76,Bookbeat!H$9:H$309) -> 0 | AV76: =SUMIF(Bookbeat!A$9:A$309,A76,Bookbeat!L$9:L$309) -> 0
A77: 9788365156556 | B77: Trylogia Sienkiewicza, Historia prawdziwa | E77: =H77+K77 -> 70 | F77: =I77+L77 -> 469.9475 | H77: =SUMIF(konwertery!A$2:A$300,A77,Histmag!C$2:C$300) -> 5 | I77: =SUMIF(konwertery!A$2:A$300,A77,konwertery!B$2:B$300) * 0.97 -> 55.0475 | K77: =N77+Q77+T77+W77+Z77+AC77+AF77+AI77+AL77+AO77+AR77+AU77 -> 65 | L77: =O77+R77+U77+X77+AA77+AD77+AG77+AJ77+AM77+AP77+AS77+AV77 -> 414.9 | N77: =SUMIF(konwertery!C$2:C$300,A77,Virtualo!L$2:L$300) -> 1 | O77: =(SUMIF(konwertery!C$2:C$300,A77,Virtualo!P$2:P$300)) -> 11.08 | Q77: =SUMIF(konwertery!D$2:D$300,A77,Empik!M$2:M$300) -> 0 | R77: =SUMIF(konwertery!D$2:D$300,A77,Empik!N$2:N$300) -> 0 | T77: =SUMIF(konwertery!E$2:E$300,A77,Publio!P$2:P$300) -> 1 | U77: =SUMIF(konwertery!E$2:E$300,A77,konwertery!F$2:F$300) -> 8.69 | W77: =SUMIF(Legimi!D$2:D$300,A77,Legimi!G$2:G$300) -> 0 | X77: =SUMIF(Legimi!D$2:D$300,A77,Legimi!H$2:H$300) -> 0 | Z77: =SUMIF(konwertery!G$2:G$302,A77,Nexto!J$2:J$283) -> 0 | AA77: =SUMIF(konwertery!G$2:G$302,A77,Nexto!N$2:P$302) -> 0 | AC77: =SUMIF(Woblink!E$9:E$309,A77,Woblink!I$9:I$309) -> 0 | AD77: =SUMIF(Woblink!E$14:E$314,A77,konwertery!R$2:R$300) -> 0 | AF77: =SUM(SUMIF(konwertery!I$2:I$300,A77,Azymut!H$2:H$298),(SUMIF(konwertery!S$2:S$300,A77,AzymutB!H$2:H367)*2)) -> 0 | AG77: =SUM(SUMIF(konwertery!I$2:I$300,A77,konwertery!J$2:J$300),SUMIF(konwertery!S$2:S$300,A77,konwertery!T$2:T$300)) -> 0 | AI77: =SUMIF(konwertery!K$2:K$300,A77,Ebookpoint!F$14:F$312) -> 63 | AJ77: =SUMIF(konwertery!K$2:K$300,A77,Ebookpoint!M$14:M$312) -> 395.13 | AL77: =SUMIF(konwertery!L$2:L$300,A77,Nasbi!F$14:F$312) -> 0 | AM77: =SUMIF(konwertery!L$2:L$300,A77,Nasbi!K$14:K$312) -> 0 | AO77: =SUMIF(StorytelE!C$2:C$300,A77,konwertery!M$2:M$300)+SUMIF(StorytelA!C$2:C$300,A77,konwertery!N$2:N$300) -> 0 | AP77: =SUMIF(StorytelE!C$2:C$300,A77,konwertery!O$2:O$300)+SUMIF(StorytelA!C$2:C$300,A77,konwertery!P$2:P$300) -> 0 | AR77: =SUMIF(konwertery!U$2:U$300,A77,Audioteka!E$4:E$302) -> 0 | AS77: =SUMIF(konwertery!U$2:U$300,A77,Audioteka!O$4:O$302) -> 0 | AU77: =SUMIF(Bookbeat!A$9:A$309,A77,Bookbeat!H$9:H$309) -> 0 | AV77: =SUMIF(Bookbeat!A$9:A$309,A77,Bookbeat!L$9:L$309) -> 0
A78: 9788365156648 | B78: Trylogia Sienkiewicza, Historia prawdziwa (audio) | E78: =H78+K78 -> 25 | F78: =I78+L78 -> 100.4543 | H78: =SUMIF(konwertery!A$2:A$300,A78,Histmag!C$2:C$300) -> 1 | I78: =SUMIF(konwertery!A$2:A$300,A78,konwertery!B$2:B$300) * 0.97 -> 13.7643 | K78: =N78+Q78+T78+W78+Z78+AC78+AF78+AI78+AL78+AO78+AR78+AU78 -> 24 | L78: =O78+R78+U78+X78+AA78+AD78+AG78+AJ78+AM78+AP78+AS78+AV78 -> 86.69 | N78: =SUMIF(konwertery!C$2:C$300,A78,Virtualo!L$2:L$300) -> 0 | O78: =(SUMIF(konwertery!C$2:C$300,A78,Virtualo!P$2:P$300)) -> 0 | Q78: =SUMIF(konwertery!D$2:D$300,A78,Empik!M$2:M$300) -> 2 | R78: =SUMIF(konwertery!D$2:D$300,A78,Empik!N$2:N$300) -> 14 | T78: =SUMIF(konwertery!E$2:E$300,A78,Publio!P$2:P$300) -> 0 | U78: =SUMIF(konwertery!E$2:E$300,A78,konwertery!F$2:F$300) -> 0 | W78: =SUMIF(Legimi!D$2:D$300,A78,Legimi!G$2:G$300) -> 0 | X78: =SUMIF(Legimi!D$2:D$300,A78,Legimi!H$2:H$300) -> 0 | Z78: =SUMIF(konwertery!G$2:G$302,A78,Nexto!J$2:J$283) -> 0 | AA78: =SUMIF(konwertery!G$2:G$302,A78,Nexto!N$2:P$302) -> 0 | AC78: =SUMIF(Woblink!E$9:E$309,A78,Woblink!I$9:I$309) -> 0 | AD78: =SUMIF(Woblink!E$14:E$314,A78,konwertery!R$2:R$300) -> 0 | AF78: =SUM(SUMIF(konwertery!I$2:I$300,A78,Azymut!H$2:H$298),(SUMIF(konwertery!S$2:S$300,A78,AzymutB!H$2:H368)*2)) -> 0 | AG78: =SUM(SUMIF(konwertery!I$2:I$300,A78,konwertery!J$2:J$300),SUMIF(konwertery!S$2:S$300,A78,konwertery!T$2:T$300)) -> 0 | AI78: =SUMIF(konwertery!K$2:K$300,A78,Ebookpoint!F$14:F$312) -> 4 | AJ78: =SUMIF(konwertery!K$2:K$300,A78,Ebookpoint!M$14:M$312) -> 43.64 | AL78: =SUMIF(konwertery!L$2:L$300,A78,Nasbi!F$14:F$312) -> 0 | AM78: =SUMIF(konwertery!L$2:L$300,A78,Nasbi!K$14:K$312) -> 0 | AO78: =SUMIF(StorytelE!C$2:C$300,A78,konwertery!M$2:M$300)+SUMIF(StorytelA!C$2:C$300,A78,konwertery!N$2:N$300) -> 18 | AP78: =SUMIF(StorytelE!C$2:C$300,A78,konwertery!O$2:O$300)+SUMIF(StorytelA!C$2:C$300,A78,konwertery!P$2:P$300) -> 29.05 | AR78: =SUMIF(konwertery!U$2:U$300,A78,Audioteka!E$4:E$302) -> 0 | AS78: =SUMIF(konwertery!U$2:U$300,A78,Audioteka!O$4:O$302) -> 0 | AU78: =SUMIF(Bookbeat!A$9:A$309,A78,Bookbeat!H$9:H$309) -> 0 | AV78: =SUMIF(Bookbeat!A$9:A$309,A78,Bookbeat!L$9:L$309) -> 0
A79: 9788365156433 | B79: Tudorowie. Od Henryka VIII do Elżbiety Wielkiej | E79: =H79+K79 -> 4 | F79: =I79+L79 -> 32.1102 | H79: =SUMIF(konwertery!A$2:A$300,A79,Histmag!C$2:C$300) -> 2 | I79: =SUMIF(konwertery!A$2:A$300,A79,konwertery!B$2:B$300) * 0.97 -> 21.9802 | K79: =N79+Q79+T79+W79+Z79+AC79+AF79+AI79+AL79+AO79+AR79+AU79 -> 2 | L79: =O79+R79+U79+X79+AA79+AD79+AG79+AJ79+AM79+AP79+AS79+AV79 -> 10.13 | N79: =SUMIF(konwertery!C$2:C$300,A79,Virtualo!L$2:L$300) -> 0 | O79: =(SUMIF(konwertery!C$2:C$300,A79,Virtualo!P$2:P$300)) -> 0 | Q79: =SUMIF(konwertery!D$2:D$300,A79,Empik!M$2:M$300) -> 0 | R79: =SUMIF(konwertery!D$2:D$300,A79,Empik!N$2:N$300) -> 0 | T79: =SUMIF(konwertery!E$2:E$300,A79,Publio!P$2:P$300) -> 0 | U79: =SUMIF(konwertery!E$2:E$300,A79,konwertery!F$2:F$300) -> 0 | W79: =SUMIF(Legimi!D$2:D$300,A79,Legimi!G$2:G$300) -> 0 | X79: =SUMIF(Legimi!D$2:D$300,A79,Legimi!H$2:H$300) -> 0 | Z79: =SUMIF(konwertery!G$2:G$302,A79,Nexto!J$2:J$283) -> 0 | AA79: =SUMIF(konwertery!G$2:G$302,A79,Nexto!N$2:P$302) -> 0 | AC79: =SUMIF(Woblink!E$9:E$309,A79,Woblink!I$9:I$309) -> 1 | AD79: =SUMIF(Woblink!E$14:E$314,A79,konwertery!R$2:R$300) -> 8.51 | AF79: =SUM(SUMIF(konwertery!I$2:I$300,A79,Azymut!H$2:H$298),(SUMIF(konwertery!S$2:S$300,A79,AzymutB!H$2:H369)*2)) -> 0 | AG79: =SUM(SUMIF(konwertery!I$2:I$300,A79,konwertery!J$2:J$300),SUMIF(konwertery!S$2:S$300,A79,konwertery!T$2:T$300)) -> 0 | AI79: =SUMIF(konwertery!K$2:K$300,A79,Ebookpoint!F$14:F$312) -> 0 | AJ79: =SUMIF(konwertery!K$2:K$300,A79,Ebookpoint!M$14:M$312) -> 0 | AL79: =SUMIF(konwertery!L$2:L$300,A79,Nasbi!F$14:F$312) -> 0 | AM79: =SUMIF(konwertery!L$2:L$300,A79,Nasbi!K$14:K$312) -> 0 | AO79: =SUMIF(StorytelE!C$2:C$300,A79,konwertery!M$2:M$300)+SUMIF(StorytelA!C$2:C$300,A79,konwertery!N$2:N$300) -> 1 | AP79: =SUMIF(StorytelE!C$2:C$300,A79,konwertery!O$2:O$300)+SUMIF(StorytelA!C$2:C$300,A79,konwertery!P$2:P$300) -> 1.62 | AR79: =SUMIF(konwertery!U$2:U$300,A79,Audioteka!E$4:E$302) -> 0 | AS79: =SUMIF(konwertery!U$2:U$300,A79,Audioteka!O$4:O$302) -> 0 | AU79: =SUMIF(Bookbeat!A$9:A$309,A79,Bookbeat!H$9:H$309) -> 0 | AV79: =SUMIF(Bookbeat!A$9:A$309,A79,Bookbeat!L$9:L$309) -> 0
A80: 9788365156785 | B80: Tudorowie. Od Henryka VIII do Elżbiety Wielkiej (audio) | E80: =H80+K80 -> 63 | F80: =I80+L80 -> 176.54 | H80: =SUMIF(konwertery!A$2:A$300,A80,Histmag!C$2:C$300) -> 0 | I80: =SUMIF(konwertery!A$2:A$300,A80,konwertery!B$2:B$300) * 0.97 -> 0 | K80: =N80+Q80+T80+W80+Z80+AC80+AF80+AI80+AL80+AO80+AR80+AU80 -> 63 | L80: =O80+R80+U80+X80+AA80+AD80+AG80+AJ80+AM80+AP80+AS80+AV80 -> 176.54 | N80: =SUMIF(konwertery!C$2:C$300,A80,Virtualo!L$2:L$300) -> 0 | O80: =(SUMIF(konwertery!C$2:C$300,A80,Virtualo!P$2:P$300)) -> 0 | Q80: =SUMIF(konwertery!D$2:D$300,A80,Empik!M$2:M$300) -> 6 | R80: =SUMIF(konwertery!D$2:D$300,A80,Empik!N$2:N$300) -> 50 | T80: =SUMIF(konwertery!E$2:E$300,A80,Publio!P$2:P$300) -> 0 | U80: =SUMIF(konwertery!E$2:E$300,A80,konwertery!F$2:F$300) -> 0 | W80: =SUMIF(Legimi!D$2:D$300,A80,Legimi!G$2:G$300) -> 1 | X80: =SUMIF(Legimi!D$2:D$300,A80,Legimi!H$2:H$300) -> 9.93 | Z80: =SUMIF(konwertery!G$2:G$302,A80,Nexto!J$2:J$283) -> 0 | AA80: =SUMIF(konwertery!G$2:G$302,A80,Nexto!N$2:P$302) -> 0 | AC80: =SUMIF(Woblink!E$9:E$309,A80,Woblink!I$9:I$309) -> 2 | AD80: =SUMIF(Woblink!E$14:E$314,A80,konwertery!R$2:R$300) -> 17.02 | AF80: =SUM(SUMIF(konwertery!I$2:I$300,A80,Azymut!H$2:H$298),(SUMIF(konwertery!S$2:S$300,A80,AzymutB!H$2:H370)*2)) -> 0 | AG80: =SUM(SUMIF(konwertery!I$2:I$300,A80,konwertery!J$2:J$300),SUMIF(konwertery!S$2:S$300,A80,konwertery!T$2:T$300)) -> 0 | AI80: =SUMIF(konwertery!K$2:K$300,A80,Ebookpoint!F$14:F$312) -> 1 | AJ80: =SUMIF(konwertery!K$2:K$300,A80,Ebookpoint!M$14:M$312) -> 9.08 | AL80: =SUMIF(konwertery!L$2:L$300,A80,Nasbi!F$14:F$312) -> 0 | AM80: =SUMIF(konwertery!L$2:L$300,A80,Nasbi!K$14:K$312) -> 0 | AO80: =SUMIF(StorytelE!C$2:C$300,A80,konwertery!M$2:M$300)+SUMIF(StorytelA!C$2:C$300,A80,konwertery!N$2:N$300) -> 47 | AP80: =SUMIF(StorytelE!C$2:C$300,A80,konwertery!O$2:O$300)+SUMIF(StorytelA!C$2:C$300,A80,konwertery!P$2:P$300) -> 70.55 | AR80: =SUMIF(konwertery!U$2:U$300,A80,Audioteka!E$4:E$302) -> 1 | AS80: =SUMIF(konwertery!U$2:U$300,A80,Audioteka!O$4:O$302) -> 8.51 | AU80: =SUMIF(Bookbeat!A$9:A$309,A80,Bookbeat!H$9:H$309) -> 5 | AV80: =SUMIF(Bookbeat!A$9:A$309,A80,Bookbeat!L$9:L$309) -> 11.45
A81: 9788393463060 | B81: Warszawa — miasto grzechu: Prostytucja w II RP | E81: =H81+K81 -> 7 | F81: =I81+L81 -> 51.541 | H81: =SUMIF(konwertery!A$2:A$300,A81,Histmag!C$2:C$300) -> 2 | I81: =SUMIF(konwertery!A$2:A$300,A81,konwertery!B$2:B$300) * 0.97 -> 14.841 | K81: =N81+Q81+T81+W81+Z81+AC81+AF81+AI81+AL81+AO81+AR81+AU81 -> 5 | L81: =O81+R81+U81+X81+AA81+AD81+AG81+AJ81+AM81+AP81+AS81+AV81 -> 36.7 | N81: =SUMIF(konwertery!C$2:C$300,A81,Virtualo!L$2:L$300) -> 0 | O81: =(SUMIF(konwertery!C$2:C$300,A81,Virtualo!P$2:P$300)) -> 0 | Q81: =SUMIF(konwertery!D$2:D$300,A81,Empik!M$2:M$300) -> 0 | R81: =SUMIF(konwertery!D$2:D$300,A81,Empik!N$2:N$300) -> 0 | T81: =SUMIF(konwertery!E$2:E$300,A81,Publio!P$2:P$300) -> 0 | U81: =SUMIF(konwertery!E$2:E$300,A81,konwertery!F$2:F$300) -> 0 | W81: =SUMIF(Legimi!D$2:D$300,A81,Legimi!G$2:G$300) -> 2 | X81: =SUMIF(Legimi!D$2:D$300,A81,Legimi!H$2:H$300) -> 19.86 | Z81: =SUMIF(konwertery!G$2:G$302,A81,Nexto!J$2:J$283) -> 0 | AA81: =SUMIF(konwertery!G$2:G$302,A81,Nexto!N$2:P$302) -> 0 | AC81: =SUMIF(Woblink!E$9:E$309,A81,Woblink!I$9:I$309) -> 1 | AD81: =SUMIF(Woblink!E$14:E$314,A81,konwertery!R$2:R$300) -> 6.8 | AF81: =SUM(SUMIF(konwertery!I$2:I$300,A81,Azymut!H$2:H$298),(SUMIF(konwertery!S$2:S$300,A81,AzymutB!H$2:H371)*2)) -> 1 | AG81: =SUM(SUMIF(konwertery!I$2:I$300,A81,konwertery!J$2:J$300),SUMIF(konwertery!S$2:S$300,A81,konwertery!T$2:T$300)) -> 8.51 | AI81: =SUMIF(konwertery!K$2:K$300,A81,Ebookpoint!F$14:F$312) -> 0 | AJ81: =SUMIF(konwertery!K$2:K$300,A81,Ebookpoint!M$14:M$312) -> 0 | AL81: =SUMIF(konwertery!L$2:L$300,A81,Nasbi!F$14:F$312) -> 0 | AM81: =SUMIF(konwertery!L$2:L$300,A81,Nasbi!K$14:K$312) -> 0 | AO81: =SUMIF(StorytelE!C$2:C$300,A81,konwertery!M$2:M$300)+SUMIF(StorytelA!C$2:C$300,A81,konwertery!N$2:N$300) -> 1 | AP81: =SUMIF(StorytelE!C$2:C$300,A81,konwertery!O$2:O$300)+SUMIF(StorytelA!C$2:C$300,A81,konwertery!P$2:P$300) -> 1.53 | AR81: =SUMIF(konwertery!U$2:U$300,A81,Audioteka!E$4:E$302) -> 0 | AS81: =SUMIF(konwertery!U$2:U$300,A81,Audioteka!O$4:O$302) -> 0 | AU81: =SUMIF(Bookbeat!A$9:A$309,A81,Bookbeat!H$9:H$309) -> 0 | AV81: =SUMIF(Bookbeat!A$9:A$309,A81,Bookbeat!L$9:L$309) -> 0
A82: 9788365156136 | B82: Warszawa — miasto grzechu: Prostytucja w II RP (audio) | E82: =H82+K82 -> 36 | F82: =I82+L82 -> 76.65 | H82: =SUMIF(konwertery!A$2:A$300,A82,Histmag!C$2:C$300) -> 0 | I82: =SUMIF(konwertery!A$2:A$300,A82,konwertery!B$2:B$300) * 0.97 -> 0 | K82: =N82+Q82+T82+W82+Z82+AC82+AF82+AI82+AL82+AO82+AR82+AU82 -> 36 | L82: =O82+R82+U82+X82+AA82+AD82+AG82+AJ82+AM82+AP82+AS82+AV82 -> 76.65 | N82: =SUMIF(konwertery!C$2:C$300,A82,Virtualo!L$2:L$300) -> 0 | O82: =(SUMIF(konwertery!C$2:C$300,A82,Virtualo!P$2:P$300)) -> 0 | Q82: =SUMIF(konwertery!D$2:D$300,A82,Empik!M$2:M$300) -> 0 | R82: =SUMIF(konwertery!D$2:D$300,A82,Empik!N$2:N$300) -> 0 | T82: =SUMIF(konwertery!E$2:E$300,A82,Publio!P$2:P$300) -> 2 | U82: =SUMIF(konwertery!E$2:E$300,A82,konwertery!F$2:F$300) -> 17.02 | W82: =SUMIF(Legimi!D$2:D$300,A82,Legimi!G$2:G$300) -> 0 | X82: =SUMIF(Legimi!D$2:D$300,A82,Legimi!H$2:H$300) -> 0 | Z82: =SUMIF(konwertery!G$2:G$302,A82,Nexto!J$2:J$283) -> 0 | AA82: =SUMIF(konwertery!G$2:G$302,A82,Nexto!N$2:P$302) -> 0 | AC82: =SUMIF(Woblink!E$9:E$309,A82,Woblink!I$9:I$309) -> 1 | AD82: =SUMIF(Woblink!E$14:E$314,A82,konwertery!R$2:R$300) -> 8.51 | AF82: =SUM(SUMIF(konwertery!I$2:I$300,A82,Azymut!H$2:H$298),(SUMIF(konwertery!S$2:S$300,A82,AzymutB!H$2:H372)*2)) -> 0 | AG82: =SUM(SUMIF(konwertery!I$2:I$300,A82,konwertery!J$2:J$300),SUMIF(konwertery!S$2:S$300,A82,konwertery!T$2:T$300)) -> 0 | AI82: =SUMIF(konwertery!K$2:K$300,A82,Ebookpoint!F$14:F$312) -> 0 | AJ82: =SUMIF(konwertery!K$2:K$300,A82,Ebookpoint!M$14:M$312) -> 0 | AL82: =SUMIF(konwertery!L$2:L$300,A82,Nasbi!F$14:F$312) -> 0 | AM82: =SUMIF(konwertery!L$2:L$300,A82,Nasbi!K$14:K$312) -> 0 | AO82: =SUMIF(StorytelE!C$2:C$300,A82,konwertery!M$2:M$300)+SUMIF(StorytelA!C$2:C$300,A82,konwertery!N$2:N$300) -> 30 | AP82: =SUMIF(StorytelE!C$2:C$300,A82,konwertery!O$2:O$300)+SUMIF(StorytelA!C$2:C$300,A82,konwertery!P$2:P$300) -> 38.78 | AR82: =SUMIF(konwertery!U$2:U$300,A82,Audioteka!E$4:E$302) -> 1 | AS82: =SUMIF(konwertery!U$2:U$300,A82,Audioteka!O$4:O$302) -> 8.51 | AU82: =SUMIF(Bookbeat!A$9:A$309,A82,Bookbeat!H$9:H$309) -> 2 | AV82: =SUMIF(Bookbeat!A$9:A$309,A82,Bookbeat!L$9:L$309) -> 3.83
A83: 9788365156099 | B83: Wielcy polskiego średniowiecza | E83: =H83+K83 -> 4 | F83: =I83+L83 -> 20.8479 | H83: =SUMIF(konwertery!A$2:A$300,A83,Histmag!C$2:C$300) -> 3 | I83: =SUMIF(konwertery!A$2:A$300,A83,konwertery!B$2:B$300) * 0.97 -> 14.6179 | K83: =N83+Q83+T83+W83+Z83+AC83+AF83+AI83+AL83+AO83+AR83+AU83 -> 1 | L83: =O83+R83+U83+X83+AA83+AD83+AG83+AJ83+AM83+AP83+AS83+AV83 -> 6.23 | N83: =SUMIF(konwertery!C$2:C$300,A83,Virtualo!L$2:L$300) -> 0 | O83: =(SUMIF(konwertery!C$2:C$300,A83,Virtualo!P$2:P$300)) -> 0 | Q83: =SUMIF(konwertery!D$2:D$300,A83,Empik!M$2:M$300) -> 0 | R83: =SUMIF(konwertery!D$2:D$300,A83,Empik!N$2:N$300) -> 0 | T83: =SUMIF(konwertery!E$2:E$300,A83,Publio!P$2:P$300) -> 0 | U83: =SUMIF(konwertery!E$2:E$300,A83,konwertery!F$2:F$300) -> 0 | W83: =SUMIF(Legimi!D$2:D$300,A83,Legimi!G$2:G$300) -> 0 | X83: =SUMIF(Legimi!D$2:D$300,A83,Legimi!H$2:H$300) -> 0 | Z83: =SUMIF(konwertery!G$2:G$302,A83,Nexto!J$2:J$283) -> 0 | AA83: =SUMIF(konwertery!G$2:G$302,A83,Nexto!N$2:P$302) -> 0 | AC83: =SUMIF(Woblink!E$9:E$309,A83,Woblink!I$9:I$309) -> 1 | AD83: =SUMIF(Woblink!E$14:E$314,A83,konwertery!R$2:R$300) -> 6.23 | AF83: =SUM(SUMIF(konwertery!I$2:I$300,A83,Azymut!H$2:H$298),(SUMIF(konwertery!S$2:S$300,A83,AzymutB!H$2:H373)*2)) -> 0 | AG83: =SUM(SUMIF(konwertery!I$2:I$300,A83,konwertery!J$2:J$300),SUMIF(konwertery!S$2:S$300,A83,konwertery!T$2:T$300)) -> 0 | AI83: =SUMIF(konwertery!K$2:K$300,A83,Ebookpoint!F$14:F$312) -> 0 | AJ83: =SUMIF(konwertery!K$2:K$300,A83,Ebookpoint!M$14:M$312) -> 0 | AL83: =SUMIF(konwertery!L$2:L$300,A83,Nasbi!F$14:F$312) -> 0 | AM83: =SUMIF(konwertery!L$2:L$300,A83,Nasbi!K$14:K$312) -> 0 | AO83: =SUMIF(StorytelE!C$2:C$300,A83,konwertery!M$2:M$300)+SUMIF(StorytelA!C$2:C$300,A83,konwertery!N$2:N$300) -> 0 | AP83: =SUMIF(StorytelE!C$2:C$300,A83,konwertery!O$2:O$300)+SUMIF(StorytelA!C$2:C$300,A83,konwertery!P$2:P$300) -> 0 | AR83: =SUMIF(konwertery!U$2:U$300,A83,Audioteka!E$4:E$302) -> 0 | AS83: =SUMIF(konwertery!U$2:U$300,A83,Audioteka!O$4:O$302) -> 0 | AU83: =SUMIF(Bookbeat!A$9:A$309,A83,Bookbeat!H$9:H$309) -> 0 | AV83: =SUMIF(Bookbeat!A$9:A$309,A83,Bookbeat!L$9:L$309) -> 0
A84: 9788393463008 | B84: Wielcy zapomniani Dwudziestolecia | E84: =H84+K84 -> 4 | F84: =I84+L84 -> 17.9818 | H84: =SUMIF(konwertery!A$2:A$300,A84,Histmag!C$2:C$300) -> 3 | I84: =SUMIF(konwertery!A$2:A$300,A84,konwertery!B$2:B$300) * 0.97 -> 12.5518 | K84: =N84+Q84+T84+W84+Z84+AC84+AF84+AI84+AL84+AO84+AR84+AU84 -> 1 | L84: =O84+R84+U84+X84+AA84+AD84+AG84+AJ84+AM84+AP84+AS84+AV84 -> 5.43 | N84: =SUMIF(konwertery!C$2:C$300,A84,Virtualo!L$2:L$300) -> 0 | O84: =(SUMIF(konwertery!C$2:C$300,A84,Virtualo!P$2:P$300)) -> 0 | Q84: =SUMIF(konwertery!D$2:D$300,A84,Empik!M$2:M$300) -> 0 | R84: =SUMIF(konwertery!D$2:D$300,A84,Empik!N$2:N$300) -> 0 | T84: =SUMIF(konwertery!E$2:E$300,A84,Publio!P$2:P$300) -> 0 | U84: =SUMIF(konwertery!E$2:E$300,A84,konwertery!F$2:F$300) -> 0 | W84: =SUMIF(Legimi!D$2:D$300,A84,Legimi!G$2:G$300) -> 0 | X84: =SUMIF(Legimi!D$2:D$300,A84,Legimi!H$2:H$300) -> 0 | Z84: =SUMIF(konwertery!G$2:G$302,A84,Nexto!J$2:J$283) -> 0 | AA84: =SUMIF(konwertery!G$2:G$302,A84,Nexto!N$2:P$302) -> 0 | AC84: =SUMIF(Woblink!E$9:E$309,A84,Woblink!I$9:I$309) -> 0 | AD84: =SUMIF(Woblink!E$14:E$314,A84,konwertery!R$2:R$300) -> 0 | AF84: =SUM(SUMIF(konwertery!I$2:I$300,A84,Azymut!H$2:H$298),(SUMIF(konwertery!S$2:S$300,A84,AzymutB!H$2:H374)*2)) -> 0 | AG84: =SUM(SUMIF(konwertery!I$2:I$300,A84,konwertery!J$2:J$300),SUMIF(konwertery!S$2:S$300,A84,konwertery!T$2:T$300)) -> 0 | AI84: =SUMIF(konwertery!K$2:K$300,A84,Ebookpoint!F$14:F$312) -> 1 | AJ84: =SUMIF(konwertery!K$2:K$300,A84,Ebookpoint!M$14:M$312) -> 5.43 | AL84: =SUMIF(konwertery!L$2:L$300,A84,Nasbi!F$14:F$312) -> 0 | AM84: =SUMIF(konwertery!L$2:L$300,A84,Nasbi!K$14:K$312) -> 0 | AO84: =SUMIF(StorytelE!C$2:C$300,A84,konwertery!M$2:M$300)+SUMIF(StorytelA!C$2:C$300,A84,konwertery!N$2:N$300) -> 0 | AP84: =SUMIF(StorytelE!C$2:C$300,A84,konwertery!O$2:O$300)+SUMIF(StorytelA!C$2:C$300,A84,konwertery!P$2:P$300) -> 0 | AR84: =SUMIF(konwertery!U$2:U$300,A84,Audioteka!E$4:E$302) -> 0 | AS84: =SUMIF(konwertery!U$2:U$300,A84,Audioteka!O$4:O$302) -> 0 | AU84: =SUMIF(Bookbeat!A$9:A$309,A84,Bookbeat!H$9:H$309) -> 0 | AV84: =SUMIF(Bookbeat!A$9:A$309,A84,Bookbeat!L$9:L$309) -> 0
A85: 9788393463015 | B85: Wielcy zapomniani Dwudziestolecia, Część 2 | E85: =H85+K85 -> 2 | F85: =I85+L85 -> 7.1004 | H85: =SUMIF(konwertery!A$2:A$300,A85,Histmag!C$2:C$300) -> 2 | I85: =SUMIF(konwertery!A$2:A$300,A85,konwertery!B$2:B$300) * 0.97 -> 7.1004 | K85: =N85+Q85+T85+W85+Z85+AC85+AF85+AI85+AL85+AO85+AR85+AU85 -> 0 | L85: =O85+R85+U85+X85+AA85+AD85+AG85+AJ85+AM85+AP85+AS85+AV85 -> 0 | N85: =SUMIF(konwertery!C$2:C$300,A85,Virtualo!L$2:L$300) -> 0 | O85: =(SUMIF(konwertery!C$2:C$300,A85,Virtualo!P$2:P$300)) -> 0 | Q85: =SUMIF(konwertery!D$2:D$300,A85,Empik!M$2:M$300) -> 0 | R85: =SUMIF(konwertery!D$2:D$300,A85,Empik!N$2:N$300) -> 0 | T85: =SUMIF(konwertery!E$2:E$300,A85,Publio!P$2:P$300) -> 0 | U85: =SUMIF(konwertery!E$2:E$300,A85,konwertery!F$2:F$300) -> 0 | W85: =SUMIF(Legimi!D$2:D$300,A85,Legimi!G$2:G$300) -> 0 | X85: =SUMIF(Legimi!D$2:D$300,A85,Legimi!H$2:H$300) -> 0 | Z85: =SUMIF(konwertery!G$2:G$302,A85,Nexto!J$2:J$283) -> 0 | AA85: =SUMIF(konwertery!G$2:G$302,A85,Nexto!N$2:P$302) -> 0 | AC85: =SUMIF(Woblink!E$9:E$309,A85,Woblink!I$9:I$309) -> 0 | AD85: =SUMIF(Woblink!E$14:E$314,A85,konwertery!R$2:R$300) -> 0 | AF85: =SUM(SUMIF(konwertery!I$2:I$300,A85,Azymut!H$2:H$298),(SUMIF(konwertery!S$2:S$300,A85,AzymutB!H$2:H375)*2)) -> 0 | AG85: =SUM(SUMIF(konwertery!I$2:I$300,A85,konwertery!J$2:J$300),SUMIF(konwertery!S$2:S$300,A85,konwertery!T$2:T$300)) -> 0 | AI85: =SUMIF(konwertery!K$2:K$300,A85,Ebookpoint!F$14:F$312) -> 0 | AJ85: =SUMIF(konwertery!K$2:K$300,A85,Ebookpoint!M$14:M$312) -> 0 | AL85: =SUMIF(konwertery!L$2:L$300,A85,Nasbi!F$14:F$312) -> 0 | AM85: =SUMIF(konwertery!L$2:L$300,A85,Nasbi!K$14:K$312) -> 0 | AO85: =SUMIF(StorytelE!C$2:C$300,A85,konwertery!M$2:M$300)+SUMIF(StorytelA!C$2:C$300,A85,konwertery!N$2:N$300) -> 0 | AP85: =SUMIF(StorytelE!C$2:C$300,A85,konwertery!O$2:O$300)+SUMIF(StorytelA!C$2:C$300,A85,konwertery!P$2:P$300) -> 0 | AR85: =SUMIF(konwertery!U$2:U$300,A85,Audioteka!E$4:E$302) -> 0 | AS85: =SUMIF(konwertery!U$2:U$300,A85,Audioteka!O$4:O$302) -> 0 | AU85: =SUMIF(Bookbeat!A$9:A$309,A85,Bookbeat!H$9:H$309) -> 0 | AV85: =SUMIF(Bookbeat!A$9:A$309,A85,Bookbeat!L$9:L$309) -> 0
... A105: 9788362329991 | B105: Źródła nienawiści, Konflikty etniczne w krajach postkomunistycznych | E105: =H105+K105 -> 2 | F105: =I105+L105 -> 25.7632 | H105: =SUMIF(konwertery!A$2:A$300,A105,Histmag!C$2:C$300) -> 2 | I105: =SUMIF(konwertery!A$2:A$300,A105,konwertery!B$2:B$300) * 0.97 -> 25.7632 | K105: =N105+Q105+T105+W105+Z105+AC105+AF105+AI105+AL105+AO105+AR105+AU105 -> 0 | L105: =O105+R105+U105+X105+AA105+AD105+AG105+AJ105+AM105+AP105+AS105+AV105 -> 0 | N105: =SUMIF(konwertery!C$2:C$300,A105,Virtualo!L$2:L$300) -> 0 | O105: =(SUMIF(konwertery!C$2:C$300,A105,Virtualo!P$2:P$300)) -> 0 | Q105: =SUMIF(konwertery!D$2:D$300,A105,Empik!M$2:M$300) -> 0 | R105: =SUMIF(konwertery!D$2:D$300,A105,Empik!N$2:N$300) -> 0 | T105: =SUMIF(konwertery!E$2:E$300,A105,Publio!P$2:P$300) -> 0 | U105: =SUMIF(konwertery!E$2:E$300,A105,konwertery!F$2:F$300) -> 0 | W105: =SUMIF(Legimi!D$2:D$300,A105,Legimi!G$2:G$300) -> 0 | X105: =SUMIF(Legimi!D$2:D$300,A105,Legimi!H$2:H$300) -> 0 | Z105: =SUMIF(konwertery!G$2:G$302,A105,Nexto!J$2:J$283) -> 0 | AA105: =SUMIF(konwertery!G$2:G$302,A105,Nexto!N$2:P$302) -> 0 | AC105: =SUMIF(Woblink!E$9:E$309,A105,Woblink!I$9:I$309) -> 0 | AD105: =SUMIF(Woblink!E$14:E$314,A105,konwertery!R$2:R$300) -> 0 | AF105: =SUM(SUMIF(konwertery!I$2:I$300,A105,Azymut!H$2:H$298),(SUMIF(konwertery!S$2:S$300,A105,AzymutB!H$2:H395)*2)) -> 0 | AG105: =SUM(SUMIF(konwertery!I$2:I$300,A105,konwertery!J$2:J$300),SUMIF(konwertery!S$2:S$300,A105,konwertery!T$2:T$300)) -> 0 | AI105: =SUMIF(konwertery!K$2:K$300,A105,Ebookpoint!F$14:F$312) -> 0 | AJ105: =SUMIF(konwertery!K$2:K$300,A105,Ebookpoint!M$14:M$312) -> 0 | AL105: =SUMIF(konwertery!L$2:L$300,A105,Nasbi!F$14:F$312) -> 0 | AM105: =SUMIF(konwertery!L$2:L$300,A105,Nasbi!K$14:K$312) -> 0 | AO105: =SUMIF(StorytelE!C$2:C$300,A105,konwertery!M$2:M$300)+SUMIF(StorytelA!C$2:C$300,A105,konwertery!N$2:N$300) -> 0 | AP105: =SUMIF(StorytelE!C$2:C$300,A105,konwertery!O$2:O$300)+SUMIF(StorytelA!C$2:C$300,A105,konwertery!P$2:P$300) -> 0 | AR105: =SUMIF(konwertery!U$2:U$300,A105,Audioteka!E$4:E$302) -> 0 | AS105: =SUMIF(konwertery!U$2:U$300,A105,Audioteka!O$4:O$302) -> 0 | AU105: =SUMIF(Bookbeat!A$9:A$309,A105,Bookbeat!H$9:H$309) -> 0 | AV105: =SUMIF(Bookbeat!A$9:A$309,A105,Bookbeat!L$9:L$309) -> 0
B107: razem: | E107: =SUM(E4:E105) -> 1390 | F107: =SUM(F4:F105) -> 5965.7572 | H107: =SUM(H4:H105) -> 115 | I107: =SUM(I4:I105) -> 1125.9372 | K107: =SUM(K4:K105) -> 1275 | L107: =SUM(L4:L105) -> 4839.82 | N107: =SUM(N4:N105) -> 17 | O107: =SUM(O4:O105) -> 177.76 | Q107: =SUM(Q4:Q105) -> 119 | R107: =SUM(R4:R105) -> 915 | T107: =SUM(T4:T105) -> 19 | U107: =SUM(U4:U105) -> 177.73 | W107: =SUM(W4:W105) -> 16 | X107: =SUM(X4:X105) -> 155.59 | Z107: =SUM(Z4:Z105) -> 4 | AA107: =SUM(AA4:AA105) -> 20.87 | AC107: =SUM(AC4:AC105) -> 14 | AD107: =SUM(AD4:AD105) -> 123.75 | AF107: =SUM(AF4:AF105) -> 4 | AG107: =SUM(AG4:AG105) -> 42.62 | AI107: =SUM(AI4:AI105) -> 195 | AJ107: =SUM(AJ4:AJ105) -> 1356.13 | AL107: =SUM(AL4:AL105) -> 2 | AM107: =SUM(AM4:AM105) -> 23.04 | AO107: =SUM(AO4:AO105) -> 799 | AP107: =SUM(AP4:AP105) -> 1251.79 | AR107: =SUM(AR4:AR105) -> 51 | AS107: =SUM(AS4:AS105) -> 501.39 | AU107: =SUM(AU4:AU105) -> 35 | AV107: =SUM(AV4:AV105) -> 94.15
B108: powinno być: | H108: 39 | I108: 425.32 | K108: =SUM(K4:K106) -> 1275 | L108: =SUM(L4:L105) -> 4839.82 | N108: =SUM(Virtualo!L:L)/2 -> 17 | O108: {=MAX(INDIRECT("Virtualo!P:P"))} -> 177.76 | Q108: {=MAX(INDIRECT("Empik!M:M"))} -> 119 | R108: {=MAX(INDIRECT("Empik!N:N"))} -> 915 | T108: =SUM(Publio!P2:P300) -> 19 | U108: =SUM(konwertery!F2:F301) -> 177.73 | W108: =SUM(Legimi!G:G) -> 16 | X108: {=MAX(INDIRECT("Legimi!H:H"))} -> 155.59 | Z108: =(SUMIF(konwertery!G$2:G$302,"*",Nexto!J$7:J$307)/2) -> 4 | AA108: =SUM(Nexto!N$7:N$283) -> 20.87 | AC108: =SUMIF(Woblink!I$9:I$314,"1") -> 14 | AD108: =SUM(konwertery!R$2:R$300) -> 123.75 | AF108: 0 | AG108: =AG107 -> 42.62 | AI108: {=MAX(INDIRECT("Ebookpoint!F:F"))} -> 195 | AJ108: {=MAX(INDIRECT("Ebookpoint!M:M"))} -> 1356.13 | AL108: {=MAX(INDIRECT("Nasbi!F:F"))} -> 2 | AM108: {=MAX(INDIRECT("Nasbi!K:K"))} -> 23.04 | AO108: =AO107 -> 799 | AP108: =AP107 -> 1251.79 | AR108: {=MAX(INDIRECT("Audioteka!E:E"))} -> 51 | AS108: {=MAX(INDIRECT("Audioteka!O:O"))} -> 501.39 | AU108: =AU107 -> 35 | AV108: =Bookbeat!D5 -> 94.15

Sheet konwertery
A1: Histmag: ISBN bez myślników | B1: Histmag: przychód jako liczba | C1: Virtualo: ISBN bez myślników | D1: Empik: ISBN bez myślników | E1: Publio: ISBN bez myślników | F1: Publio: przychód jako liczba | G1: Nexto: ISBN bez myślników | H1: Nexto: przychód jako liczba | I1: Azymut: ISBN bez myślników | J1: Azymut: przychód jako liczba | K1: Ebookpoint: ISBN | L1: Nasbi: ISBN | M1: Storytel (ebooki): egzemplarze | N1: Storytel (audiobooki): egzemplarze | O1: Storytel (ebooki):egzemplarze | P1: Storytel (audiobooki):egzemplarze | R1: Woblink (dochód z przecinkami) | S1: Azymut Biblio: ISBN bez myślników | T1: Azymut: przychód jako liczba | U1: Audioteka: ISBN bez myślników
A2: =SUBSTITUTE(Histmag!B2,"-","") -> 9788365156860 | B2: =VALUE(SUBSTITUTE(Histmag!D2,".",",")) -> 144.9 | C2: =SUBSTITUTE(Virtualo!G2,"-","") -> 9788365156716 | D2: =SUBSTITUTE(Empik!F2,"-","") -> 9788365156808 | E2: =SUBSTITUTE(Publio!H2,"-","") -> 9788365156556 | F2: =VALUE(SUBSTITUTE(Publio!Q2,".",",")) -> 8.69 | G2: =IFERROR(IF(SEARCH("-", #REF!), SUBSTITUTE(#REF!,"-","")), "") | H2: =IFERROR(VALUE(SUBSTITUTE(#REF!,".",",")),0) -> 0 | I2: =SUBSTITUTE(Azymut!D2,"-","") -> 9788365156624 | J2: =VALUE(SUBSTITUTE(Azymut!O2,".",",")) -> 11.37 | K2: =SUBSTITUTE(Ebookpoint!E14,"-","") -> 9788365156112 | L2: =SUBSTITUTE(Nasbi!E14,"-","") -> 9788365156624 | M2: =VALUE(SUBSTITUTE(StorytelE!G2,".",",")) -> 1 | N2: =VALUE(SUBSTITUTE(StorytelA!G2,".",",")) -> 30 | O2: =VALUE(SUBSTITUTE(StorytelE!M2,".",",")) -> 1.25 | P2: =VALUE(SUBSTITUTE(StorytelA!M2,".",",")) -> 38.78 | R2: =VALUE(SUBSTITUTE(Woblink!H14,".",",")) -> 11.37 | S2: =SUBSTITUTE(AzymutB!D2,"-","") | T2: =VALUE(SUBSTITUTE(AzymutB!O2,".",",")) -> 0 | U2: =SUBSTITUTE(Audioteka!Q4,"-","") -> 9788365156716
A3: =SUBSTITUTE(Histmag!B3,"-","") -> 9788365156822 | B3: =VALUE(SUBSTITUTE(Histmag!D3,".",",")) -> 90.97 | C3: =SUBSTITUTE(Virtualo!G3,"-","") -> 9788365156372 | D3: =SUBSTITUTE(Empik!F3,"-","") -> 9788365156532 | E3: =SUBSTITUTE(Publio!H3,"-","") -> 9788365156372 | F3: =VALUE(SUBSTITUTE(Publio!Q3,".",",")) -> 10.23 | G3: =IFERROR(IF(SEARCH("-", #REF!), SUBSTITUTE(#REF!,"-","")), "") | H3: =IFERROR(VALUE(SUBSTITUTE(Nexto!P7,".",",")),0) -> 0 | I3: =SUBSTITUTE(Azymut!D3,"-","") -> 9788365156563 | J3: =VALUE(SUBSTITUTE(Azymut!O3,".",",")) -> 11.37 | K3: =SUBSTITUTE(Ebookpoint!E15,"-","") -> 9788365156129 | L3: =SUBSTITUTE(Nasbi!E15,"-","") -> 9788365156792 | M3: =VALUE(SUBSTITUTE(StorytelE!G3,".",",")) -> 2 | N3: =VALUE(SUBSTITUTE(StorytelA!G3,".",",")) -> 16 | O3: =VALUE(SUBSTITUTE(StorytelE!M3,".",",")) -> 3.12 | P3: =VALUE(SUBSTITUTE(StorytelA!M3,".",",")) -> 15.89 | R3: =VALUE(SUBSTITUTE(Woblink!H15,".",",")) -> 10.23 | S3: =SUBSTITUTE(AzymutB!D3,"-","") | T3: =VALUE(SUBSTITUTE(AzymutB!O3,".",",")) -> 0 | U3: =SUBSTITUTE(Audioteka!Q5,"-","") -> 9788365156723
A4: =SUBSTITUTE(Histmag!B4,"-","") -> 9788365156556 | B4: =VALUE(SUBSTITUTE(Histmag!D4,".",",")) -> 56.75 | C4: =SUBSTITUTE(Virtualo!G4,"-","") -> 9788365156655 | D4: =SUBSTITUTE(Empik!F4,"-","") -> 9788365156532 | E4: =SUBSTITUTE(Publio!H4,"-","") -> 9788393463053 | F4: =VALUE(SUBSTITUTE(Publio!Q4,".",",")) -> 6.23 | G4: =IFERROR(IF(SEARCH("-", #REF!), SUBSTITUTE(#REF!,"-","")), "") | H4: =IFERROR(VALUE(SUBSTITUTE(Nexto!P8,".",",")),0) -> 0 | I4: =SUBSTITUTE(Azymut!D4,"-","") -> 9788365156860 | J4: =VALUE(SUBSTITUTE(Azymut!O4,".",",")) -> 11.37 | K4: =SUBSTITUTE(Ebookpoint!E16,"-","") -> 9788365156143 | L4: =SUBSTITUTE(Nasbi!E16,"-","") | M4: =VALUE(SUBSTITUTE(StorytelE!G4,".",",")) -> 1 | N4: =VALUE(SUBSTITUTE(StorytelA!G4,".",",")) -> 13 | O4: =VALUE(SUBSTITUTE(StorytelE!M4,".",",")) -> 1.71 | P4: =VALUE(SUBSTITUTE(StorytelA!M4,".",",")) -> 15.94 | R4: =VALUE(SUBSTITUTE(Woblink!H16,".",",")) -> 11.37 | S4: =SUBSTITUTE(AzymutB!D4,"-","") | T4: =VALUE(SUBSTITUTE(AzymutB!O4,".",",")) -> 0 | U4: =SUBSTITUTE(Audioteka!Q6,"-","") -> 9788365156846
A5: =SUBSTITUTE(Histmag!B5,"-","") -> 9788365156853 | B5: =VALUE(SUBSTITUTE(Histmag!D5,".",",")) -> 74.86 | C5: =SUBSTITUTE(Virtualo!G5,"-","") -> 9788365156426 | D5: =SUBSTITUTE(Empik!F5,"-","") -> 9788365156761 | E5: =SUBSTITUTE(Publio!H5,"-","") -> 9788365156822 | F5: =VALUE(SUBSTITUTE(Publio!Q5,".",",")) -> 9.66 | G5: =IFERROR(IF(SEARCH("-", #REF!), SUBSTITUTE(#REF!,"-","")), "") | H5: =IFERROR(VALUE(SUBSTITUTE(Nexto!P9,".",",")),0) -> 0 | I5: =SUBSTITUTE(Azymut!D5,"-","") -> 9788393463060 | J5: =VALUE(SUBSTITUTE(Azymut!O5,".",",")) -> 8.51 | K5: =SUBSTITUTE(Ebookpoint!E17,"-","") -> 9788365156150 | L5: =SUBSTITUTE(Nasbi!E17,"-","") | M5: =VALUE(SUBSTITUTE(StorytelE!G5,".",",")) -> 1 | N5: =VALUE(SUBSTITUTE(StorytelA!G5,".",",")) -> 17 | O5: =VALUE(SUBSTITUTE(StorytelE!M5,".",",")) -> 1.53 | P5: =VALUE(SUBSTITUTE(StorytelA!M5,".",",")) -> 20.83 | R5: =VALUE(SUBSTITUTE(Woblink!H17,".",",")) -> 8.51 | S5: =SUBSTITUTE(AzymutB!D5,"-","") | T5: =VALUE(SUBSTITUTE(AzymutB!O5,".",",")) -> 0 | U5: =SUBSTITUTE(Audioteka!Q7,"-","") -> 9788365156785
A6: =SUBSTITUTE(Histmag!B6,"-","") -> 9788365156815 | B6: =VALUE(SUBSTITUTE(Histmag!D6,".",",")) -> 56.84 | C6: =SUBSTITUTE(Virtualo!G6,"-","") -> 9788365156495 | D6: =SUBSTITUTE(Empik!F6,"-","") -> 9788365156464 | E6: =SUBSTITUTE(Publio!H6,"-","") -> 9788365156419 | F6: =VALUE(SUBSTITUTE(Publio!Q6,".",",")) -> 7.24 | G6: =IFERROR(IF(SEARCH("-", #REF!), SUBSTITUTE(#REF!,"-","")), "") | H6: =IFERROR(VALUE(SUBSTITUTE(Nexto!P10,".",",")),0) -> 0 | I6: =SUBSTITUTE(Azymut!D6,"-","") | J6: =VALUE(SUBSTITUTE(Azymut!O6,".",",")) -> 0 | K6: =SUBSTITUTE(Ebookpoint!E18,"-","") -> 9788393463008 | L6: =SUBSTITUTE(Nasbi!E18,"-","") | M6: =VALUE(SUBSTITUTE(StorytelE!G6,".",",")) -> 1 | N6: =VALUE(SUBSTITUTE(StorytelA!G6,".",",")) -> 35 | O6: =VALUE(SUBSTITUTE(StorytelE!M6,".",",")) -> 1.37 | P6: =VALUE(SUBSTITUTE(StorytelA!M6,".",",")) -> 35.56 | R6: =VALUE(SUBSTITUTE(Woblink!H18,".",",")) -> 6.8 | S6: =SUBSTITUTE(AzymutB!D6,"-","") | T6: =VALUE(SUBSTITUTE(AzymutB!O6,".",",")) -> 0 | U6: =SUBSTITUTE(Audioteka!Q8,"-","") -> 9788365156457
A7: =SUBSTITUTE(Histmag!B7,"-","") -> 9788393463046 | B7: =VALUE(SUBSTITUTE(Histmag!D7,".",",")) -> 17.69 | C7: =SUBSTITUTE(Virtualo!G7,"-","") -> 9788365156532 | D7: =SUBSTITUTE(Empik!F7,"-","") -> 9788365156716 | E7: =SUBSTITUTE(Publio!H7,"-","") -> 9788365156822 | F7: =VALUE(SUBSTITUTE(Publio!Q7,".",",")) -> 9.66 | G7: =IFERROR(IF(SEARCH("-", Nexto!B7), SUBSTITUTE(Nexto!B7,"-","")), "") | H7: =IFERROR(VALUE(SUBSTITUTE(Nexto!P11,".",",")),0) -> 9.22 | I7: =SUBSTITUTE(Azymut!D7,"-","") | J7: =VALUE(SUBSTITUTE(Azymut!O7,".",",")) -> 0 | K7: =SUBSTITUTE(Ebookpoint!E19,"-","") -> 9788365156013 | L7: =SUBSTITUTE(Nasbi!E19,"-","") | M7: =VALUE(SUBSTITUTE(StorytelE!G7,".",",")) -> 2 | N7: =VALUE(SUBSTITUTE(StorytelA!G7,".",",")) -> 5 | O7: =VALUE(SUBSTITUTE(StorytelE!M7,".",",")) -> 3.09 | P7: =VALUE(SUBSTITUTE(StorytelA!M7,".",",")) -> 13.35 | R7: =VALUE(SUBSTITUTE(Woblink!H19,".",",")) -> 11.37 | S7: =SUBSTITUTE(AzymutB!D7,"-","") | T7: =VALUE(SUBSTITUTE(AzymutB!O7,".",",")) -> 0 | U7: =SUBSTITUTE(Audioteka!Q9,"-","") -> 9788365156792
A8: =SUBSTITUTE(Histmag!B8,"-","") -> 9788393463008 | B8: =VALUE(SUBSTITUTE(Histmag!D8,".",",")) -> 12.94 | C8: =SUBSTITUTE(Virtualo!G8,"-","") -> 9788365156860 | D8: =SUBSTITUTE(Empik!F8,"-","") -> 9788365156716 | E8: =SUBSTITUTE(Publio!H8,"-","") -> 9788365156853 | F8: =VALUE(SUBSTITUTE(Publio!Q8,".",",")) -> 11.37 | G8: =IFERROR(IF(SEARCH("-", Nexto!B8), SUBSTITUTE(Nexto!B8,"-","")), "") | H8: =IFERROR(VALUE(SUBSTITUTE(Nexto!P12,".",",")),0) -> 12.32 | I8: =SUBSTITUTE(Azymut!D8,"-","") | J8: =VALUE(SUBSTITUTE(Azymut!O8,".",",")) -> 0 | K8: =SUBSTITUTE(Ebookpoint!E20,"-","") -> 9788365156235 | L8: =SUBSTITUTE(Nasbi!E20,"-","") | M8: =VALUE(SUBSTITUTE(StorytelE!G8,".",",")) -> 1 | N8: =VALUE(SUBSTITUTE(StorytelA!G8,".",",")) -> 20 | O8: =VALUE(SUBSTITUTE(StorytelE!M8,".",",")) -> 2.07 | P8: =VALUE(SUBSTITUTE(StorytelA!M8,".",",")) -> 46.83 | R8: =VALUE(SUBSTITUTE(Woblink!H20,".",",")) -> 8.51 | S8: =SUBSTITUTE(AzymutB!D8,"-","") | T8: =VALUE(SUBSTITUTE(AzymutB!O8,".",",")) -> 0 | U8: =SUBSTITUTE(Audioteka!Q10,"-","") -> 9788365156761
A9: =SUBSTITUTE(Histmag!B9,"-","") -> 9788393463077 | B9: =VALUE(SUBSTITUTE(Histmag!D9,".",",")) -> 22.16 | C9: =SUBSTITUTE(Virtualo!G9,"-","") -> 9788365156556 | D9: =SUBSTITUTE(Empik!F9,"-","") -> 9788365156457 | E9: =SUBSTITUTE(Publio!H9,"-","") -> 9788365156419 | F9: =VALUE(SUBSTITUTE(Publio!Q9,".",",")) -> 7.24 | G9: =IFERROR(IF(SEARCH("-", Nexto!B9), SUBSTITUTE(Nexto!B9,"-","")), "") | H9: =IFERROR(VALUE(SUBSTITUTE(Nexto!P13,".",",")),0) -> 7.99 | I9: =SUBSTITUTE(Azymut!D9,"-","") | J9: =VALUE(SUBSTITUTE(Azymut!O9,".",",")) -> 0 | K9: =SUBSTITUTE(Ebookpoint!E21,"-","") -> 9788365156372 | L9: =SUBSTITUTE(Nasbi!E21,"-","") | M9: =VALUE(SUBSTITUTE(StorytelE!G9,".",",")) -> 1 | N9: =VALUE(SUBSTITUTE(StorytelA!G9,".",",")) -> 2 | O9: =VALUE(SUBSTITUTE(StorytelE!M9,".",",")) -> 1.95 | P9: =VALUE(SUBSTITUTE(StorytelA!M9,".",",")) -> 4.06 | R9: =VALUE(SUBSTITUTE(Woblink!H21,".",",")) -> 6.23 | S9: =SUBSTITUTE(AzymutB!D9,"-","") | T9: =VALUE(SUBSTITUTE(AzymutB!O9,".",",")) -> 0 | U9: =SUBSTITUTE(Audioteka!Q11,"-","") -> 9788365156334
A10: =SUBSTITUTE(Histmag!B10,"-","") -> 9788365156099 | B10: =VALUE(SUBSTITUTE(Histmag!D10,".",",")) -> 15.07 | C10: =SUBSTITUTE(Virtualo!G10,"-","") -> 9788365156143 | D10: =SUBSTITUTE(Empik!F10,"-","") -> 9788365156457 | E10: =SUBSTITUTE(Publio!H10,"-","") -> 9788365156112 | F10: =VALUE(SUBSTITUTE(Publio!Q10,".",",")) -> 6.28 | G10: =IFERROR(IF(SEARCH("-", Nexto!B10), SUBSTITUTE(Nexto!B10,"-","")), "") | H10: =IFERROR(VALUE(SUBSTITUTE(Nexto!P14,".",",")),0) -> 9.22 | I10: =SUBSTITUTE(Azymut!D10,"-","") | J10: =VALUE(SUBSTITUTE(Azymut!O10,".",",")) -> 0 | K10: =SUBSTITUTE(Ebookpoint!E22,"-","") -> 9788365156389 | L10: =SUBSTITUTE(Nasbi!E22,"-","") | M10: =VALUE(SUBSTITUTE(StorytelE!G10,".",",")) -> 1 | N10: =VALUE(SUBSTITUTE(StorytelA!G10,".",",")) -> 18 | O10: =VALUE(SUBSTITUTE(StorytelE!M10,".",",")) -> 3.6 | P10: =VALUE(SUBSTITUTE(StorytelA!M10,".",",")) -> 29.05 | R10: =VALUE(SUBSTITUTE(Woblink!H22,".",",")) -> 6.23 | S10: =SUBSTITUTE(AzymutB!D10,"-","") | T10: =VALUE(SUBSTITUTE(AzymutB!O10,".",",")) -> 0 | U10: =SUBSTITUTE(Audioteka!Q12,"-","") -> 9788365156846
A11: =SUBSTITUTE(Histmag!B11,"-","") -> 9788365156273 | B11: =VALUE(SUBSTITUTE(Histmag!D11,".",",")) -> 26.07 | C11: =SUBSTITUTE(Virtualo!G11,"-","") -> 9788365156600 | D11: =SUBSTITUTE(Empik!F11,"-","") -> 9788365156792 | E11: =SUBSTITUTE(Publio!H11,"-","") -> 9788365156822 | F11: =VALUE(SUBSTITUTE(Publio!Q11,".",",")) -> 9.66 | G11: =IFERROR(IF(SEARCH("-", Nexto!B11), SUBSTITUTE(Nexto!B11,"-","")), "") -> 9788365156280 | H11: =IFERROR(VALUE(SUBSTITUTE(Nexto!P15,".",",")),0) -> 38.75 | I11: =SUBSTITUTE(Azymut!D11,"-","") | J11: =VALUE(SUBSTITUTE(Azymut!O11,".",",")) -> 0 | K11: =SUBSTITUTE(Ebookpoint!E23,"-","") -> 9788365156389 | L11: =SUBSTITUTE(Nasbi!E23,"-","") | M11: =VALUE(SUBSTITUTE(StorytelE!G11,".",",")) -> 1 | N11: =VALUE(SUBSTITUTE(StorytelA!G11,".",",")) -> 27 | O11: =VALUE(SUBSTITUTE(StorytelE!M11,".",",")) -> 3.59 | P11: =VALUE(SUBSTITUTE(StorytelA!M11,".",",")) -> 37.34 | R11: =VALUE(SUBSTITUTE(Woblink!H23,".",",")) -> 8.51 | S11: =SUBSTITUTE(AzymutB!D11,"-","") | T11: =VALUE(SUBSTITUTE(AzymutB!O11,".",",")) -> 0 | U11: =SUBSTITUTE(Audioteka!Q13,"-","") -> 9788365156730
A12: =SUBSTITUTE(Histmag!B12,"-","") -> 9788393463039 | B12: =VALUE(SUBSTITUTE(Histmag!D12,".",",")) -> 19.94 | C12: =SUBSTITUTE(Virtualo!G12,"-","") -> 9788365156747 | D12: =SUBSTITUTE(Empik!F12,"-","") -> 9788365156310 | E12: =SUBSTITUTE(Publio!H12,"-","") -> 9788365156136 | F12: =VALUE(SUBSTITUTE(Publio!Q12,".",",")) -> 8.51 | G12: =IFERROR(IF(SEARCH("-", Nexto!B12), SUBSTITUTE(Nexto!B12,"-","")), "") -> 9788365156853 | H12: =IFERROR(VALUE(SUBSTITUTE(Nexto!P16,".",",")),0) -> 0 | I12: =SUBSTITUTE(Azymut!D12,"-","") | J12: =VALUE(SUBSTITUTE(Azymut!O12,".",",")) -> 0 | K12: =SUBSTITUTE(Ebookpoint!E24,"-","") -> 9788365156419 | L12: =SUBSTITUTE(Nasbi!E24,"-","") | M12: =VALUE(SUBSTITUTE(StorytelE!G12,".",",")) -> 2 | N12: =VALUE(SUBSTITUTE(StorytelA!G12,".",",")) -> 32 | O12: =VALUE(SUBSTITUTE(StorytelE!M12,".",",")) -> 2.5 | P12: =VALUE(SUBSTITUTE(StorytelA!M12,".",",")) -> 30.16 | R12: =VALUE(SUBSTITUTE(Woblink!H24,".",",")) -> 8.51 | S12: =SUBSTITUTE(AzymutB!D12,"-","") | T12: =VALUE(SUBSTITUTE(AzymutB!O12,".",",")) -> 0 | U12: =SUBSTITUTE(Audioteka!Q14,"-","") -> 9788365156570
A13: =SUBSTITUTE(Histmag!B13,"-","") -> 9788365156310 | B13: =VALUE(SUBSTITUTE(Histmag!D13,".",",")) -> 28.37 | C13: =SUBSTITUTE(Virtualo!G13,"-","") -> 9788365156235 | D13: =SUBSTITUTE(Empik!F13,"-","") -> 9788365156792 | E13: =SUBSTITUTE(Publio!H13,"-","") -> 9788365156389 | F13: =VALUE(SUBSTITUTE(Publio!Q13,".",",")) -> 6.23 | G13: =IFERROR(IF(SEARCH("-", Nexto!B13), SUBSTITUTE(Nexto!B13,"-","")), "") -> 9788365156204 | H13: =IFERROR(VALUE(SUBSTITUTE(Nexto!P17,".",",")),0) -> 0 | I13: =SUBSTITUTE(Azymut!D13,"-","") | J13: =VALUE(SUBSTITUTE(Azymut!O13,".",",")) -> 0 | K13: =SUBSTITUTE(Ebookpoint!E25,"-","") -> 9788365156556 | L13: =SUBSTITUTE(Nasbi!E25,"-","") | M13: =VALUE(SUBSTITUTE(StorytelE!G13,".",",")) -> 1 | N13: =VALUE(SUBSTITUTE(StorytelA!G13,".",",")) -> 42 | O13: =VALUE(SUBSTITUTE(StorytelE!M13,".",",")) -> 1.62 | P13: =VALUE(SUBSTITUTE(StorytelA!M13,".",",")) -> 57.45 | R13: =VALUE(SUBSTITUTE(Woblink!H25,".",",")) -> 8.51 | S13: =SUBSTITUTE(AzymutB!D13,"-","") | T13: =VALUE(SUBSTITUTE(AzymutB!O13,".",",")) -> 0 | U13: =SUBSTITUTE(Audioteka!Q15,"-","") -> 9788365156778
A14: =SUBSTITUTE(Histmag!B14,"-","") -> 9788365156549 | B14: =VALUE(SUBSTITUTE(Histmag!D14,".",",")) -> 28.37 | C14: =SUBSTITUTE(Virtualo!G14,"-","") -> 9788393463091 | D14: =SUBSTITUTE(Empik!F14,"-","") -> 9788365156730 | E14: =SUBSTITUTE(Publio!H14,"-","") -> 9788365156860 | F14: =VALUE(SUBSTITUTE(Publio!Q14,".",",")) -> 11.37 | G14: =IFERROR(IF(SEARCH("-", Nexto!B14), SUBSTITUTE(Nexto!B14,"-","")), "") -> 9788365156211 | H14: =IFERROR(VALUE(SUBSTITUTE(Nexto!P18,".",",")),0) -> 0 | I14: =SUBSTITUTE(Azymut!D14,"-","") | J14: =VALUE(SUBSTITUTE(Azymut!O14,".",",")) -> 0 | K14: =SUBSTITUTE(Ebookpoint!E26,"-","") -> 9788365156556 | L14: =SUBSTITUTE(Nasbi!E26,"-","") | M14: =VALUE(SUBSTITUTE(StorytelE!G14,".",",")) -> 1 | N14: =VALUE(SUBSTITUTE(StorytelA!G14,".",",")) -> 21 | O14: =VALUE(SUBSTITUTE(StorytelE!M14,".",",")) -> 2.52 | P14: =VALUE(SUBSTITUTE(StorytelA!M14,".",",")) -> 40.12 | R14: =VALUE(SUBSTITUTE(Woblink!H26,".",",")) -> 11.37 | S14: =SUBSTITUTE(AzymutB!D14,"-","") | T14: =VALUE(SUBSTITUTE(AzymutB!O14,".",",")) -> 0 | U14: =SUBSTITUTE(Audioteka!Q16,"-","") -> 9788365156853
A15: =SUBSTITUTE(Histmag!B15,"-","") -> 9788365156754 | B15: =VALUE(SUBSTITUTE(Histmag!D15,".",",")) -> 33.99 | C15: =SUBSTITUTE(Virtualo!G15,"-","") -> 9788365156709 | D15: =SUBSTITUTE(Empik!F15,"-","") -> 9788365156730 | E15: =SUBSTITUTE(Publio!H15,"-","") -> 9788365156860 | F15: =VALUE(SUBSTITUTE(Publio!Q15,".",",")) -> 11.37 | G15: =IFERROR(IF(SEARCH("-", Nexto!B15), SUBSTITUTE(Nexto!B15,"-","")), "") | H15: =IFERROR(VALUE(SUBSTITUTE(Nexto!P19,".",",")),0) -> 0 | I15: =SUBSTITUTE(Azymut!D15,"-","") | J15: =VALUE(SUBSTITUTE(Azymut!O15,".",",")) -> 0 | K15: =SUBSTITUTE(Ebookpoint!E27,"-","") -> 9788365156556 | L15: =SUBSTITUTE(Nasbi!E27,"-","") | M15: =VALUE(SUBSTITUTE(StorytelE!G15,".",",")) -> 1 | N15: =VALUE(SUBSTITUTE(StorytelA!G15,".",",")) -> 15 | O15: =VALUE(SUBSTITUTE(StorytelE!M15,".",",")) -> 2.19 | P15: =VALUE(SUBSTITUTE(StorytelA!M15,".",",")) -> 54.2 | R15: =VALUE(SUBSTITUTE(Woblink!H27,".",",")) -> 6.23 | S15: =SUBSTITUTE(AzymutB!D15,"-","") | T15: =VALUE(SUBSTITUTE(AzymutB!O15,".",",")) -> 0 | U15: =SUBSTITUTE(Audioteka!Q17,"-","") -> 9788365156686
A16: =SUBSTITUTE(Histmag!B16,"-","") -> 9788365156358 | B16: =VALUE(SUBSTITUTE(Histmag!D16,".",",")) -> 12.42 | C16: =SUBSTITUTE(Virtualo!G16,"-","") | D16: =SUBSTITUTE(Empik!F16,"-","") -> 9788365156839 | E16: =SUBSTITUTE(Publio!H16,"-","") -> 9788365156860 | F16: =VALUE(SUBSTITUTE(Publio!Q16,".",",")) -> 11.37 | G16: =IFERROR(IF(SEARCH("-", Nexto!B16), SUBSTITUTE(Nexto!B16,"-","")), "") | H16: =IFERROR(VALUE(SUBSTITUTE(Nexto!P20,".",",")),0) -> 0 | I16: =SUBSTITUTE(Azymut!D16,"-","") | J16: =VALUE(SUBSTITUTE(Azymut!O16,".",",")) -> 0 | K16: =SUBSTITUTE(Ebookpoint!E28,"-","") -> 9788365156556 | L16: =SUBSTITUTE(Nasbi!E28,"-","") | M16: =VALUE(SUBSTITUTE(StorytelE!G16,".",",")) -> 1 | N16: =VALUE(SUBSTITUTE(StorytelA!G16,".",",")) -> 35 | O16: =VALUE(SUBSTITUTE(StorytelE!M16,".",",")) -> 2.37 | P16: =VALUE(SUBSTITUTE(StorytelA!M16,".",",")) -> 62.85 | R16: =VALUE(SUBSTITUTE(Woblink!H28,".",",")) -> 0 | S16: =SUBSTITUTE(AzymutB!D16,"-","") | T16: =VALUE(SUBSTITUTE(AzymutB!O16,".",",")) -> 0 | U16: =SUBSTITUTE(Audioteka!Q18,"-","") -> 9788365156853
A17: =SUBSTITUTE(Histmag!B17,"-","") -> 9788362329984 | B17: =VALUE(SUBSTITUTE(Histmag!D17,".",",")) -> 13.14 | C17: =SUBSTITUTE(Virtualo!G17,"-","") | D17: =SUBSTITUTE(Empik!F17,"-","") -> 9788365156839 | E17: =SUBSTITUTE(Publio!H17,"-","") -> 9788365156860 | F17: =VALUE(SUBSTITUTE(Publio!Q17,".",",")) -> 11.37 | G17: =IFERROR(IF(SEARCH("-", Nexto!B17), SUBSTITUTE(Nexto!B17,"-","")), "") | H17: =IFERROR(VALUE(SUBSTITUTE(Nexto!P21,".",",")),0) -> 0 | I17: =SUBSTITUTE(Azymut!D17,"-","") | J17: =VALUE(SUBSTITUTE(Azymut!O17,".",",")) -> 0 | K17: =SUBSTITUTE(Ebookpoint!E29,"-","") -> 9788365156556 | L17: =SUBSTITUTE(Nasbi!E29,"-","") | M17: =VALUE(SUBSTITUTE(StorytelE!G17,".",",")) -> 7 | N17: =VALUE(SUBSTITUTE(StorytelA!G17,".",",")) -> 43 | O17: =VALUE(SUBSTITUTE(StorytelE!M17,".",",")) -> 16.82 | P17: =VALUE(SUBSTITUTE(StorytelA!M17,".",",")) -> 57.96 | R17: =VALUE(SUBSTITUTE(Woblink!H29,".",",")) -> 0 | S17: =SUBSTITUTE(AzymutB!D17,"-","") | T17: =VALUE(SUBSTITUTE(AzymutB!O17,".",",")) -> 0 | U17: =SUBSTITUTE(Audioteka!Q19,"-","") -> 9788365156808
A18: =SUBSTITUTE(Histmag!B18,"-","") -> 9788365156006 | B18: =VALUE(SUBSTITUTE(Histmag!D18,".",",")) -> 9.8 | C18: =SUBSTITUTE(Virtualo!G18,"-","") | D18: =SUBSTITUTE(Empik!F18,"-","") -> 9788365156129 | E18: =SUBSTITUTE(Publio!H18,"-","") -> 9788365156860 | F18: =VALUE(SUBSTITUTE(Publio!Q18,".",",")) -> 11.37 | G18: =IFERROR(IF(SEARCH("-", Nexto!B18), SUBSTITUTE(Nexto!B18,"-","")), "") | H18: =IFERROR(VALUE(SUBSTITUTE(Nexto!P22,".",",")),0) -> 0 | I18: =SUBSTITUTE(Azymut!D18,"-","") | J18: =VALUE(SUBSTITUTE(Azymut!O18,".",",")) -> 0 | K18: =SUBSTITUTE(Ebookpoint!E30,"-","") -> 9788365156556 | L18: =SUBSTITUTE(Nasbi!E30,"-","") | M18: =VALUE(SUBSTITUTE(StorytelE!G18,".",",")) -> 3 | N18: =VALUE(SUBSTITUTE(StorytelA!G18,".",",")) -> 22 | O18: =VALUE(SUBSTITUTE(StorytelE!M18,".",",")) -> 8.38 | P18: =VALUE(SUBSTITUTE(StorytelA!M18,".",",")) -> 49.71 | R18: =VALUE(SUBSTITUTE(Woblink!H30,".",",")) -> 0 | S18: =SUBSTITUTE(AzymutB!D18,"-","") | T18: =VALUE(SUBSTITUTE(AzymutB!O18,".",",")) -> 0 | U18: =SUBSTITUTE(Audioteka!Q20,"-","") -> 9788365156853
... A26: =SUBSTITUTE(Histmag!B26,"-","") -> 9788365156433 | B26: =VALUE(SUBSTITUTE(Histmag!D26,".",",")) -> 22.66 | C26: =SUBSTITUTE(Virtualo!G26,"-","") | D26: =SUBSTITUTE(Empik!F26,"-","") -> 9788365156570 | E26: =SUBSTITUTE(Publio!H26,"-","") | F26: =VALUE(SUBSTITUTE(Publio!Q26,".",",")) -> 0 | G26: =IFERROR(IF(SEARCH("-", Nexto!B26), SUBSTITUTE(Nexto!B26,"-","")), "") | H26: =IFERROR(VALUE(SUBSTITUTE(Nexto!P30,".",",")),0) -> 0 | I26: =SUBSTITUTE(Azymut!D26,"-","") | J26: =VALUE(SUBSTITUTE(Azymut!O26,".",",")) -> 0 | K26: =SUBSTITUTE(Ebookpoint!E38,"-","") -> 9788365156754 | L26: =SUBSTITUTE(Nasbi!E38,"-","") | M26: =VALUE(SUBSTITUTE(StorytelE!G26,".",",")) -> 0 | N26: =VALUE(SUBSTITUTE(StorytelA!G26,".",",")) -> 0 | O26: =VALUE(SUBSTITUTE(StorytelE!M26,".",",")) -> 0 | P26: =VALUE(SUBSTITUTE(StorytelA!M26,".",",")) -> 0 | R26: =VALUE(SUBSTITUTE(Woblink!H38,".",",")) -> 0 | S26: =SUBSTITUTE(AzymutB!D26,"-","") | T26: =VALUE(SUBSTITUTE(AzymutB!O26,".",",")) -> 0 | U26: =SUBSTITUTE(Audioteka!Q28,"-","")
A27: =SUBSTITUTE(Histmag!B27,"-","") -> 9788365156570 | B27: =VALUE(SUBSTITUTE(Histmag!D27,".",",")) -> 23.42 | C27: =SUBSTITUTE(Virtualo!G27,"-","") | D27: =SUBSTITUTE(Empik!F27,"-","") -> 9788365156853 | E27: =SUBSTITUTE(Publio!H27,"-","") | F27: =VALUE(SUBSTITUTE(Publio!Q27,".",",")) -> 0 | G27: =IFERROR(IF(SEARCH("-", Nexto!B27), SUBSTITUTE(Nexto!B27,"-","")), "") | H27: =IFERROR(VALUE(SUBSTITUTE(#REF!,".",",")),0) -> 0 | I27: =SUBSTITUTE(Azymut!D27,"-","") | J27: =VALUE(SUBSTITUTE(Azymut!O27,".",",")) -> 0 | K27: =SUBSTITUTE(Ebookpoint!E39,"-","") -> 9788365156785 | L27: =SUBSTITUTE(Nasbi!E39,"-","") | M27: =VALUE(SUBSTITUTE(StorytelE!G27,".",",")) -> 0 | N27: =VALUE(SUBSTITUTE(StorytelA!G27,".",",")) -> 0 | O27: =VALUE(SUBSTITUTE(StorytelE!M27,".",",")) -> 0 | P27: =VALUE(SUBSTITUTE(StorytelA!M27,".",",")) -> 0 | R27: =VALUE(SUBSTITUTE(Woblink!H39,".",",")) -> 0 | S27: =SUBSTITUTE(AzymutB!D27,"-","") | T27: =VALUE(SUBSTITUTE(AzymutB!O27,".",",")) -> 0 | U27: =SUBSTITUTE(Audioteka!Q29,"-","")
A28: =SUBSTITUTE(Histmag!B28,"-","") -> 9788365156587 | B28: =VALUE(SUBSTITUTE(Histmag!D28,".",",")) -> 18.44 | C28: =SUBSTITUTE(Virtualo!G28,"-","") | D28: =SUBSTITUTE(Empik!F28,"-","") -> 9788365156747 | E28: =SUBSTITUTE(Publio!H28,"-","") | F28: =VALUE(SUBSTITUTE(Publio!Q28,".",",")) -> 0 | G28: =IFERROR(IF(SEARCH("-", Nexto!B28), SUBSTITUTE(Nexto!B28,"-","")), "") | H28: =IFERROR(VALUE(SUBSTITUTE(#REF!,".",",")),0) -> 0 | I28: =SUBSTITUTE(Azymut!D28,"-","") | J28: =VALUE(SUBSTITUTE(Azymut!O28,".",",")) -> 0 | K28: =SUBSTITUTE(Ebookpoint!E40,"-","") -> 9788365156815 | L28: =SUBSTITUTE(Nasbi!E40,"-","") | M28: =VALUE(SUBSTITUTE(StorytelE!G28,".",",")) -> 0 | N28: =VALUE(SUBSTITUTE(StorytelA!G28,".",",")) -> 0 | O28: =VALUE(SUBSTITUTE(StorytelE!M28,".",",")) -> 0 | P28: =VALUE(SUBSTITUTE(StorytelA!M28,".",",")) -> 0 | R28: =VALUE(SUBSTITUTE(Woblink!H40,".",",")) -> 0 | S28: =SUBSTITUTE(AzymutB!D28,"-","") | T28: =VALUE(SUBSTITUTE(AzymutB!O28,".",",")) -> 0 | U28: =SUBSTITUTE(Audioteka!Q30,"-","")
A29: =SUBSTITUTE(Histmag!B29,"-","") -> 9788365156709 | B29: =VALUE(SUBSTITUTE(Histmag!D29,".",",")) -> 12.42 | C29: =SUBSTITUTE(Virtualo!G29,"-","") | D29: =SUBSTITUTE(Empik!F29,"-","") -> 9788365156747 | E29: =SUBSTITUTE(Publio!H29,"-","") | F29: =VALUE(SUBSTITUTE(Publio!Q29,".",",")) -> 0 | G29: =IFERROR(IF(SEARCH("-", Nexto!B29), SUBSTITUTE(Nexto!B29,"-","")), "") | H29: =IFERROR(VALUE(SUBSTITUTE(#REF!,".",",")),0) -> 0 | I29: =SUBSTITUTE(Azymut!D29,"-","") | J29: =VALUE(SUBSTITUTE(Azymut!O29,".",",")) -> 0 | K29: =SUBSTITUTE(Ebookpoint!E41,"-","") -> 9788365156815 | L29: =SUBSTITUTE(Nasbi!E41,"-","") | M29: =VALUE(SUBSTITUTE(StorytelE!G29,".",",")) -> 0 | N29: =VALUE(SUBSTITUTE(StorytelA!G29,".",",")) -> 0 | O29: =VALUE(SUBSTITUTE(StorytelE!M29,".",",")) -> 0 | P29: =VALUE(SUBSTITUTE(StorytelA!M29,".",",")) -> 0 | R29: =VALUE(SUBSTITUTE(Woblink!H41,".",",")) -> 0 | S29: =SUBSTITUTE(AzymutB!D29,"-","") | T29: =VALUE(SUBSTITUTE(AzymutB!O29,".",",")) -> 0 | U29: =SUBSTITUTE(Audioteka!Q31,"-","")
A30: =SUBSTITUTE(Histmag!B30,"-","") -> 9788365156846 | B30: =VALUE(SUBSTITUTE(Histmag!D30,".",",")) -> 15.56 | C30: =SUBSTITUTE(Virtualo!G30,"-","") | D30: =SUBSTITUTE(Empik!F30,"-","") -> 9788365156846 | E30: =SUBSTITUTE(Publio!H30,"-","") | F30: =VALUE(SUBSTITUTE(Publio!Q30,".",",")) -> 0 | G30: =IFERROR(IF(SEARCH("-", Nexto!B30), SUBSTITUTE(Nexto!B30,"-","")), "") | H30: =IFERROR(VALUE(SUBSTITUTE(#REF!,".",",")),0) -> 0 | I30: =SUBSTITUTE(Azymut!D30,"-","") | J30: =VALUE(SUBSTITUTE(Azymut!O30,".",",")) -> 0 | K30: =SUBSTITUTE(Ebookpoint!E42,"-","") -> 9788365156815 | L30: =SUBSTITUTE(Nasbi!E42,"-","") | M30: =VALUE(SUBSTITUTE(StorytelE!G30,".",",")) -> 0 | N30: =VALUE(SUBSTITUTE(StorytelA!G30,".",",")) -> 0 | O30: =VALUE(SUBSTITUTE(StorytelE!M30,".",",")) -> 0 | P30: =VALUE(SUBSTITUTE(StorytelA!M30,".",",")) -> 0 | R30: =VALUE(SUBSTITUTE(Woblink!H42,".",",")) -> 0 | S30: =SUBSTITUTE(AzymutB!D30,"-","") | T30: =VALUE(SUBSTITUTE(AzymutB!O30,".",",")) -> 0 | U30: =SUBSTITUTE(Audioteka!Q32,"-","")
A31: =SUBSTITUTE(Histmag!B31,"-","") -> 9788365156303 | B31: =VALUE(SUBSTITUTE(Histmag!D31,".",",")) -> 10.46 | C31: =SUBSTITUTE(Virtualo!G31,"-","") | D31: =SUBSTITUTE(Empik!F31,"-","") -> 9788365156846 | E31: =SUBSTITUTE(Publio!H31,"-","") | F31: =VALUE(SUBSTITUTE(Publio!Q31,".",",")) -> 0 | G31: =IFERROR(IF(SEARCH("-", #REF!), SUBSTITUTE(#REF!,"-","")), "") | H31: =IFERROR(VALUE(SUBSTITUTE(#REF!,".",",")),0) -> 0 | I31: =SUBSTITUTE(Azymut!D31,"-","") | J31: =VALUE(SUBSTITUTE(Azymut!O31,".",",")) -> 0 | K31: =SUBSTITUTE(Ebookpoint!E43,"-","") -> 9788365156815 | L31: =SUBSTITUTE(Nasbi!E43,"-","") | M31: =VALUE(SUBSTITUTE(StorytelE!G31,".",",")) -> 0 | N31: =VALUE(SUBSTITUTE(StorytelA!G31,".",",")) -> 0 | O31: =VALUE(SUBSTITUTE(StorytelE!M31,".",",")) -> 0 | P31: =VALUE(SUBSTITUTE(StorytelA!M31,".",",")) -> 0 | R31: =VALUE(SUBSTITUTE(Woblink!H43,".",",")) -> 0 | S31: =SUBSTITUTE(AzymutB!D31,"-","") | T31: =VALUE(SUBSTITUTE(AzymutB!O31,".",",")) -> 0 | U31: =SUBSTITUTE(Audioteka!Q33,"-","")
A32: =SUBSTITUTE(Histmag!B32,"-","") -> 9788365156334 | B32: =VALUE(SUBSTITUTE(Histmag!D32,".",",")) -> 4.9 | C32: =SUBSTITUTE(Virtualo!G32,"-","") | D32: =SUBSTITUTE(Empik!F32,"-","") -> 9788365156846 | E32: =SUBSTITUTE(Publio!H32,"-","") | F32: =VALUE(SUBSTITUTE(Publio!Q32,".",",")) -> 0 | G32: =IFERROR(IF(SEARCH("-", #REF!), SUBSTITUTE(#REF!,"-","")), "") | H32: =IFERROR(VALUE(SUBSTITUTE(#REF!,".",",")),0) -> 0 | I32: =SUBSTITUTE(Azymut!D32,"-","") | J32: =VALUE(SUBSTITUTE(Azymut!O32,".",",")) -> 0 | K32: =SUBSTITUTE(Ebookpoint!E44,"-","") -> 9788365156822 | L32: =SUBSTITUTE(Nasbi!E44,"-","") | M32: =VALUE(SUBSTITUTE(StorytelE!G32,".",",")) -> 0 | N32: =VALUE(SUBSTITUTE(StorytelA!G32,".",",")) -> 0 | O32: =VALUE(SUBSTITUTE(StorytelE!M32,".",",")) -> 0 | P32: =VALUE(SUBSTITUTE(StorytelA!M32,".",",")) -> 0 | R32: =VALUE(SUBSTITUTE(Woblink!H44,".",",")) -> 0 | S32: =SUBSTITUTE(AzymutB!D32,"-","") | T32: =VALUE(SUBSTITUTE(AzymutB!O32,".",",")) -> 0 | U32: =SUBSTITUTE(Audioteka!Q34,"-","")
A33: =SUBSTITUTE(Histmag!B33,"-","") -> 9788365156211 | B33: =VALUE(SUBSTITUTE(Histmag!D33,".",",")) -> 7.93 | C33: =SUBSTITUTE(Virtualo!G33,"-","") | D33: =SUBSTITUTE(Empik!F33,"-","") -> 9788365156709 | E33: =SUBSTITUTE(Publio!H33,"-","") | F33: =VALUE(SUBSTITUTE(Publio!Q33,".",",")) -> 0 | G33: =IFERROR(IF(SEARCH("-", #REF!), SUBSTITUTE(#REF!,"-","")), "") | H33: =IFERROR(VALUE(SUBSTITUTE(#REF!,".",",")),0) -> 0 | I33: =SUBSTITUTE(Azymut!D33,"-","") | J33: =VALUE(SUBSTITUTE(Azymut!O33,".",",")) -> 0 | K33: =SUBSTITUTE(Ebookpoint!E45,"-","") -> 9788365156822 | L33: =SUBSTITUTE(Nasbi!E45,"-","") | M33: =VALUE(SUBSTITUTE(StorytelE!G33,".",",")) -> 0 | N33: =VALUE(SUBSTITUTE(StorytelA!G33,".",",")) -> 0 | O33: =VALUE(SUBSTITUTE(StorytelE!M33,".",",")) -> 0 | P33: =VALUE(SUBSTITUTE(StorytelA!M33,".",",")) -> 0 | R33: =VALUE(SUBSTITUTE(Woblink!H45,".",",")) -> 0 | S33: =SUBSTITUTE(AzymutB!D33,"-","") | T33: =VALUE(SUBSTITUTE(AzymutB!O33,".",",")) -> 0 | U33: =SUBSTITUTE(Audioteka!Q35,"-","")
A34: =SUBSTITUTE(Histmag!B34,"-","") -> 9788365156280 | B34: =VALUE(SUBSTITUTE(Histmag!D34,".",",")) -> 7.93 | C34: =SUBSTITUTE(Virtualo!G34,"-","") | D34: =SUBSTITUTE(Empik!F34,"-","") -> 9788365156709 | E34: =SUBSTITUTE(Publio!H34,"-","") | F34: =VALUE(SUBSTITUTE(Publio!Q34,".",",")) -> 0 | G34: =IFERROR(IF(SEARCH("-", #REF!), SUBSTITUTE(#REF!,"-","")), "") | H34: =IFERROR(VALUE(SUBSTITUTE(#REF!,".",",")),0) -> 0 | I34: =SUBSTITUTE(Azymut!D34,"-","") | J34: =VALUE(SUBSTITUTE(Azymut!O34,".",",")) -> 0 | K34: =SUBSTITUTE(Ebookpoint!E46,"-","") -> 9788365156822 | L34: =SUBSTITUTE(Nasbi!E46,"-","") | M34: =VALUE(SUBSTITUTE(StorytelE!G34,".",",")) -> 0 | N34: =VALUE(SUBSTITUTE(StorytelA!G34,".",",")) -> 0 | O34: =VALUE(SUBSTITUTE(StorytelE!M34,".",",")) -> 0 | P34: =VALUE(SUBSTITUTE(StorytelA!M34,".",",")) -> 0 | R34: =VALUE(SUBSTITUTE(Woblink!H46,".",",")) -> 0 | S34: =SUBSTITUTE(AzymutB!D34,"-","") | T34: =VALUE(SUBSTITUTE(AzymutB!O34,".",",")) -> 0 | U34: =SUBSTITUTE(Audioteka!Q36,"-","")
A35: =SUBSTITUTE(Histmag!B35,"-","") -> 9788393463022 | B35: =VALUE(SUBSTITUTE(Histmag!D35,".",",")) -> 4.28 | C35: =SUBSTITUTE(Virtualo!G35,"-","") | D35: =SUBSTITUTE(Empik!F35,"-","") -> 9788365156648 | E35: =SUBSTITUTE(Publio!H35,"-","") | F35: =VALUE(SUBSTITUTE(Publio!Q35,".",",")) -> 0 | G35: =IFERROR(IF(SEARCH("-", #REF!), SUBSTITUTE(#REF!,"-","")), "") | H35: =IFERROR(VALUE(SUBSTITUTE(#REF!,".",",")),0) -> 0 | I35: =SUBSTITUTE(Azymut!D35,"-","") | J35: =VALUE(SUBSTITUTE(Azymut!O35,".",",")) -> 0 | K35: =SUBSTITUTE(Ebookpoint!E47,"-","") -> 9788365156822 | L35: =SUBSTITUTE(Nasbi!E47,"-","") | M35: =VALUE(SUBSTITUTE(StorytelE!G35,".",",")) -> 0 | N35: =VALUE(SUBSTITUTE(StorytelA!G35,".",",")) -> 0 | O35: =VALUE(SUBSTITUTE(StorytelE!M35,".",",")) -> 0 | P35: =VALUE(SUBSTITUTE(StorytelA!M35,".",",")) -> 0 | R35: =VALUE(SUBSTITUTE(Woblink!H47,".",",")) -> 0 | S35: =SUBSTITUTE(AzymutB!D35,"-","") | T35: =VALUE(SUBSTITUTE(AzymutB!O35,".",",")) -> 0 | U35: =SUBSTITUTE(Audioteka!Q37,"-","")
A36: =SUBSTITUTE(Histmag!B36,"-","") -> 9788365156051 | B36: =VALUE(SUBSTITUTE(Histmag!D36,".",",")) -> 11.33 | C36: =SUBSTITUTE(Virtualo!G36,"-","") | D36: =SUBSTITUTE(Empik!F36,"-","") -> 9788365156648 | E36: =SUBSTITUTE(Publio!H36,"-","") | F36: =VALUE(SUBSTITUTE(Publio!Q36,".",",")) -> 0 | G36: =IFERROR(IF(SEARCH("-", #REF!), SUBSTITUTE(#REF!,"-","")), "") | H36: =IFERROR(VALUE(SUBSTITUTE(#REF!,".",",")),0) -> 0 | I36: =SUBSTITUTE(Azymut!D36,"-","") | J36: =VALUE(SUBSTITUTE(Azymut!O36,".",",")) -> 0 | K36: =SUBSTITUTE(Ebookpoint!E48,"-","") -> 9788365156846 | L36: =SUBSTITUTE(Nasbi!E48,"-","") | M36: =VALUE(SUBSTITUTE(StorytelE!G36,".",",")) -> 0 | N36: =VALUE(SUBSTITUTE(StorytelA!G36,".",",")) -> 0 | O36: =VALUE(SUBSTITUTE(StorytelE!M36,".",",")) -> 0 | P36: =VALUE(SUBSTITUTE(StorytelA!M36,".",",")) -> 0 | R36: =VALUE(SUBSTITUTE(Woblink!H48,".",",")) -> 0 | S36: =SUBSTITUTE(AzymutB!D36,"-","") | T36: =VALUE(SUBSTITUTE(AzymutB!O36,".",",")) -> 0 | U36: =SUBSTITUTE(Audioteka!Q38,"-","")
